Workbook
Name _: #REF!
Name __: #REF!
Name ____: #REF!
Name _______A70000: #REF!
Name _______A80000: #REF!
Name _______sh1: #REF!
Name _______SP14: #REF!
Name _______SP15: #REF!
Name _______SP16: #REF!
Name _______SP17: #REF!
Name _______SP18: #REF!
Name _______SP19: #REF!
Name _______SP2: #REF!
Name _______SP20: #REF!
Name _______SP3: #REF!
Name _______SP4: #REF!
Name _______SP5: #REF!
Name _______SP7: #REF!
Name _______SP8: #REF!
Name _______SP9: #REF!
Name ______A70000: #REF!
Name ______A80000: #REF!
Name ______DAT1: #REF!
Name ______DAT10: #REF!
Name ______DAT2: #REF!
Name ______DAT3: #REF!
Name ______DAT4: #REF!
Name ______DAT5: #REF!
Name ______DAT6: #REF!
Name ______DAT7: #REF!
Name ______DAT8: #REF!
Name ______DAT9: #REF!
Name ______END1: #REF!
Name ______END2: #REF!
Name ______END4: #REF!
Name ______END6: #REF!
Name ______END7: #REF!
Name ______IV65900: #REF!
Name ______IV66000: #REF!
Name ______IV69000: #REF!
Name ______IV70000: #REF!
Name ______JA1: #REF!
Name ______KA1: #REF!
Name ______LA1: #REF!
Name ______lp280202: #REF!
Name ______MIF1: #REF!
Name ______MIF2: #REF!
Name ______MIF3: #REF!
Name ______MO33: #REF!
Name ______MO34: #REF!
Name ______MO35: #REF!
Name ______MO36: #REF!
Name ______MO37: #REF!
Name ______MO38: #REF!
Name ______MO39: #REF!
Name ______MO40: #REF!
Name ______MO41: #REF!
Name ______MO42: #REF!
Name ______MO43: #REF!
Name ______MO44: #REF!

Sheet Output
B2: Общие показатели проекта Model Farm Zhailau
A4: х | B4: Ключевые допущения
A6: 1 | B6: Проект финансируется АКК в рамках Национальной программы развития животноводства по целевому назначению: строительство инфраструктуры, закуп маточного поголовья и быков-производителей (долгосрочные займы) и финансирование оборотного капитала (закуп кормов, чипов, прочих расходников, оплата ФОТ пастухам, обязательное страхование). Финансирование оборотного капитала необходимо в течение срока реализации проекта, со сроком погашения - 2 года.
B7: Общая стомость проекта
E8: 1ый год | F8: 2ой год
B9: Капитальные затраты | D9: тыс. тенге | E9: =SUM(E10:E12) -> 302465.15 | F9: =SUM(F10:F12) -> 0
C10: ='Operating Model'!C17 -> Предварительные расходы | D10: тыс. тенге | E10: ='Operating Model'!F17 -> 20000 | F10: ='Operating Model'!G17 -> 0
C11: ='Operating Model'!C18 -> Строительство зданий и инфраструктура | D11: тыс. тенге | E11: ='Operating Model'!F18 -> 224825.15 | F11: ='Operating Model'!G18 -> 0
C12: ='Operating Model'!C19 -> Спецтехника и оборудование | D12: тыс. тенге | E12: ='Operating Model'!F19 -> 57640 | F12: ='Operating Model'!G19 -> 0
B13: Закуп стада | D13: тыс. тенге | E13: =SUM(E14:E16) -> 119100 | F13: =SUM(F14:F16) -> 0
C14: ='Operating Model'!C22 -> Маточное поголовье | D14: тыс. тенге | E14: ='Operating Model'!F22 -> 110000 | F14: ='Operating Model'!G22 -> 0
C15: ='Operating Model'!C23 -> Быки-проивзодители | D15: тыс. тенге | E15: ='Operating Model'!F23 -> 9100 | F15: ='Operating Model'!G23 -> 0
C16: ='Operating Model'!C24 -> Закуп товарного стада | D16: тыс. тенге | E16: ='Operating Model'!F24 -> 0 | F16: ='Operating Model'!G24 -> 0
B17: Итого долгосрочные инвестиции | D17: тыс. тенге | E17: =E9+E13 -> 421565.15 | F17: =F9+F13 -> 0
B18: Оборотный капитал (первые 2 года) | D18: тыс. тенге | E18: ='Operating Model'!F26 -> 56436.079 | F18: ='Operating Model'!G26 -> 0
B19: Итого стоимость проекта | D19: тыс. тенге | E19: =SUM(E17,E18) -> 478001.22 | F19: =SUM(F17,F18) -> 0
B22: Условия по займам | E22: Большая Ферма
B23: Инвестиционный займ
B24: Сумма | D24: тыс. тенге | E24: ='Operating Model'!AL9 -> 379408.63
B25: Ставка | D25: % | E25: =Loans!E4 -> 0.05
B26: Срок | D26: лет | E26: =Loans!E5 -> 10
B28: Оборотный займ | E28: =E71 -> 2026 | F28: =F71 -> 2027 | G28: =G71 -> 2028 | H28: =H71 -> 2029 | I28: =I71 -> 2030 | J28: =J71 -> 2031 | K28: =K71 -> 2032 | L28: =L71 -> 2033 | ... O28: =O71 -> 2036
B29: Сумма | D29: тыс. тенге | E29: =E46 -> 16062.139 | F29: =F46 -> 33048.538 | G29: =G46 -> 39510.59 | H29: =H46 -> 91478.45 | I29: =I46 -> 107743.92 | J29: =J46 -> 116731.42 | K29: =K46 -> 125873.93 | L29: =L46 -> 134423.33 | ... O29: =O46 -> 0
B30: Ставка | D30: % | E30: ='Operating Model'!E305 -> 0.06
B31: Срок | D31: лет | E31: ='Operating Model'!E313 -> 2 | S31: =100/20 -> 5
A33: 3 | B33: Залоговое обеспечение
B35: Этап 1 (при финансировании)
C36: Требования программы (15% от суммы займа) | D36: тыс. тенге | E36: =E24*F36 -> 56911.295 | F36: 0.15 | G36: коэффициент покрытия
C37: Залог денег | D37: тыс. тенге | E37: ='Operating Model'!AQ10 -> 0 | F37: =E37/F61 -> 0
B39: Этап 2 (высвобождение денег и оформление твердых залогов)
C40: Наличие твердых залогов (недвижимость) | D40: тыс. тенге | E40: =E56 -> 224825.15 | F40: =E40/F61 -> 0.59256729
C41: Твердые активы в залог | D41: тыс. тенге | E41: =F61*F36 -> 56911.295
C42: Необремененные твердые залоги | D42: тыс. тенге | E42: =E40-E41 -> 167913.85
A44: 4 | B44: Формирование оборотного капитала и займы на оборотку
E45: =E28 -> 2026 | F45: =F28 -> 2027 | G45: =G28 -> 2028 | H45: =H28 -> 2029 | I45: =I28 -> 2030 | J45: =J28 -> 2031 | K45: =K28 -> 2032 | L45: =L28 -> 2033 | ... O45: =O28 -> 2036
B46: Потребность в оборотном капитале | D46: тыс. тенге | E46: ='Operating Model'!AI308 -> 16062.139 | F46: ='Operating Model'!AJ308 -> 33048.538 | G46: ='Operating Model'!AK308 -> 39510.59 | H46: ='Operating Model'!AL308 -> 91478.45 | I46: ='Operating Model'!AM308 -> 107743.92 | J46: ='Operating Model'!AN308 -> 116731.42 | K46: ='Operating Model'!AO308 -> 125873.93 | L46: ='Operating Model'!AP308 -> 134423.33 | ... O46: ='Operating Model'!AS308 -> 0
B47: Необремененные твердые залоги | D47: тыс. тенге | E47: =E42 -> 167913.85 | F47: =E47 -> 167913.85 | G47: =F47 -> 167913.85 | H47: =G47 -> 167913.85 | I47: =H47 -> 167913.85 | J47: =I47 -> 167913.85
B48: Деньги на депозите | D48: тыс. тенге | E48: =E37-H61 -> -42156.515 | F48: =E48 -> -42156.515 | G48: =F48 -> -42156.515 | H48: =G48 -> -42156.515 | I48: =H48 -> -42156.515 | J48: =I48 -> -42156.515
B49: Займы покрываются (да - 1/нет - 0) | E49: =IF(SUM(E47:E48)>E46,1,0) -> 1 | F49: =IF(SUM(F47:F48)>F46,1,0) -> 1 | G49: =IF(SUM(G47:G48)>G46,1,0) -> 1 | H49: =IF(SUM(H47:H48)>H46,1,0) -> 1 | I49: =IF(SUM(I47:I48)>I46,1,0) -> 1 | J49: =IF(SUM(J47:J48)>J46,1,0) -> 1
B50: Займы покрываются (%) | D50: % | E50: =SUM(E48+E47)/E46-1 -> 6.8294262 | F50: =SUM(F48+F47)/F46-1 -> 2.8052314 | G50: =SUM(G48+G47)/G46-1 -> 2.1828767 | H50: =SUM(H48+H47)/H46-1 -> 0.37472089 | I50: =SUM(I48+I47)/I46-1 -> 0.16718733 | J50: =SUM(J48+J47)/J46-1 -> 0.077322065
A52: 3 | B52: Таким образом суммарные затраты на реализацию проекта будут выглядеть следующим образом:
C53: Наименование | E53: Всего | F53: Структура финансирования
F54: Займ АКК | G54: Доля, % | H54: Собственное участие | I54: Доля, %
C55: =C10 -> Предварительные расходы | D55: тыс. тенге | E55: =E10+F10 -> 20000 | F55: =E55-H55 -> 0 | G55: =F55/E55 -> 0 | H55: =E55 -> 20000 | I55: =H55/E55 -> 1
C56: Строительство инфраструктуры | D56: тыс. тенге | E56: =E11+F11 -> 224825.15 | F56: =E56-H56 -> 224825.15 | G56: =F56/E56 -> 1 | H56: 0 | I56: =H56/E56 -> 0 | V56: 0.1 | W56: 0.1
C57: Спецтехника и оборудование фермеров | D57: тыс. тенге | E57: =E12+F12 -> 57640 | F57: =E57-H57 -> 51876 | G57: =F57/E57 -> 0.9 | H57: =E57*$V$56 -> 5764 | I57: =H57/E57 -> 0.1
C58: Закуп маточного поголовья | D58: тыс. тенге | E58: =E14+F14 -> 110000 | F58: =E58-H58 -> 94517.485 | G58: =F58/E58 -> 0.85924987 | H58: =H61-SUM(H55:H57)-H59 -> 15482.515 | I58: =H58/E58 -> 0.14075013
C59: Закуп быков производителей | D59: тыс. тенге | E59: =E15+F15 -> 9100 | F59: =E59-H59 -> 8190 | G59: =F59/E59 -> 0.9 | H59: =E59*$V$56 -> 910 | I59: =H59/E59 -> 0.1
C60: Закуп товарного стада | D60: тыс. тенге | E60: =E16 -> 0 | F60: =E60-H60 -> 0 | G60: =IFERROR(F60/E60,0) -> 0 | H60: =E60*$V$56 -> 0 | I60: =IFERROR(H60/E60,0) -> 0
C61: Итого долгосрочные инвестиции | D61: тыс. тенге | E61: =SUM(E55:E60) -> 421565.15 | F61: =SUM(F55:F60) -> 379408.63 | G61: =F61/E61 -> 0.9 | H61: =E61*I61 -> 42156.515 | I61: 0.1 | J61: =F61*15% -> 56911.295
C63: Оборотный капитал | D63: тыс. тенге | E63: =E18 -> 56436.079 | F63: =E63-H63 -> 35357.822 | G63: =F63/E63 -> 0.62651096 | H63: =Input!F39-Output!H61 -> 21078.257 | I63: =H63/E63 -> 0.37348904
C65: Итого стоимость проекта | D65: тыс. тенге | E65: =E61+E63 -> 478001.22 | F65: =F61+F63 -> 414766.45 | G65: =F65/E65 -> 0.86771002 | H65: =H61+H63 -> 63234.772 | I65: =H65/E65 -> 0.13228998 | J65: =F65*15% -> 62214.968
A70: х | B70: Движение скота
E71: ='Operating Model'!AI38 -> 2026 | F71: ='Operating Model'!AJ38 -> 2027 | G71: ='Operating Model'!AK38 -> 2028 | H71: ='Operating Model'!AL38 -> 2029 | I71: ='Operating Model'!AM38 -> 2030 | J71: ='Operating Model'!AN38 -> 2031 | K71: ='Operating Model'!AO38 -> 2032 | L71: ='Operating Model'!AP38 -> 2033 | ... O71: ='Operating Model'!AS38 -> 2036
B72: Мощность репродуктора | D72: голов | E72: ='Operating Model'!AI41 -> 300 | F72: ='Operating Model'!AJ41 -> 300 | G72: ='Operating Model'!AK41 -> 300 | H72: ='Operating Model'!AL41 -> 300 | I72: ='Operating Model'!AM41 -> 300 | J72: ='Operating Model'!AN41 -> 300 | K72: ='Operating Model'!AO41 -> 300 | L72: ='Operating Model'!AP41 -> 300 | ... O72: ='Operating Model'!AS41 -> 300
B74: Маточное поголовье к.п. | D74: голов | E74: =SUM('Operating Model'!AI57) -> 198.00749 | F74: =SUM('Operating Model'!AJ57) -> 163.25379 | G74: =SUM('Operating Model'!AK57) -> 201.16948 | H74: =SUM('Operating Model'!AL57) -> 247.89109 | I74: =SUM('Operating Model'!AM57) -> 300 | J74: =SUM('Operating Model'!AN57) -> 300 | K74: =SUM('Operating Model'!AO57) -> 300 | L74: =SUM('Operating Model'!AP57) -> 300 | ... O74: =SUM('Operating Model'!AS57) -> 300
B75: Быки-производители на к.п. | D75: голов | E75: ='Operating Model'!AI66 -> 14 | F75: ='Operating Model'!AJ66 -> 14 | G75: ='Operating Model'!AK66 -> 10.883586 | H75: ='Operating Model'!AL66 -> 13.411299 | I75: ='Operating Model'!AM66 -> 16.526073 | J75: ='Operating Model'!AN66 -> 20 | K75: ='Operating Model'!AO66 -> 20 | L75: ='Operating Model'!AP66 -> 20 | ... O75: ='Operating Model'!AS66 -> 20
B76: Телочки на к.п. | D76: голов | E76: ='Operating Model'!AI87 -> 0 | F76: ='Operating Model'!AJ87 -> 0 | G76: ='Operating Model'!AK87 -> 0 | H76: ='Operating Model'!AL87 -> 0 | I76: ='Operating Model'!AM87 -> 0 | J76: ='Operating Model'!AN87 -> 0 | K76: ='Operating Model'!AO87 -> 0 | L76: ='Operating Model'!AP87 -> 0 | ... O76: ='Operating Model'!AS87 -> 0
B77: Бычки на к.п. | D77: голов | E77: ='Operating Model'!AI96 -> 0 | F77: ='Operating Model'!AJ96 -> 0 | G77: ='Operating Model'!AK96 -> 0 | H77: ='Operating Model'!AL96 -> 0 | I77: ='Operating Model'!AM96 -> 0 | J77: ='Operating Model'!AN96 -> 0 | K77: ='Operating Model'!AO96 -> 0 | L77: ='Operating Model'!AP96 -> 0 | ... O77: ='Operating Model'!AS96 -> 0
E79: =E71 -> 2026 | F79: =F71 -> 2027 | G79: =G71 -> 2028 | H79: =H71 -> 2029 | I79: =I71 -> 2030 | J79: =J71 -> 2031 | K79: =K71 -> 2032 | L79: =L71 -> 2033 | ... O79: =O71 -> 2036
B80: Приплод | D80: голов | E80: ='Operating Model'!AI70 -> 0 | F80: ='Operating Model'!AJ70 -> 0 | G80: ='Operating Model'!AK70 -> 138.76572 | H80: ='Operating Model'!AL70 -> 170.99406 | I80: ='Operating Model'!AM70 -> 210.70743 | J80: ='Operating Model'!AN70 -> 255 | K80: ='Operating Model'!AO70 -> 255 | L80: ='Operating Model'!AP70 -> 255 | ... O80: ='Operating Model'!AS70 -> 255
B81: Выбракованный скот | D81: голов | E81: =SUM('Operating Model'!AI53,'Operating Model'!AI63) -> 0 | F81: =SUM('Operating Model'!AJ53,'Operating Model'!AJ63) -> -29.039492 | G81: =SUM('Operating Model'!AK53,'Operating Model'!AK63) -> -27.988068 | H81: =SUM('Operating Model'!AL53,'Operating Model'!AL63) -> -32.896319 | I81: =SUM('Operating Model'!AM53,'Operating Model'!AM63) -> -40.536489 | J81: =SUM('Operating Model'!AN53,'Operating Model'!AN63) -> -49.131518 | K81: =SUM('Operating Model'!AO53,'Operating Model'!AO63) -> -50 | L81: =SUM('Operating Model'!AP53,'Operating Model'!AP63) -> -50 | ... O81: =SUM('Operating Model'!AS53,'Operating Model'!AS63) -> -50
B82: Падеж скота | D82: голов | E82: =SUM('Operating Model'!AI54,'Operating Model'!AI64,'Operating Model'!AI82,'Operating Model'!AI93) -> -1.9925125 | F82: =SUM('Operating Model'!AJ54,'Operating Model'!AJ64,'Operating Model'!AJ82,'Operating Model'!AJ93) -> -5.7142074 | G82: =SUM('Operating Model'!AK54,'Operating Model'!AK64,'Operating Model'!AK82,'Operating Model'!AK93) -> -9.4805853 | H82: =SUM('Operating Model'!AL54,'Operating Model'!AL64,'Operating Model'!AL82,'Operating Model'!AL93) -> -11.491414 | I82: =SUM('Operating Model'!AM54,'Operating Model'!AM64,'Operating Model'!AM82,'Operating Model'!AM93) -> -14.160295 | J82: =SUM('Operating Model'!AN54,'Operating Model'!AN64,'Operating Model'!AN82,'Operating Model'!AN93) -> -17.145782 | K82: =SUM('Operating Model'!AO54,'Operating Model'!AO64,'Operating Model'!AO82,'Operating Model'!AO93) -> -17.25 | L82: =SUM('Operating Model'!AP54,'Operating Model'!AP64,'Operating Model'!AP82,'Operating Model'!AP93) -> -17.25 | ... O82: =SUM('Operating Model'!AS54,'Operating Model'!AS64,'Operating Model'!AS82,'Operating Model'!AS93) -> -17.25
C83: Падеж телочек | D83: голов | E83: ='Operating Model'!AI82 -> 0 | F83: ='Operating Model'!AJ82 -> 0 | G83: ='Operating Model'!AK82 -> -2.0814858 | H83: ='Operating Model'!AL82 -> -2.5649109 | I83: ='Operating Model'!AM82 -> -3.1606114 | J83: ='Operating Model'!AN82 -> -3.825 | K83: ='Operating Model'!AO82 -> -3.825 | L83: ='Operating Model'!AP82 -> -3.825 | ... O83: ='Operating Model'!AS82 -> -3.825
C84: Падеж бычков | D84: голов | E84: ='Operating Model'!AI93 -> 0 | F84: ='Operating Model'!AJ93 -> 0 | G84: ='Operating Model'!AK93 -> -2.0814858 | H84: ='Operating Model'!AL93 -> -2.5649109 | I84: ='Operating Model'!AM93 -> -3.1606114 | J84: ='Operating Model'!AN93 -> -3.825 | K84: ='Operating Model'!AO93 -> -3.825 | L84: ='Operating Model'!AP93 -> -3.825 | ... O84: ='Operating Model'!AS93 -> -3.825
B86: КРС на н.п. | E86: ='Operating Model'!AI104 -> 214 | F86: ='Operating Model'!AJ104 -> 212.00749 | G86: ='Operating Model'!AK104 -> 177.25379 | H86: ='Operating Model'!AL104 -> 212.05307 | I86: ='Operating Model'!AM104 -> 261.30239 | J86: ='Operating Model'!AN104 -> 316.52607 | K86: ='Operating Model'!AO104 -> 320 | L86: ='Operating Model'!AP104 -> 320 | ... O86: ='Operating Model'!AS104 -> 320
B87: КРС на к.п. | D87: голов | E87: ='Operating Model'!AI105 -> 212.00749 | F87: ='Operating Model'!AJ105 -> 177.25379 | G87: ='Operating Model'!AK105 -> 212.05307 | H87: ='Operating Model'!AL105 -> 261.30239 | I87: ='Operating Model'!AM105 -> 316.52607 | J87: ='Operating Model'!AN105 -> 320 | K87: ='Operating Model'!AO105 -> 320 | L87: ='Operating Model'!AP105 -> 320 | ... O87: ='Operating Model'!AS105 -> 320
B89: Приплод | D89: % | E89: =E80/E74 -> 0 | F89: =F80/F74 -> 0 | G89: =G80/F74 -> 0.85 | H89: =H80/G74 -> 0.85 | I89: =I80/H74 -> 0.85 | J89: =J80/I74 -> 0.85 | K89: =K80/J74 -> 0.85 | L89: =L80/K74 -> 0.85 | M89: =M80/L74 -> 0.85 | N89: =N80/M74 -> 0.85 | O89: =O80/N74 -> 0.85
B90: Деловой приплод | D90: % | E90: 0 | F90: =SUM(F80,F83,F84)/F74 -> 0 | G90: =SUM(G80,G83,G84)/F74 -> 0.8245 | H90: =SUM(H80,H83,H84)/G74 -> 0.8245 | I90: =SUM(I80,I83,I84)/H74 -> 0.8245 | J90: =SUM(J80,J83,J84)/I74 -> 0.8245 | K90: =SUM(K80,K83,K84)/J74 -> 0.8245 | L90: =SUM(L80,L83,L84)/K74 -> 0.8245 | M90: =SUM(M80,M83,M84)/L74 -> 0.8245 | N90: =SUM(N80,N83,N84)/M74 -> 0.8245 | O90: =SUM(O80,O83,O84)/N74 -> 0.8245
B91: Общий коэффициент падежа | D91: % | E91: =-SUM(E82)/E86 -> 0.009310806 | F91: =-SUM(F82)/F86 -> 0.026952857 | G91: =-SUM(G82)/G86 -> 0.053485939 | H91: =-SUM(H82)/H86 -> 0.054191217 | I91: =-SUM(I82)/I86 -> 0.054191217 | J91: =-SUM(J82)/J86 -> 0.054168625 | K91: =-SUM(K82)/K86 -> 0.05390625 | L91: =-SUM(L82)/L86 -> 0.05390625 | ... O91: =-SUM(O82)/O86 -> 0.05390625
B92: Общий коэффициент потерь | D92: % | E92: =-SUM(E81:E82)/E86 -> 0.009310806 | F92: =-SUM(F81:F82)/F86 -> 0.16392675 | G92: =-SUM(G81:G82)/G86 -> 0.21138422 | H92: =-SUM(H81:H82)/H86 -> 0.2093237 | I92: =-SUM(I81:I82)/I86 -> 0.2093237 | J92: =-SUM(J81:J82)/J86 -> 0.2093897 | K92: =-SUM(K81:K82)/K86 -> 0.21015625 | L92: =-SUM(L81:L82)/L86 -> 0.21015625 | ... O92: =-SUM(O81:O82)/O86 -> 0.21015625
A94: х | B94: Показатели продажи
B96: Маточное поголовье | D96: голов | E96: ='Operating Model'!AI166 -> 0 | F96: ='Operating Model'!AJ166 -> 29.039492 | G96: ='Operating Model'!AK166 -> 24.488068 | H96: ='Operating Model'!AL166 -> 30.175422 | I96: ='Operating Model'!AM166 -> 37.183664 | J96: ='Operating Model'!AN166 -> 45 | K96: ='Operating Model'!AO166 -> 45 | L96: ='Operating Model'!AP166 -> 45 | ... O96: ='Operating Model'!AS166 -> 45
B97: Быки-производители | D97: голов | E97: ='Operating Model'!AI167 -> 0 | F97: ='Operating Model'!AJ167 -> 0 | G97: ='Operating Model'!AK167 -> 3.5 | H97: ='Operating Model'!AL167 -> 2.7208965 | I97: ='Operating Model'!AM167 -> 3.3528247 | J97: ='Operating Model'!AN167 -> 4.1315182 | K97: ='Operating Model'!AO167 -> 5 | L97: ='Operating Model'!AP167 -> 5 | ... O97: ='Operating Model'!AS167 -> 5
B98: Телочки | D98: голов | E98: ='Operating Model'!AI165 -> 0 | F98: ='Operating Model'!AJ165 -> 0 | G98: ='Operating Model'!AK165 -> 0 | H98: ='Operating Model'!AL165 -> 0 | I98: ='Operating Model'!AM165 -> 5.4637988 | J98: ='Operating Model'!AN165 -> 69.675 | K98: ='Operating Model'!AO165 -> 69.675 | L98: ='Operating Model'!AP165 -> 69.675 | ... O98: ='Operating Model'!AS165 -> 69.675
B99: Бычки | D99: голов | E99: ='Operating Model'!AI168 -> 0 | F99: ='Operating Model'!AJ168 -> 0 | G99: ='Operating Model'!AK168 -> 66.497788 | H99: ='Operating Model'!AL168 -> 77.357002 | I99: ='Operating Model'!AM168 -> 95.323165 | J99: ='Operating Model'!AN168 -> 115.57377 | K99: ='Operating Model'!AO168 -> 118.075 | L99: ='Operating Model'!AP168 -> 118.075 | ... O99: ='Operating Model'!AS168 -> 118.075
B100: Продажи КРС, голов | D100: голов | E100: ='Operating Model'!AI170 -> 0 | F100: ='Operating Model'!AJ170 -> 29.039492 | G100: ='Operating Model'!AK170 -> 94.485857 | H100: ='Operating Model'!AL170 -> 110.25332 | I100: ='Operating Model'!AM170 -> 141.32345 | J100: ='Operating Model'!AN170 -> 234.38029 | K100: ='Operating Model'!AO170 -> 237.75 | L100: ='Operating Model'!AP170 -> 237.75 | ... O100: ='Operating Model'!AS170 -> 237.75
B103: Маточное поголовье | D103: кг | E103: ='Operating Model'!AI175 -> 0 | F103: ='Operating Model'!AJ175 -> 17423.695 | G103: ='Operating Model'!AK175 -> 14692.841 | H103: ='Operating Model'!AL175 -> 18105.253 | I103: ='Operating Model'!AM175 -> 22310.198 | J103: ='Operating Model'!AN175 -> 27000 | K103: ='Operating Model'!AO175 -> 27000 | L103: ='Operating Model'!AP175 -> 27000 | ... O103: ='Operating Model'!AS175 -> 27000
B104: Быки-производители | D104: кг | E104: ='Operating Model'!AI176 -> 0 | F104: ='Operating Model'!AJ176 -> 0 | G104: ='Operating Model'!AK176 -> 2625 | H104: ='Operating Model'!AL176 -> 2040.6724 | I104: ='Operating Model'!AM176 -> 2514.6185 | J104: ='Operating Model'!AN176 -> 3098.6387 | K104: ='Operating Model'!AO176 -> 3750 | L104: ='Operating Model'!AP176 -> 3750 | ... O104: ='Operating Model'!AS176 -> 3750
B105: Телочки | D105: кг | E105: ='Operating Model'!AI174 -> 0 | F105: ='Operating Model'!AJ174 -> 0 | G105: ='Operating Model'!AK174 -> 0 | H105: ='Operating Model'!AL174 -> 0 | I105: ='Operating Model'!AM174 -> 1510.194 | J105: ='Operating Model'!AN174 -> 19258.17 | K105: ='Operating Model'!AO174 -> 19258.17 | L105: ='Operating Model'!AP174 -> 19258.17 | ... O105: ='Operating Model'!AS174 -> 19258.17
B106: Бычки | D106: кг | E106: ='Operating Model'!AI177 -> 0 | F106: ='Operating Model'!AJ177 -> 0 | G106: ='Operating Model'!AK177 -> 22010.768 | H106: ='Operating Model'!AL177 -> 25605.168 | I106: ='Operating Model'!AM177 -> 31551.968 | J106: ='Operating Model'!AN177 -> 38254.919 | K106: ='Operating Model'!AO177 -> 39082.825 | L106: ='Operating Model'!AP177 -> 39082.825 | ... O106: ='Operating Model'!AS177 -> 39082.825
B107: Продажи КРС, кг | D107: кг | E107: =SUM(E103:E106) -> 0 | F107: =SUM(F103:F106) -> 17423.695 | G107: =SUM(G103:G106) -> 39328.609 | H107: =SUM(H103:H106) -> 45751.093 | I107: =SUM(I103:I106) -> 57886.978 | J107: =SUM(J103:J106) -> 87611.727 | K107: =SUM(K103:K106) -> 89090.995 | L107: =SUM(L103:L106) -> 89090.995 | ... O107: =SUM(O103:O106) -> 89090.995
A110: х | B110: Финансовые показатели
B111: Отчет о прибылях и убытках Большая ферма
E112: =E71 -> 2026 | F112: =F71 -> 2027 | G112: =G71 -> 2028 | H112: =H71 -> 2029 | I112: =I71 -> 2030 | J112: =J71 -> 2031 | K112: =K71 -> 2032 | L112: =L71 -> 2033 | ... O112: =O71 -> 2036
B113: Выручка | D113: тыс. тенге | E113: ='Operating Model'!AI188 -> 55640 | F113: ='Operating Model'!AJ188 -> 34655.729 | G113: ='Operating Model'!AK188 -> 106930.8 | H113: ='Operating Model'!AL188 -> 135108.42 | I113: ='Operating Model'!AM188 -> 186015.32 | J113: ='Operating Model'!AN188 -> 304695.22 | K113: ='Operating Model'!AO188 -> 334821.94 | L113: ='Operating Model'!AP188 -> 357760.26 | ... O113: ='Operating Model'!AS188 -> 422447.87
B114: Валовая прибыль | D114: тыс. тенге | E114: ='Operating Model'!AI222 -> 37513.072 | F114: ='Operating Model'!AJ222 -> -20343.488 | G114: ='Operating Model'!AK222 -> 36201.264 | H114: ='Operating Model'!AL222 -> 58756.156 | I114: ='Operating Model'!AM222 -> 95728.956 | J114: ='Operating Model'!AN222 -> 207479.75 | K114: ='Operating Model'!AO222 -> 229924.21 | L114: ='Operating Model'!AP222 -> 245650.57 | ... O114: ='Operating Model'!AS222 -> 289984.35
B115: EBITDA | D115: тыс. тенге | E115: ='Operating Model'!AI231 -> 33109.59 | F115: ='Operating Model'!AJ231 -> -24411.518 | G115: ='Operating Model'!AK231 -> 30351.156 | H115: ='Operating Model'!AL231 -> 52695.6 | I115: ='Operating Model'!AM231 -> 89003.239 | J115: ='Operating Model'!AN231 -> 198661.25 | K115: ='Operating Model'!AO231 -> 220683.05 | L115: ='Operating Model'!AP231 -> 236130.73 | ... O115: ='Operating Model'!AS231 -> 279711.58
B116: EBITDA, adj. | D116: тыс. тенге | E116: ='Operating Model'!AI243 -> 33109.59 | F116: ='Operating Model'!AJ243 -> -24411.518 | G116: ='Operating Model'!AK243 -> 30351.156 | H116: ='Operating Model'!AL243 -> 52695.6 | I116: ='Operating Model'!AM243 -> 89003.239 | J116: ='Operating Model'!AN243 -> 198661.25 | K116: ='Operating Model'!AO243 -> 220683.05 | L116: ='Operating Model'!AP243 -> 236130.73 | ... O116: ='Operating Model'!AS243 -> 279711.58
B117: Чистая прибыль | D117: тыс. тенге | E117: ='Operating Model'!AI240 -> 18272.487 | F117: ='Operating Model'!AJ240 -> -50067.057 | G117: ='Operating Model'!AK240 -> -1736.7356 | H117: ='Operating Model'!AL240 -> 924.97012 | I117: ='Operating Model'!AM240 -> 28272.535 | J117: ='Operating Model'!AN240 -> 120206.13 | K117: ='Operating Model'!AO240 -> 143887.72 | L117: ='Operating Model'!AP240 -> 156995.3 | ... O117: ='Operating Model'!AS240 -> 209079.49
B120: Показатели маржинальности
B121: Валовая прибыль | D121: % | E121: =E114/E$113 -> 0.67421049 | F121: =F114/F$113 -> -0.58701658 | G121: =G114/G$113 -> 0.3385485 | H121: =H114/H$113 -> 0.43488152 | I121: =I114/I$113 -> 0.51462942 | J121: =J114/J$113 -> 0.68094193 | K121: =K114/K$113 -> 0.6867059 | L121: =L114/L$113 -> 0.68663459 | ... O121: =O114/O$113 -> 0.68643817
B122: EBITDA | D122: % | E122: =E115/E$113 -> 0.59506811 | F122: =F115/F$113 -> -0.70440065 | G122: =G115/G$113 -> 0.28383922 | H122: =H115/H$113 -> 0.39002454 | I122: =I115/I$113 -> 0.47847263 | J122: =J115/J$113 -> 0.65199991 | K122: =K115/K$113 -> 0.6591057 | L122: =L115/L$113 -> 0.66002504 | ... O122: =O115/O$113 -> 0.66212094
B123: EBITDA, adj. | D123: % | E123: =E116/E$113 -> 0.59506811 | F123: =F116/F$113 -> -0.70440065 | G123: =G116/G$113 -> 0.28383922 | H123: =H116/H$113 -> 0.39002454 | I123: =I116/I$113 -> 0.47847263 | J123: =J116/J$113 -> 0.65199991 | K123: =K116/K$113 -> 0.6591057 | L123: =L116/L$113 -> 0.66002504 | ... O123: =O116/O$113 -> 0.66212094
B124: Чистая прибыль | D124: % | E124: =E117/E$113 -> 0.32840559 | F124: =F117/F$113 -> -1.4446978 | G124: =G117/G$113 -> -0.016241678 | H124: =H117/H$113 -> 0.0068461322 | I124: =I117/I$113 -> 0.15199036 | J124: =J117/J$113 -> 0.39451268 | K124: =K117/K$113 -> 0.42974399 | L124: =L117/L$113 -> 0.43882821 | ... O124: =O117/O$113 -> 0.49492376
B126: Балансовые показатели | E126: =E112 -> 2026 | F126: =F112 -> 2027 | G126: =G112 -> 2028 | H126: =H112 -> 2029 | I126: =I112 -> 2030 | J126: =J112 -> 2031 | K126: =K112 -> 2032 | L126: =L112 -> 2033 | ... O126: =O112 -> 2036
B127: Активы | D127: тыс. тенге | E127: ='Operating Model'!AI261 -> 455899.77 | F127: ='Operating Model'!AJ261 -> 438881.25 | G127: ='Operating Model'!AK261 -> 421176.63 | H127: ='Operating Model'!AL261 -> 441115.17 | I127: ='Operating Model'!AM261 -> 498204.69 | J127: ='Operating Model'!AN261 -> 604247.45 | K127: ='Operating Model'!AO261 -> 726848.84 | L127: ='Operating Model'!AP261 -> 862119.7 | ... O127: ='Operating Model'!AS261 -> 1062831
B128: Биологические активы | D128: тыс. тенге | E128: =SUM('Operating Model'!AI258:AI260) -> 119100 | F128: =SUM('Operating Model'!AJ258:AJ260) -> 119100 | G128: =SUM('Operating Model'!AK258:AK260) -> 119100 | H128: =SUM('Operating Model'!AL258:AL260) -> 119100 | I128: =SUM('Operating Model'!AM258:AM260) -> 119100 | J128: =SUM('Operating Model'!AN258:AN260) -> 119100 | K128: =SUM('Operating Model'!AO258:AO260) -> 119100 | L128: =SUM('Operating Model'!AP258:AP260) -> 119100 | ... O128: =SUM('Operating Model'!AS258:AS260) -> 119100
B129: Обязательства | D129: тыс. тенге | E129: ='Operating Model'!AI268 -> 374392.51 | F129: ='Operating Model'!AJ268 -> 407441.05 | G129: ='Operating Model'!AK268 -> 391473.16 | H129: ='Operating Model'!AL268 -> 410486.73 | I129: ='Operating Model'!AM268 -> 439303.72 | J129: ='Operating Model'!AN268 -> 425140.35 | K129: ='Operating Model'!AO268 -> 403854.02 | L129: ='Operating Model'!AP268 -> 382129.59 | ... O129: ='Operating Model'!AS268 -> -7.2759576e-11
B130: Займы на оборотку | D130: тыс. тенге | E130: ='Operating Model'!AI266 -> 16062.139 | F130: ='Operating Model'!AJ266 -> 49110.678 | G130: ='Operating Model'!AK266 -> 72559.128 | H130: ='Operating Model'!AL266 -> 130989.04 | I130: ='Operating Model'!AM266 -> 199222.37 | J130: ='Operating Model'!AN266 -> 224475.34 | K130: ='Operating Model'!AO266 -> 242605.36 | L130: ='Operating Model'!AP266 -> 260297.27 | ... O130: ='Operating Model'!AS266 -> 0
...

Sheet Input
B1: Проект Franchise Karabalyk
B3: Общие вводные данные
B4: Цена закупа 1 маточного поголовья | D4: тенге | F4: 550000
B5: Цена закупа 1 быка производителя | D5: тенге | F5: 650000
B6: Норма по количеству быков-производителей | D6: ratio | F6: =1/15 -> 0.066666667
B7: Норма на пастбища | D7: га на 1 голову | F7: 10
B8: Площадь пастбищ на 1 ферму | D8: га | F8: =F7*F42 -> 3000
B9: Переключатель (1= с субсидиями, 2 - без субсидий) | F9: 1
B10: Переключатель (1= с привлечением займов на ПОС, 2 - без без привлечения займов на ПОС) | F10: 1
B11: Переключатель (1= без переоценки биоактивов, 2 - с переоценкой активов) | F11: 1
B13: Условия финансирования
B15: Капитальные затраты
C16: Ставка вознаграждения | D16: % | F16: =Output!D190 -> 0.05
C17: Срок кредитования | D17: лет | F17: 10
C18: Срок кредитования | D18: мес. | F18: =F17*12 -> 120
C19: Льготный период | D19: лет | F19: 2
C20: Доля займа | D20: % | F20: 0.9
B22: Закуп поголовья
C23: Ставка вознаграждения | D23: % | F23: 0.05
C24: Срок кредитования | D24: лет | F24: 10
C25: Срок кредитования | D25: мес. | F25: =F24*12 -> 120
C26: Льготный период | D26: лет | F26: 2
C27: Доля займа | D27: % | F27: 0.9
B29: Оборотный капитал
C30: Ставка вознаграждения | D30: % | F30: 0.06
C31: Срок кредитования | D31: лет | F31: =F32/12 -> 1.25
C32: Срок кредитования | D32: мес. | F32: 15
C33: Льготный период | D33: мес. | F33: 15
B36: Дата старта проекта | D36: дата | F36: 46265
B37: Размер паушального взноса | D37: тыс. тенге | F37: 0
B38: Минимальный размер роялти, в год | D38: тыс. тенге | F38: 0
B39: Размер собственного участия | D39: тыс. тенге | F39: =F44 -> 63234.772
B40: Закуп маточного поголовья | D40: кол-во голов | F40: =F62 -> 200 | G40: 0
B41: Закуп быков-производителей | D41: кол-во голов | F41: =ROUNDUP(F40*$F$6,0) -> 14 | G41: =ROUNDUP(G40*$F$6,0) -> 0
B42: Мощность репродуктора | D42: кол-во голов | F42: =F63 -> 300
B43: Доля собственного участия | D43: % | F43: 0.15
B44: Размер необходимого собственного участия | D44: тыс. тенге | F44: =F56*F43 -> 63234.772
F46: 1 ый год
F47: Итого | G47: Займ АКК | H47: Собственное участие
B48: Капитальные затраты | D48: тыс. тенге | F48: =SUM(F49,F50,F51) -> 302465.15 | G48: =F48-H48 -> 257095.37 | H48: =F48*$F$43 -> 45369.772
C49: Предварительные расходы | D49: тыс. тенге | F49: 20000 | G49: =F49-H49 -> 0 | H49: =F49 -> 20000
C50: Строительство зданий и инфраструктура | D50: тыс. тенге | F50: =CAPEX!H29/1000+CAPEX!H38/1000 -> 224825.15 | G50: =F50-H50 -> 208101.37 | H50: =H48-H49-H51 -> 16723.772
C51: Спецтехника и оборудование | D51: тыс. тенге | F51: =(CAPEX!H49+CAPEX!H71)/1000 -> 57640 | G51: =F51-H51 -> 48994 | H51: =F51*F43 -> 8646
B52: Закуп стада | D52: тыс. тенге | F52: =SUM(F53,F54) -> 119100 | G52: =F52-H52 -> 101235 | H52: =F52*$F$43 -> 17865
C53: Маточное поголовье | D53: тыс. тенге | F53: =F40*$F$4/1000 -> 110000 | G53: =F53-H53 -> 93500 | H53: =F53*$F$43 -> 16500
C54: Быки-проивзодители | D54: тыс. тенге | F54: =F41*$F$5/1000 -> 9100 | G54: =F54-H54 -> 7735 | H54: =F54*$F$43 -> 1365
C55: Закуп товарного стада | D55: тыс. тенге | F55: 0 | G55: =F55-H55 -> 0
B56: Итого | D56: тыс. тенге | F56: =SUM(F48,F52) -> 421565.15 | G56: =F56-H56 -> 358330.37 | H56: =SUM(H48,H52) -> 63234.772
B57: Норма тведых залогов | D57: 0.15 | G57: =$D$57*G56 -> 53749.556
B60: Гибкие параметры модели
B62: Стартовое маточное поголовье | D62: голов | F62: 200
B63: Мощность репродуктора | D63: голов | F63: 300
B64: Тип отёла | F64: Зимний
B65: Материал закрытых сооружений | F65: Сэндвич-панель
B66: Материал вспомогательных сооружений | F66: Лёгкий каркас
B68: Параметры из Справочника
B69: Регион | F69: REG-SKO
B70: Пастбищная норма | D70: га/усл.гол. | F70: =_xlfn.XLOOKUP(F69,Справочник!A58:A74,Справочник!D58:D74,"-") -> 3.5
B71: К утепления (зима) | D71: множ. | F71: =_xlfn.XLOOKUP("COEF-001",Справочник!A81:A88,Справочник!D81:D88,1) -> 1
B72: К непредвиденных | D72: множ. | F72: =_xlfn.XLOOKUP("COEF-006",Справочник!A81:A88,Справочник!D81:D88,1) -> 1.1
B73: К ПИР | D73: доля | F73: =_xlfn.XLOOKUP("COEF-007",Справочник!A81:A88,Справочник!D81:D88,0) -> 0.05
B74: К технадзора | D74: доля | F74: =_xlfn.XLOOKUP("COEF-008",Справочник!A81:A88,Справочник!D81:D88,0) -> 0.03
B75: Цена/м² закрытых (из материала) | D75: тыс.тг/м² | F75: =_xlfn.XLOOKUP(F65,Справочник!B41:B47,Справочник!D41:D47,0) -> 25
B76: Цена/м² вспомогат. (из материала) | D76: тыс.тг/м² | F76: =_xlfn.XLOOKUP(F66,Справочник!B41:B47,Справочник!D41:D47,0) -> 15
B77: Срок службы закрытых | D77: лет | F77: =_xlfn.XLOOKUP(F65,Справочник!B41:B47,Справочник!E41:E47,0) -> 30
B78: Срок службы вспомогат. | D78: лет | F78: =_xlfn.XLOOKUP(F66,Справочник!B41:B47,Справочник!E41:E47,0) -> 20

Sheet Feeding Rations
A1: х | B1: РАЦИОНЫ ПИТАНИЯ / FEEDING RATIONS
B3: Суточный рацион по месяцам (сезонный паттерн)
J4: 1 | K4: =J4+1 -> 2 | L4: =K4+1 -> 3 | M4: =L4+1 -> 4 | N4: =M4+1 -> 5 | O4: =N4+1 -> 6 | P4: =O4+1 -> 7 | Q4: =P4+1 -> 8 | R4: =Q4+1 -> 9 | ... U4: =T4+1 -> 12
B5: Маточное поголовье
C6: Зеленая масса | D6: кг | J6: 0 | K6: 0 | L6: 0 | M6: 0 | N6: 32 | O6: 32 | P6: 32 | Q6: 32 | R6: 32 | S6: 32 | T6: 0 | U6: 0
C7: Концентраты | D7: кг | J7: 2.4 | K7: 2.4 | L7: 2.4 | M7: 2.4 | N7: 0 | O7: 0 | P7: 0 | Q7: 0 | R7: 0 | S7: 0 | T7: 2.4 | U7: 2.4
C8: Соль поваренная | D8: кг | J8: 0.057 | K8: 0.057 | L8: 0.057 | M8: 0.057 | N8: 0.05 | O8: 0.05 | P8: 0.05 | Q8: 0.05 | R8: 0.05 | S8: 0.05 | T8: 0.06 | U8: 0.06
C9: Сено | D9: кг | J9: 7 | K9: 7 | L9: 7 | M9: 7 | N9: 0 | O9: 0 | P9: 0 | Q9: 0 | R9: 0 | S9: 0 | T9: 9 | U9: 9
C10: Сенаж | D10: кг | J10: 9 | K10: 9 | L10: 9 | M10: 9 | N10: 0 | O10: 0 | P10: 0 | Q10: 0 | R10: 0 | S10: 0 | T10: 8 | U10: 8
C11: Силос | D11: кг | J11: 15 | K11: 15 | L11: 15 | M11: 15 | N11: 0 | O11: 0 | P11: 0 | Q11: 0 | R11: 0 | S11: 0 | T11: 10 | U11: 10
C12: Диаммонийфосфат | D12: кг | J12: 0.03 | K12: 0.03 | L12: 0.03 | M12: 0.03 | N12: 0 | O12: 0 | P12: 0 | Q12: 0 | R12: 0 | S12: 0 | T12: 0.04 | U12: 0.04
C13: Монокальцийфосфат | D13: кг | J13: 0.055 | K13: 0.055 | L13: 0.055 | M13: 0.055 | N13: 0 | O13: 0 | P13: 0 | Q13: 0 | R13: 0 | S13: 0 | T13: 0.045 | U13: 0.045
B15: Быки-производители
C16: Зеленая масса | D16: кг | J16: 0 | K16: 0 | L16: 0 | M16: 0 | N16: 12 | O16: 12 | P16: 12 | Q16: 12 | R16: 12 | S16: 12 | T16: 0 | U16: 0
C17: Сено | D17: кг | J17: 4.5 | K17: 4.5 | L17: 4.5 | M17: 4.5 | N17: 0 | O17: 0 | P17: 0 | Q17: 0 | R17: 0 | S17: 0 | T17: 4.5 | U17: 4.5
C18: Силос | D18: кг | J18: 3 | K18: 3 | L18: 3 | M18: 3 | N18: 0 | O18: 0 | P18: 0 | Q18: 0 | R18: 0 | S18: 0 | T18: 3 | U18: 3
C19: Концентраты | D19: кг | J19: =3.5-0.72 -> 2.78 | K19: =3.5-0.72 -> 2.78 | L19: =3.5-0.72 -> 2.78 | M19: =3.5-0.72 -> 2.78 | N19: 0 | O19: 0 | P19: 0 | Q19: 0 | R19: 0 | S19: 0 | T19: =3.5-0.72 -> 2.78 | U19: =3.5-0.72 -> 2.78
C20: БМВД | D20: кг | J20: 0.72 | K20: 0.72 | L20: 0.72 | M20: 0.72 | N20: 0 | O20: 0 | P20: 0 | Q20: 0 | R20: 0 | S20: 0 | T20: 0.72 | U20: 0.72
C21: Соль поваренная | D21: кг | J21: 0.045 | K21: 0.045 | L21: 0.045 | M21: 0.045 | N21: 0.05 | O21: 0.05 | P21: 0.05 | Q21: 0.05 | R21: 0.05 | S21: 0.05 | T21: 0.045 | U21: 0.045
B23: Молодняк
C24: Молоко | D24: л | J24: 7 | K24: 6 | L24: 5 | M24: 4 | N24: 4 | O24: 5 | P24: 0 | Q24: 0 | R24: 0 | S24: 0 | T24: 0 | U24: 6
C25: Сено | D25: кг | J25: 0.3 | K25: 0.5 | L25: 1 | M25: 1.2 | N25: 0 | O25: 0 | P25: 0 | Q25: 0 | R25: 0 | S25: 0 | T25: 0 | U25: 0
C26: Силос | D26: кг | J26: 0 | K26: 2 | L26: 4 | M26: 4 | N26: 0 | O26: 0 | P26: 0 | Q26: 0 | R26: 0 | S26: 0 | T26: 0 | U26: 0
C27: Концентраты | D27: кг | J27: 0.2 | K27: 0.4 | L27: 0.6 | M27: 0.7 | N27: 0 | O27: 0 | P27: 0 | Q27: 0 | R27: 0 | S27: 0 | T27: 0 | U27: 0
C28: Соль поваренная | D28: кг | J28: 0.008 | K28: 0.012 | L28: 0.016 | M28: 0.018 | N28: 0.022 | O28: 0.027 | P28: 0 | Q28: 0 | R28: 0 | S28: 0 | T28: 0 | U28: 0
C29: Кормовой фосфат | D29: кг | J29: 0.01 | K29: 0.02 | L29: 0.03 | M29: 0.03 | N29: 0.04 | O29: 0.03 | P29: 0 | Q29: 0 | R29: 0 | S29: 0 | T29: 0 | U29: 0
C30: Зеленая масса | D30: кг | J30: 0 | K30: 0 | L30: 0 | M30: 0 | N30: 0 | O30: 9 | P30: 0 | Q30: 0 | R30: 0 | S30: 0 | T30: 0 | U30: 0
B32: Телочки
C33: Зеленая масса | D33: кг | J33: 0 | K33: 0 | L33: 0 | M33: 0 | N33: 29 | O33: 29 | P33: 29 | Q33: 29 | R33: 29 | S33: 29 | T33: 0 | U33: 0
C34: Концентраты | D34: кг | J34: 0 | K34: 0 | L34: 0 | M34: 0 | N34: 0 | O34: 0 | P34: 0 | Q34: 0 | R34: 0 | S34: 0 | T34: 0 | U34: 0
C35: Соль поваренная | D35: кг | J35: 0.03 | K35: 0.03 | L35: 0.03 | M35: 0.03 | N35: 0.03 | O35: 0.03 | P35: 0.03 | Q35: 0.03 | R35: 0.03 | S35: 0.03 | T35: 0.03 | U35: 0.03
C36: Кормовой фосфат | D36: кг | J36: 0.03 | K36: 0.03 | L36: 0.03 | M36: 0.03 | N36: 0.03 | O36: 0.03 | P36: 0.03 | Q36: 0.03 | R36: 0.03 | S36: 0.03 | T36: 0.03 | U36: 0.03
C37: Сено | D37: кг | J37: 4 | K37: 4 | L37: 4 | M37: 4 | N37: 0 | O37: 0 | P37: 0 | Q37: 0 | R37: 0 | S37: 0 | T37: 4 | U37: 4
C38: Сенаж | D38: кг | J38: 5 | K38: 5 | L38: 5 | M38: 5 | N38: 0 | O38: 0 | P38: 0 | Q38: 0 | R38: 0 | S38: 0 | T38: 5 | U38: 5
C39: Дерть ячменная | D39: кг | J39: 0.3 | K39: 0.3 | L39: 0.3 | M39: 0.3 | N39: 0 | O39: 0 | P39: 0 | Q39: 0 | R39: 0 | S39: 0 | T39: 0.3 | U39: 0.3
C40: Зерноотходы | D40: кг | J40: 1.6 | K40: 1.6 | L40: 1.6 | M40: 1.6 | N40: 0 | O40: 0 | P40: 0 | Q40: 0 | R40: 0 | S40: 0 | T40: 1.6 | U40: 1.6
B42: Бычки
C43: Зеленая масса | D43: кг | J43: 0 | K43: 0 | L43: 0 | M43: 0 | N43: 30 | O43: 30 | P43: 30 | Q43: 30 | R43: 30 | S43: 30 | T43: 0 | U43: 0
C44: Концентраты | D44: кг | J44: 0 | K44: 0 | L44: 0 | M44: 0 | N44: 0 | O44: 0 | P44: 0 | Q44: 0 | R44: 0 | S44: 0 | T44: 0 | U44: 0
C45: Соль поваренная | D45: кг | J45: 0 | K45: 0 | L45: 0 | M45: 0 | N45: 0.04 | O45: 0.04 | P45: 0.04 | Q45: 0.04 | R45: 0.04 | S45: 0.04 | T45: 0 | U45: 0
C46: Кормовой фосфат | D46: кг | J46: 0 | K46: 0 | L46: 0 | M46: 0 | N46: 0.04 | O46: 0.04 | P46: 0.04 | Q46: 0.04 | R46: 0.04 | S46: 0.04 | T46: 0 | U46: 0
C47: Сено | D47: кг | J47: 0 | K47: 0 | L47: 0 | M47: 0 | N47: 0 | O47: 0 | P47: 0 | Q47: 0 | R47: 0 | S47: 0 | T47: 0 | U47: 0
C48: Солома | D48: кг | J48: 0 | K48: 0 | L48: 0 | M48: 0 | N48: 0 | O48: 0 | P48: 0 | Q48: 0 | R48: 0 | S48: 0 | T48: 0 | U48: 0
C49: Силос | D49: кг | J49: 0 | K49: 0 | L49: 0 | M49: 0 | N49: 0 | O49: 0 | P49: 0 | Q49: 0 | R49: 0 | S49: 0 | T49: 0 | U49: 0

Sheet Operating Model
B1: Проект Model Farm Zhailau
C2: Модель консорциума, без управляющей компании | AI2: 46387 | AJ2: =EOMONTH(AI2,12) -> 46752 | AK2: =EOMONTH(AJ2,12) -> 47118 | AL2: =EOMONTH(AK2,12) -> 47483 | AM2: =EOMONTH(AL2,12) -> 47848 | AN2: =EOMONTH(AM2,12) -> 48213 | AO2: =EOMONTH(AN2,12) -> 48579 | AP2: =EOMONTH(AO2,12) -> 48944 | AQ2: =EOMONTH(AP2,12) -> 49309 | ... AT2: =EOMONTH(AS2,12) -> 50405 | AU2: https://adilet.zan.kz/rus/docs/V2500036215#z85
A3: х | B3: Саммари проекта
AN4: Темп роста для модели Гордона | AQ4: 0.03
B5: Дата старта проекта | F5: 46265
B6: Стартовый взнос инвестора | F6: =Input!F39 -> 63234.772
B7: Кол-во хозяйств | D7: ед. | F7: 1 | AI7: Источники финансирования проекта
B8: Цена 1 маточного поголовья | D8: тенге | F8: 550000 | AK8: % | AL8: Сумма, тыс. тенге | AM8: Сумма, тыс. тенге | AN8: Сумма, тыс. тенге
B9: Цена 1 быка производителя | D9: тенге | F9: 750000 | AI9: Займ | AK9: 0.9 | AL9: =AL12*AK9 -> 379408.63 | AM9: =AM12*AK9 -> 0 | AN9: =SUM(AL9:AM9) -> 379408.63
B10: Переключатель (1= с субсидиями, 2 - без субсидий) | F10: 1 | AI10: Первоначальный взнос | AK10: 0.1 | AL10: =AK10*AL12 -> 42156.515 | AM10: =AM12*AK10 -> 0 | AN10: =SUM(AL10:AM10) -> 42156.515
B11: Переключатель (1= с привлечением займов на ПОС, 2 - без без привлечения займов на ПОС) | F11: 1 | AI11: Старт взнос | AK11: 0 | AL11: =F6-AL10 -> 21078.257 | AM11: 0 | AN11: =SUM(AL11:AM11) -> 21078.257
B12: Переключатель (1= без переоценки биоактивов, 2 - с переоценкой активов) | F12: 1 | AI12: Итого | AK12: =SUM(AK9:AK11) -> 1 | AL12: =F16 -> 421565.15 | AM12: =G16 -> 0 | AN12: =SUM(AL12:AM12) -> 421565.15
B16: Капитальные затраты, итого | F16: =SUM(F17:F24) -> 421565.15 | AI16: Ключевые показатели проекта
C17: Предварительные расходы | D17: тыс. тенге | F17: =Input!F49 -> 20000
C18: Строительство зданий и инфраструктура | D18: тыс. тенге | F18: =Input!F50 -> 224825.15 | AL18: =D414 -> Без учета остатка КРС
C19: Спецтехника и оборудование | D19: тыс. тенге | F19: =Input!F51 -> 57640 | AI19: =C415 -> NPV (10 лет) | AL19: =D415 -> 458767.09
C21: Финансирование административных затрат (первые 3 лет) | D21: тыс. тенге | F21: 0
C22: Маточное поголовье | D22: тыс. тенге | F22: =Input!F53 -> 110000 | AI22: =C416 -> IRR (10 лет) | AL22: =D416 -> 0.17060885
C23: Быки-проивзодители | D23: тыс. тенге | F23: =Input!F54 -> 9100 | AI23: =C417 -> Простая окупаемость | AL23: =D417 -> 7.2195121
C24: Закуп товарного стада | D24: тыс. тенге | F24: 0 | AI24: =C418 -> Дисконтированная окупаемость | AL24: =D418 -> 8.150759
B26: Оборотный капитал, итого | D26: тыс. тенге | F26: =SUM(J308:AG308) -> 56436.079
A28: х | B28: Макроэкономические показатели
J29: =EOMONTH(F5,0) -> 46265 | K29: =EOMONTH(J29,1) -> 46295 | L29: =EOMONTH(K29,1) -> 46326 | M29: =EOMONTH(L29,1) -> 46356 | N29: =EOMONTH(M29,1) -> 46387 | O29: =EOMONTH(N29,1) -> 46418 | P29: =EOMONTH(O29,1) -> 46446 | Q29: =EOMONTH(P29,1) -> 46477 | R29: =EOMONTH(Q29,1) -> 46507 | ... AG29: =EOMONTH(AF29,1) -> 46965 | AI29: =AI38 -> 2026 | AJ29: =AJ38 -> 2027 | AK29: =AK38 -> 2028 | AL29: =AL38 -> 2029 | AM29: =AM38 -> 2030 | AN29: =AN38 -> 2031 | AO29: =AO38 -> 2032 | AP29: =AP38 -> 2033 | ... AT29: =AT38 -> 2037
B30: Рост ВВП | D30: % | E30: https://www.imf.org/external/datamapper/profile/KAZ | F30: IMF | AI30: 4.3 | AJ30: 3.8 | AK30: 2.6 | AL30: 3.1 | AM30: 3.1 | AN30: 3.1 | AO30: 3.1 | AP30: 3.1 | AQ30: 3.1 | AR30: 3.1 | AS30: 3.1 | AT30: 3.1
B31: ИПЦ в KZ, ср. | D31: % | E31: https://www.imf.org/external/datamapper/profile/KAZ | F31: IMF | J31: 1 | K31: =J31 -> 1 | L31: =K31 -> 1 | M31: =L31 -> 1 | N31: =M31 -> 1 | O31: =AJ31+N31 -> 1.105 | P31: 1 | Q31: 1 | R31: 1 | S31: 1 | T31: 1 | U31: 1 | V31: 1 | W31: 1 | X31: 1 | Y31: 1 | Z31: 1 | AA31: =AK31+Z31 -> 1.1 | AB31: 1 | AC31: 1 | AD31: 1 | AE31: 1 | AF31: 1 | AG31: 1 | AI31: 0.11 | AJ31: 0.105 | AK31: 0.1 | AL31: 0.095 | AM31: 0.09 | AN31: 0.085 | AO31: 0.08 | AP31: 0.07 | AQ31: 0.065 | AR31: 0.06 | AS31: 0.05 | AT31: 0.05
B32: KZT/USD | D32: тенге/долл. США | AI32: 550 | AJ32: =AI32*(1+5%) -> 577.5 | AK32: =AJ32*(1+5%) -> 606.375 | AL32: =AK32*(1+5%) -> 636.69375 | AM32: =AL32*(1+5%) -> 668.52844 | AN32: =AM32*(1+5%) -> 701.95486 | AO32: =AN32*(1+5%) -> 737.0526 | AP32: =AO32*(1+5%) -> 773.90523 | AQ32: =AP32*(1+5%) -> 812.60049 | ... AT32: =AS32*(1+5%) -> 940.68665
A34: х | B34: Движение скота
J35: 1 | K35: =J35+1 -> 2 | L35: =K35+1 -> 3 | M35: =L35+1 -> 4 | N35: =M35+1 -> 5 | O35: =N35+1 -> 6 | P35: =O35+1 -> 7 | Q35: =P35+1 -> 8 | R35: =Q35+1 -> 9 | ... AG35: =AF35+1 -> 24 | AI35: 5 | AJ35: 12 | AK35: 12 | AL35: 12 | AM35: 12 | AN35: 12 | AO35: 12 | AP35: 12 | AQ35: 12 | AR35: 12 | AS35: 12 | AT35: 12
A36: Репродуктор
J37: =YEAR(J39) -> 2026 | K37: =YEAR(K39) -> 2026 | L37: =YEAR(L39) -> 2026 | M37: =YEAR(M39) -> 2026 | N37: =YEAR(N39) -> 2026 | O37: =YEAR(O39) -> 2027 | P37: =YEAR(P39) -> 2027 | Q37: =YEAR(Q39) -> 2027 | ... AG37: =YEAR(AG39) -> 2028 | AI37: =YEAR(AI39) -> 2026 | AJ37: =YEAR(AJ39) -> 2027 | AK37: =YEAR(AK39) -> 2028 | AL37: =YEAR(AL39) -> 2029 | AM37: =YEAR(AM39) -> 2030 | AN37: =YEAR(AN39) -> 2031 | AO37: =YEAR(AO39) -> 2032 | AP37: =YEAR(AP39) -> 2033 | ... AT37: =YEAR(AT39) -> 2037
E38: Год | G38: Месяц | J38: 46265 | K38: =EDATE(J38,1) -> 46295 | L38: =EDATE(K38,1) -> 46325 | M38: =EDATE(L38,1) -> 46356 | N38: =EDATE(M38,1) -> 46386 | O38: =EDATE(N38,1) -> 46417 | P38: =EDATE(O38,1) -> 46446 | Q38: =EDATE(P38,1) -> 46474 | R38: =EDATE(Q38,1) -> 46505 | ... AG38: =EDATE(AF38,1) -> 46962 | AI38: =YEAR(AI2) -> 2026 | AJ38: =YEAR(AJ2) -> 2027 | AK38: =YEAR(AK2) -> 2028 | AL38: =YEAR(AL2) -> 2029 | AM38: =YEAR(AM2) -> 2030 | AN38: =YEAR(AN2) -> 2031 | AO38: =YEAR(AO2) -> 2032 | AP38: =YEAR(AP2) -> 2033 | ... AT38: =YEAR(AT2) -> 2037
J39: 46265 | K39: =EOMONTH(J39,1) -> 46295 | L39: =EOMONTH(K39,1) -> 46326 | M39: =EOMONTH(L39,1) -> 46356 | N39: =EOMONTH(M39,1) -> 46387 | O39: =EOMONTH(N39,1) -> 46418 | P39: =EOMONTH(O39,1) -> 46446 | Q39: =EOMONTH(P39,1) -> 46477 | R39: =EOMONTH(Q39,1) -> 46507 | ... AG39: =EOMONTH(AF39,1) -> 46965 | AI39: 46387 | AJ39: =EOMONTH(AI39,12) -> 46752 | AK39: =EOMONTH(AJ39,12) -> 47118 | AL39: =EOMONTH(AK39,12) -> 47483 | AM39: =EOMONTH(AL39,12) -> 47848 | AN39: =EOMONTH(AM39,12) -> 48213 | AO39: =EOMONTH(AN39,12) -> 48579 | AP39: =EOMONTH(AO39,12) -> 48944 | AQ39: =EOMONTH(AP39,12) -> 49309 | ... AT39: =EOMONTH(AS39,12) -> 50405
B41: Мощность репродуктора | D41: голов | E41: =Input!F42 -> 300 | J41: =$E$41*J42 -> 300 | K41: =$E$41*K42 -> 300 | L41: =$E$41*L42 -> 300 | M41: =$E$41*M42 -> 300 | N41: =$E$41*N42 -> 300 | O41: =$E$41*O42 -> 300 | P41: =$E$41*P42 -> 300 | Q41: =$E$41*Q42 -> 300 | ... AG41: =$E$41*AG42 -> 300 | AI41: =$E$41*AI42 -> 300 | AJ41: =$E$41*AJ42 -> 300 | AK41: =$E$41*AK42 -> 300 | AL41: =$E$41*AL42 -> 300 | AM41: =$E$41*AM42 -> 300 | AN41: =$E$41*AN42 -> 300 | AO41: =$E$41*AO42 -> 300 | AP41: =$E$41*AP42 -> 300 | ... AT41: =$E$41*AT42 -> 300
B42: Кол-во репродукторов | D42: ед. | J42: =J45 -> 1 | K42: =J42 -> 1 | L42: =K42 -> 1 | M42: =L42 -> 1 | N42: =M42 -> 1 | O42: =N42 -> 1 | P42: =O42 -> 1 | Q42: =P42 -> 1 | R42: =Q42 -> 1 | ... AG42: =AF42 -> 1 | AI42: 1 | AJ42: =AI42 -> 1 | AK42: =AJ42 -> 1 | AL42: =AK42 -> 1 | AM42: =AL42 -> 1 | AN42: =AM42 -> 1 | AO42: =AN42 -> 1 | AP42: =AO42 -> 1 | AQ42: =AP42 -> 1 | ... AT42: =AS42 -> 1
B45: Количество хозяйств | D45: единиц | J45: 1 | K45: 0 | L45: 0 | M45: 0 | N45: 0 | O45: 0 | P45: 0 | Q45: 0 | R45: 0 | S45: =J45 -> 1 | T45: 0 | U45: 0 | V45: 0 | W45: 0 | X45: 0 | Y45: 0 | Z45: 0 | AA45: 0 | AB45: 0 | AC45: 0 | AD45: 0 | AE45: 0 | AF45: 0 | AG45: 0 | AI45: =F7 -> 1 | AJ45: 0 | AK45: 0 | AL45: 0 | AM45: 0 | AN45: 0 | AO45: 0 | AP45: 0 | AQ45: 0 | AR45: 0 | AS45: 0 | AT45: 0
B46: Закуп маточного поголовья | D46: голов | E46: =Input!F40 -> 200 | J46: =$E$46*J45 -> 200 | K46: 0 | L46: 0 | M46: 0 | N46: 0 | O46: 0 | P46: 0 | Q46: 0 | R46: 0 | S46: =$F$46*S45 -> 0 | T46: 0 | U46: 0 | V46: 0 | W46: 0 | X46: 0 | Y46: 0 | Z46: 0 | AA46: 0 | AB46: 0 | AC46: 0 | AD46: 0 | AE46: 0 | AF46: 0 | AG46: 0 | AI46: =SUMIF($J$37:$AG$37,AI$37,$J46:$AG46) -> 200 | AJ46: =SUMIF($J$37:$AG$37,AJ$37,$J46:$AG46) -> 0 | AK46: 0 | AL46: =SUMIF($J$37:$AG$37,AL$37,$J46:$AG46) -> 0 | AM46: 0 | AN46: 0 | AO46: 0 | AP46: 0 | AQ46: 0 | AR46: 0 | AS46: 0 | AT46: 0
B47: Закуп быков производителей | D47: голов | E47: =ROUNDUP(E48,0) -> 14 | J47: =$E$47*J45 -> 14 | K47: 0 | L47: 0 | M47: 0 | N47: 0 | O47: 0 | P47: 0 | Q47: 0 | R47: 0 | S47: =F47 -> 0 | T47: 0 | U47: 0 | V47: 0 | W47: 0 | X47: 0 | Y47: 0 | Z47: 0 | AA47: 0 | AB47: 0 | AC47: 0 | AD47: 0 | AE47: 0 | AF47: 0 | AG47: 0 | AI47: =SUMIF($J$37:$AG$37,AI$37,$J47:$AG47) -> 14 | AJ47: =SUMIF($J$37:$AG$37,AJ$37,$J47:$AG47) -> 0 | AK47: 0 | AL47: =SUMIF($J$37:$AG$37,AL$37,$J47:$AG47) -> 0 | AM47: 0 | AN47: 0 | AO47: 0 | AP47: 0 | AQ47: 0 | AR47: 0 | AS47: 0 | AT47: 0
B48: Норма для быков производителей | D48: коэф-т | E48: =1/15*E46 -> 13.333333
B50: Маточное поголовье н.п. | D50: голов | J50: 0 | K50: =J57 -> 200 | L50: =K57 -> 199.5 | M50: =L57 -> 199.00125 | N50: =M57 -> 198.50375 | O50: =N57 -> 198.00749 | P50: =O57 -> 197.51247 | Q50: =P57 -> 197.01869 | R50: =Q57 -> 196.52614 | ... AG50: =AF57 -> 160.82024 | AI50: 0 | AJ50: =AI57 -> 198.00749 | AK50: =AJ57 -> 163.25379 | AL50: =AK57 -> 201.16948 | AM50: =AL57 -> 247.89109 | AN50: =AM57 -> 300 | AO50: =AN57 -> 300 | AP50: =AO57 -> 300 | AQ50: =AP57 -> 300 | ... AT50: =AS57 -> 300
B51: + | C51: Покупка маточного поголовья | D51: голов | J51: =J46 -> 200 | K51: =K46 -> 0 | L51: =L46 -> 0 | M51: =M46 -> 0 | N51: =N46 -> 0 | O51: =O46 -> 0 | P51: =P46 -> 0 | Q51: =Q46 -> 0 | ... AG51: =AG46 -> 0 | AI51: =SUMIF($J$37:$AG$37,AI$37,$J51:$AG51) -> 200 | AJ51: =SUMIF($J$37:$AG$37,AJ$37,$J51:$AG51) -> 0 | AK51: =AK46 -> 0 | AL51: =AL46 -> 0 | AM51: =AM46 -> 0 | AN51: =AN46 -> 0 | AO51: =AO46 -> 0 | AP51: =AP46 -> 0 | AQ51: =AQ46 -> 0 | AR51: =AR46 -> 0 | ... AT51: =AT46 -> 0
B52: + | C52: Перевод из телок | D52: голов | J52: =-J85 -> 0 | K52: =-K85 -> 0 | L52: =-L85 -> 0 | M52: =-M85 -> 0 | N52: =-N85 -> 0 | O52: =-O85 -> 0 | P52: =-P85 -> 0 | Q52: =-Q85 -> 0 | ... AG52: =-AG85 -> 0 | AI52: =SUMIF($J$37:$AG$37,AI$37,$J52:$AG52) -> 0 | AJ52: =SUMIF($J$37:$AG$37,AJ$37,$J52:$AG52) -> 0 | AK52: =-AK85 -> 67.301374 | AL52: =-AL85 -> 82.932118 | AM52: =-AM85 -> 102.1931 | AN52: =-AN85 -> 123.675 | AO52: =-AO85 -> 123.675 | AP52: =-AP85 -> 123.675 | AQ52: =-AQ85 -> 123.675 | AR52: =-AR85 -> 123.675 | ... AT52: =-AT85 -> 123.675
B53: - | C53: Выбраковка / отправка на откорм из-за состояния скота | D53: голов | E53: 0.15 | G53: =E53/12 -> 0.0125 | J53: 0 | K53: 0 | L53: 0 | M53: 0 | N53: 0 | O53: 0 | P53: 0 | Q53: 0 | R53: 0 | S53: 0 | T53: 0 | U53: 0 | V53: 0 | W53: 0 | X53: =-$E53*X$50 -> -29.039492 | Y53: 0 | Z53: 0 | AA53: 0 | AB53: 0 | AC53: 0 | AD53: 0 | AE53: 0 | AF53: 0 | AG53: 0 | AI53: =SUMIF($J$37:$AG$37,AI$37,$J53:$AG53) -> 0 | AJ53: =SUMIF($J$37:$AG$37,AJ$37,$J53:$AG53) -> -29.039492 | AK53: =-$E53*AK$50 -> -24.488068 | AL53: =-$E53*AL$50 -> -30.175422 | AM53: =-$E53*AM$50 -> -37.183664 | AN53: =-$E53*AN$50 -> -45 | AO53: =-$E53*AO$50 -> -45 | AP53: =-$E53*AP$50 -> -45 | AQ53: =-$E53*AQ$50 -> -45 | AR53: =-$E53*AR$50 -> -45 | ... AT53: =-$E53*AT$50 -> -45
B54: - | C54: Падеж маточного поголовья | D54: голов | E54: 0.03 | G54: =E54/12 -> 0.0025 | J54: =-$G54*J$50 -> 0 | K54: =-$G54*K$50 -> -0.5 | L54: =-$G54*L$50 -> -0.49875 | M54: =-$G54*M$50 -> -0.49750312 | N54: =-$G54*N$50 -> -0.49625937 | O54: =-$G54*O$50 -> -0.49501872 | P54: =-$G54*P$50 -> -0.49378117 | Q54: =-$G54*Q$50 -> -0.49254672 | ... AG54: =-$G54*AG$50 -> -0.40205059 | AI54: =SUMIF($J$37:$AG$37,AI$37,$J54:$AG54) -> -1.9925125 | AJ54: =SUMIF($J$37:$AG$37,AJ$37,$J54:$AG54) -> -5.7142074 | AK54: =-$E54*AK$50 -> -4.8976136 | AL54: =-$E54*AL$50 -> -6.0350844 | AM54: =-$E54*AM$50 -> -7.4367328 | AN54: =-$E54*AN$50 -> -9 | AO54: =-$E54*AO$50 -> -9 | AP54: =-$E54*AP$50 -> -9 | AQ54: =-$E54*AQ$50 -> -9 | AR54: =-$E54*AR$50 -> -9 | ... AT54: =-$E54*AT$50 -> -9
B55: Маточное поголовье промежуточно | J55: =SUM(J50:J54) -> 200 | K55: =SUM(K50:K54) -> 199.5 | L55: =SUM(L50:L54) -> 199.00125 | M55: =SUM(M50:M54) -> 198.50375 | N55: =SUM(N50:N54) -> 198.00749 | O55: =SUM(O50:O54) -> 197.51247 | P55: =SUM(P50:P54) -> 197.01869 | Q55: =SUM(Q50:Q54) -> 196.52614 | ... AG55: =SUM(AG50:AG54) -> 160.41819 | AI55: =SUM(AI50:AI54) -> 198.00749 | AJ55: =SUM(AJ50:AJ54) -> 163.25379 | AK55: =SUM(AK50:AK54) -> 201.16948 | AL55: =SUM(AL50:AL54) -> 247.89109 | AM55: =SUM(AM50:AM54) -> 305.4638 | AN55: =SUM(AN50:AN54) -> 369.675 | AO55: =SUM(AO50:AO54) -> 369.675 | AP55: =SUM(AP50:AP54) -> 369.675 | ... AT55: =SUM(AT50:AT54) -> 369.675
B56: - | C56: Продажа как племенной скот (телочки) | D56: голов | J56: =-MIN(J55-MIN(J55,J41)) -> 0 | K56: =-MIN(K55-MIN(K55,K41)) -> 0 | L56: =-MIN(L55-MIN(L55,L41)) -> 0 | M56: =-MIN(M55-MIN(M55,M41)) -> 0 | N56: =-MIN(N55-MIN(N55,N41)) -> 0 | O56: =-MIN(O55-MIN(O55,O41)) -> 0 | P56: =-MIN(P55-MIN(P55,P41)) -> 0 | Q56: =-MIN(Q55-MIN(Q55,Q41)) -> 0 | ... AG56: =-MIN(AG55-MIN(AG55,AG41)) -> 0 | AI56: =SUMIF($J$37:$AG$37,AI$37,$J56:$AG56) -> 0 | AJ56: =SUMIF($J$37:$AG$37,AJ$37,$J56:$AG56) -> 0 | AK56: =-MIN(AK55-MIN(AK55,AK41)) -> 0 | AL56: =-MIN(AL55-MIN(AL55,AL41)) -> 0 | AM56: =-MIN(AM55-MIN(AM55,AM41)) -> -5.4637988 | AN56: =-MIN(AN55-MIN(AN55,AN41)) -> -69.675 | AO56: =-MIN(AO55-MIN(AO55,AO41)) -> -69.675 | AP56: =-MIN(AP55-MIN(AP55,AP41)) -> -69.675 | AQ56: =-MIN(AQ55-MIN(AQ55,AQ41)) -> -69.675 | AR56: =-MIN(AR55-MIN(AR55,AR41)) -> -69.675 | ... AT56: =-MIN(AT55-MIN(AT55,AT41)) -> -69.675
B57: Маточное поголовье к.п. | D57: голов | J57: =SUM(J55:J56) -> 200 | K57: =SUM(K55:K56) -> 199.5 | L57: =SUM(L55:L56) -> 199.00125 | M57: =SUM(M55:M56) -> 198.50375 | N57: =SUM(N55:N56) -> 198.00749 | O57: =SUM(O55:O56) -> 197.51247 | P57: =SUM(P55:P56) -> 197.01869 | Q57: =SUM(Q55:Q56) -> 196.52614 | ... AG57: =SUM(AG55:AG56) -> 160.41819 | AI57: =SUM(AI55:AI56) -> 198.00749 | AJ57: =SUM(AJ55:AJ56) -> 163.25379 | AK57: =SUM(AK55:AK56) -> 201.16948 | AL57: =SUM(AL55:AL56) -> 247.89109 | AM57: =SUM(AM55:AM56) -> 300 | AN57: =SUM(AN55:AN56) -> 300 | AO57: =SUM(AO55:AO56) -> 300 | AP57: =SUM(AP55:AP56) -> 300 | ... AT57: =SUM(AT55:AT56) -> 300
B58: Среднее количество маточного поголовья | D58: голов | J58: =AVERAGE(J50+J51,J57) -> 200 | K58: =AVERAGE(K50+K51,K57) -> 199.75 | L58: =AVERAGE(L50+L51,L57) -> 199.25063 | M58: =AVERAGE(M50+M51,M57) -> 198.7525 | N58: =AVERAGE(N50+N51,N57) -> 198.25562 | O58: =AVERAGE(O50+O51,O57) -> 197.75998 | P58: =AVERAGE(P50+P51,P57) -> 197.26558 | Q58: =AVERAGE(Q50+Q51,Q57) -> 196.77241 | ... AG58: =AVERAGE(AG50+AG51,AG57) -> 160.61921 | AI58: =AVERAGE(AI50+AI51,AI57) -> 199.00374 | AJ58: =AVERAGE(AJ50+AJ51,AJ57) -> 180.63064 | AK58: =AVERAGE(AK50+AK51,AK57) -> 182.21163 | AL58: =AVERAGE(AL50+AL51,AL57) -> 224.53029 | AM58: =AVERAGE(AM50+AM51,AM57) -> 273.94555 | AN58: =AVERAGE(AN50+AN51,AN57) -> 300 | AO58: =AVERAGE(AO50+AO51,AO57) -> 300 | AP58: =AVERAGE(AP50+AP51,AP57) -> 300 | ... AT58: =AVERAGE(AT50+AT51,AT57) -> 300
B60: Быки-производители на н.п. | D60: голов | J60: 0 | K60: =J66 -> 14 | L60: =K66 -> 14 | M60: =L66 -> 14 | N60: =M66 -> 14 | O60: =N66 -> 14 | P60: =O66 -> 14 | Q60: =P66 -> 14 | R60: =Q66 -> 14 | ... AG60: =AF66 -> 13.791308 | AI60: 0 | AJ60: =AI66 -> 14 | AK60: =AJ66 -> 14 | AL60: =AK66 -> 10.883586 | AM60: =AL66 -> 13.411299 | AN60: =AM66 -> 16.526073 | AO60: =AN66 -> 20 | AP60: =AO66 -> 20 | AQ60: =AP66 -> 20 | ... AT60: =AS66 -> 20
B61: + | C61: Покупка Быков-производителей | D61: голов | J61: =J47 -> 14 | K61: =K47 -> 0 | L61: =L47 -> 0 | M61: =M47 -> 0 | N61: =N47 -> 0 | O61: =O47 -> 0 | P61: =P47 -> 0 | Q61: =Q47 -> 0 | ... AG61: =AG47 -> 0 | AI61: =SUMIF($J$37:$AG$37,AI$37,$J61:$AG61) -> 14 | AJ61: =SUMIF($J$37:$AG$37,AJ$37,$J61:$AG61) -> 0 | AK61: =AK47 -> 0 | AL61: =AL47 -> 0 | AM61: =AM47 -> 0 | AN61: =AN47 -> 0 | AO61: =AO47 -> 0 | AP61: =AP47 -> 0 | AQ61: =AQ47 -> 0 | AR61: =AR47 -> 0 | ... AT61: =AT47 -> 0
B62: + | C62: Перевод из бычков (до коэф. 1:15) | D62: голов | J62: =-J92 -> 0 | K62: =-K92 -> 0 | L62: =-L92 -> 0 | M62: =-M92 -> 0 | N62: =-N92 -> 0 | O62: =-O92 -> 0 | P62: =-P92 -> 0 | Q62: =-Q92 -> 0 | ... AG62: =-AG92 -> 0 | AI62: =SUMIF($J$37:$AG$37,AI$37,$J62:$AG62) -> 0 | AJ62: =SUMIF($J$37:$AG$37,AJ$37,$J62:$AG62) -> 0 | AK62: =-AK92 -> 0.80358589 | AL62: =-AL92 -> 5.5751169 | AM62: =-AM92 -> 6.8699378 | AN62: =-AN92 -> 8.1012276 | AO62: =-AO92 -> 5.6 | AP62: =-AP92 -> 5.6 | AQ62: =-AQ92 -> 5.6 | AR62: =-AR92 -> 5.6 | ... AT62: =-AT92 -> 5.6
B63: - | C63: Выбраковка / отправка на откорм из-за состояния скота | D63: голов | E63: 0.25 | G63: =E63/12 -> 0.020833333 | J63: =IF(J$35>17,-$G63*J$60,0) -> 0 | K63: =IF(K$35>17,-$G63*K$60,0) -> 0 | L63: =IF(L$35>17,-$G63*L$60,0) -> 0 | M63: =IF(M$35>17,-$G63*M$60,0) -> 0 | N63: =IF(N$35>17,-$G63*N$60,0) -> 0 | O63: =IF(O$35>17,-$G63*O$60,0) -> 0 | P63: =IF(P$35>17,-$G63*P$60,0) -> 0 | Q63: =IF(Q$35>17,-$G63*Q$60,0) -> 0 | ... Z63: =IF(Z$35>17,-$G63*Z$60,0) -> 0 | AA63: 0 | AB63: 0 | AC63: 0 | AD63: 0 | AE63: 0 | AF63: 0 | AG63: 0 | AI63: =SUMIF($J$37:$AG$37,AI$37,$J63:$AG63) -> 0 | AJ63: =SUMIF($J$37:$AG$37,AJ$37,$J63:$AG63) -> 0 | AK63: =-$E63*AK$60 -> -3.5 | AL63: =-$E63*AL$60 -> -2.7208965 | AM63: =-$E63*AM$60 -> -3.3528247 | AN63: =-$E63*AN$60 -> -4.1315182 | AO63: =-$E63*AO$60 -> -5 | AP63: =-$E63*AP$60 -> -5 | AQ63: =-$E63*AQ$60 -> -5 | AR63: =-$E63*AR$60 -> -5 | ... AT63: =-$E63*AT$60 -> -5
B64: - | C64: Падеж быков-производителей | D64: голов | E64: 0.03 | G64: =E64/12 -> 0.0025 | J64: =IF(J$35>17,-$G64*J$60,0) -> 0 | K64: =IF(K$35>17,-$G64*K$60,0) -> 0 | L64: =IF(L$35>17,-$G64*L$60,0) -> 0 | M64: =IF(M$35>17,-$G64*M$60,0) -> 0 | N64: =IF(N$35>17,-$G64*N$60,0) -> 0 | O64: =IF(O$35>17,-$G64*O$60,0) -> 0 | P64: =IF(P$35>17,-$G64*P$60,0) -> 0 | Q64: =IF(Q$35>17,-$G64*Q$60,0) -> 0 | ... AG64: =IF(AG$35>17,-$G64*AG$60,0) -> -0.03447827 | AI64: =SUMIF($J$37:$AG$37,AI$37,$J64:$AG64) -> 0 | AJ64: =SUMIF($J$37:$AG$37,AJ$37,$J64:$AG64) -> 0 | AK64: =-$E64*AK$60 -> -0.42 | AL64: =-$E64*AL$60 -> -0.32650758 | AM64: =-$E64*AM$60 -> -0.40233896 | AN64: =-$E64*AN$60 -> -0.49578219 | AO64: =-$E64*AO$60 -> -0.6 | AP64: =-$E64*AP$60 -> -0.6 | AQ64: =-$E64*AQ$60 -> -0.6 | AR64: =-$E64*AR$60 -> -0.6 | ... AT64: =-$E64*AT$60 -> -0.6
B65: - | C65: Продажа как племенной скот | D65: голов
B66: Быки-производители на к.п. | D66: голов | J66: =SUM(J60:J65) -> 14 | K66: =SUM(K60:K65) -> 14 | L66: =SUM(L60:L65) -> 14 | M66: =SUM(M60:M65) -> 14 | N66: =SUM(N60:N65) -> 14 | O66: =SUM(O60:O65) -> 14 | P66: =SUM(P60:P65) -> 14 | Q66: =SUM(Q60:Q65) -> 14 | ... AG66: =SUM(AG60:AG65) -> 13.75683 | AI66: =SUM(AI60:AI65) -> 14 | AJ66: =SUM(AJ60:AJ65) -> 14 | AK66: =SUM(AK60:AK65) -> 10.883586 | AL66: =SUM(AL60:AL65) -> 13.411299 | AM66: =SUM(AM60:AM65) -> 16.526073 | AN66: =SUM(AN60:AN65) -> 20 | AO66: =SUM(AO60:AO65) -> 20 | AP66: =SUM(AP60:AP65) -> 20 | ... AT66: =SUM(AT60:AT65) -> 20
B67: Среднее количество быков-производителей | D67: голов | J67: =AVERAGE(J60+J61,J66) -> 14 | K67: =AVERAGE(K60+K61,K66) -> 14 | L67: =AVERAGE(L60+L61,L66) -> 14 | M67: =AVERAGE(M60+M61,M66) -> 14 | N67: =AVERAGE(N60+N61,N66) -> 14 | O67: =AVERAGE(O60+O61,O66) -> 14 | P67: =AVERAGE(P60+P61,P66) -> 14 | Q67: =AVERAGE(Q60+Q61,Q66) -> 14 | ... AG67: =AVERAGE(AG60+AG61,AG66) -> 13.774069 | AI67: =AVERAGE(AI60,AI66) -> 7 | AJ67: =AVERAGE(AJ60,AJ66) -> 14 | AK67: =AVERAGE(AK60,AK66) -> 12.441793 | AL67: =AVERAGE(AL60,AL66) -> 12.147442 | AM67: =AVERAGE(AM60,AM66) -> 14.968686 | AN67: =AVERAGE(AN60,AN66) -> 18.263036 | AO67: =AVERAGE(AO60,AO66) -> 20 | AP67: =AVERAGE(AP60,AP66) -> 20 | ... AT67: =AVERAGE(AT60,AT66) -> 20
B69: Приплод на репродукторе на н.п. | D69: голов | J69: 0 | K69: =J76 -> 0 | L69: =K76 -> 0 | M69: =L76 -> 0 | N69: =M76 -> 0 | O69: =N76 -> 0 | P69: =O76 -> 0 | Q69: =P76 -> 0 | R69: =Q76 -> 0 | ... AG69: =AF76 -> 0 | AI69: 0 | AJ69: =AI76 -> 0 | AK69: =AJ76 -> 0 | AL69: =AK76 -> 0 | AM69: =AL76 -> 0 | AN69: =AM76 -> 0 | AO69: =AN76 -> 0 | AP69: =AO76 -> 0 | AQ69: =AP76 -> 0 | ... AT69: =AS76 -> 0
B70: + | C70: Новый приплод | D70: голов | E70: =Output!D189 -> 0.85 | G70: =IF(Input!F64="Зимний",18,12) -> 18 | J70: =IF(J35=$G$70,$E70*SUM(J50:J51),0) -> 0 | K70: =IF(K35=$G$70,$E70*SUM(K50:K51),0) -> 0 | L70: =IF(L35=$G$70,$E70*SUM(L50:L51),0) -> 0 | M70: =IF(M35=$G$70,$E70*SUM(M50:M51),0) -> 0 | N70: =IF(N35=$G$70,$E70*SUM(N50:N51),0) -> 0 | O70: =IF(O35=$G$70,$E70*SUM(O50:O51),0) -> 0 | P70: =IF(P35=$G$70,$E70*SUM(P50:P51),0) -> 0 | Q70: =IF(Q35=$G$70,$E70*SUM(Q50:Q51),0) -> 0 | ... AG70: =IF(AG35=$G$70,$E70*SUM(AG50:AG51),0) -> 0 | AI70: =SUMIF($J$37:$AG$37,AI$37,$J70:$AG70) -> 0 | AJ70: =SUMIF($J$37:$AG$37,AJ$37,$J70:$AG70) -> 0 | AK70: =$E70*SUM(AK50) -> 138.76572 | AL70: =$E70*SUM(AL50) -> 170.99406 | AM70: =$E70*SUM(AM50) -> 210.70743 | AN70: =$E70*SUM(AN50) -> 255 | AO70: =$E70*SUM(AO50) -> 255 | AP70: =$E70*SUM(AP50) -> 255 | AQ70: =$E70*SUM(AQ50) -> 255 | AR70: =$E70*SUM(AR50) -> 255 | ... AT70: =$E70*SUM(AT50) -> 255
B71: - | C71: Падеж приплода | D71: голов | J71: 0 | K71: 0 | L71: 0 | M71: 0 | N71: 0 | O71: 0 | P71: 0 | Q71: 0 | R71: 0 | S71: 0 | T71: 0 | U71: 0 | V71: 0 | W71: 0 | X71: 0 | Y71: 0 | Z71: 0 | AA71: 0 | AB71: 0 | AC71: 0 | AD71: 0 | AE71: 0 | AF71: 0 | AG71: 0 | AI71: =SUMIF($J$37:$AG$37,AI$37,$J71:$AG71) -> 0 | AJ71: =SUMIF($J$37:$AG$37,AJ$37,$J71:$AG71) -> 0 | AK71: 0 | AL71: 0 | AM71: 0 | AN71: 0 | AO71: 0 | AP71: 0 | AQ71: 0 | AR71: 0 | AS71: 0 | AT71: 0
B72: - | C72: Продажа как племенной скот | D72: голов | J72: 0 | K72: 0 | L72: 0 | M72: 0 | N72: 0 | O72: 0 | P72: 0 | Q72: 0 | R72: 0 | S72: 0 | T72: 0 | U72: 0 | V72: 0 | W72: 0 | X72: 0 | Y72: 0 | Z72: 0 | AA72: 0 | AB72: 0 | AC72: 0 | AD72: 0 | AE72: 0 | AF72: 0 | AG72: 0 | AI72: =SUMIF($J$37:$AG$37,AI$37,$J72:$AG72) -> 0 | AJ72: 0 | AK72: 0 | AL72: 0 | AM72: 0 | AN72: 0 | AO72: 0 | AP72: 0 | AQ72: 0 | AR72: 0 | AS72: 0 | AT72: 0
B73: Приплод до распределения | D73: голов | J73: =SUM(J69:J72) -> 0 | K73: =SUM(K69:K72) -> 0 | L73: =SUM(L69:L72) -> 0 | M73: =SUM(M69:M72) -> 0 | N73: =SUM(N69:N72) -> 0 | O73: =SUM(O69:O72) -> 0 | P73: =SUM(P69:P72) -> 0 | Q73: =SUM(Q69:Q72) -> 0 | ... AG73: =SUM(AG69:AG72) -> 0 | AI73: =SUM(AI69:AI72) -> 0 | AJ73: =SUM(AJ69:AJ72) -> 0 | AK73: =SUM(AK69:AK72) -> 138.76572 | AL73: =SUM(AL69:AL72) -> 170.99406 | AM73: =SUM(AM69:AM72) -> 210.70743 | AN73: =SUM(AN69:AN72) -> 255 | AO73: =SUM(AO69:AO72) -> 255 | AP73: =SUM(AP69:AP72) -> 255 | ... AT73: =SUM(AT69:AT72) -> 255
B74: - | C74: Перевод приплода в телочек | D74: голов | E74: 0.5 | J74: =-J73*$E$74 -> 0 | K74: =-K73*$E$74 -> 0 | L74: =-L73*$E$74 -> 0 | M74: =-M73*$E$74 -> 0 | N74: =-N73*$E$74 -> 0 | O74: =-O73*$E$74 -> 0 | P74: =-P73*$E$74 -> 0 | Q74: =-Q73*$E$74 -> 0 | ... AG74: =-AG73*$E$74 -> 0 | AI74: =SUMIF($J$37:$AG$37,AI$37,$J74:$AG74) -> 0 | AJ74: =SUMIF($J$37:$AG$37,AJ$37,$J74:$AG74) -> 0 | AK74: =-AK73*$E$74 -> -69.38286 | AL74: =-AL73*$E$74 -> -85.497029 | AM74: =-AM73*$E$74 -> -105.35371 | AN74: =-AN73*$E$74 -> -127.5 | AO74: =-AO73*$E$74 -> -127.5 | AP74: =-AP73*$E$74 -> -127.5 | AQ74: =-AQ73*$E$74 -> -127.5 | AR74: =-AR73*$E$74 -> -127.5 | ... AT74: =-AT73*$E$74 -> -127.5
B75: - | C75: Перевод приплода в бычков | D75: голов | E75: 0.5 | J75: =-J73*$E$75 -> 0 | K75: =-K73*$E$75 -> 0 | L75: =-L73*$E$75 -> 0 | M75: =-M73*$E$75 -> 0 | N75: =-N73*$E$75 -> 0 | O75: =-O73*$E$75 -> 0 | P75: =-P73*$E$75 -> 0 | Q75: =-Q73*$E$75 -> 0 | ... AG75: =-AG73*$E$75 -> 0 | AI75: =SUMIF($J$37:$AG$37,AI$37,$J75:$AG75) -> 0 | AJ75: =SUMIF($J$37:$AG$37,AJ$37,$J75:$AG75) -> 0 | AK75: =-AK73*$E$75 -> -69.38286 | AL75: =-AL73*$E$75 -> -85.497029 | AM75: =-AM73*$E$75 -> -105.35371 | AN75: =-AN73*$E$75 -> -127.5 | AO75: =-AO73*$E$75 -> -127.5 | AP75: =-AP73*$E$75 -> -127.5 | AQ75: =-AQ73*$E$75 -> -127.5 | AR75: =-AR73*$E$75 -> -127.5 | ... AT75: =-AT73*$E$75 -> -127.5
B76: Приплод на репродукторе на к.п. | D76: голов | J76: =SUM(J73:J75) -> 0 | K76: =SUM(K73:K75) -> 0 | L76: =SUM(L73:L75) -> 0 | M76: =SUM(M73:M75) -> 0 | N76: =SUM(N73:N75) -> 0 | O76: =SUM(O73:O75) -> 0 | P76: =SUM(P73:P75) -> 0 | Q76: =SUM(Q73:Q75) -> 0 | ... AG76: =SUM(AG73:AG75) -> 0 | AI76: =SUM(AI73:AI75) -> 0 | AJ76: =SUM(AJ73:AJ75) -> 0 | AK76: =SUM(AK73:AK75) -> 0 | AL76: =SUM(AL73:AL75) -> 0 | AM76: =SUM(AM73:AM75) -> 0 | AN76: =SUM(AN73:AN75) -> 0 | AO76: =SUM(AO73:AO75) -> 0 | AP76: =SUM(AP73:AP75) -> 0 | ... AT76: =SUM(AT73:AT75) -> 0
B77: Среднее количество приплода | D77: голов | J77: =AVERAGE(J76,J69) -> 0 | K77: =AVERAGE(K76,K69) -> 0 | L77: =AVERAGE(L76,L69) -> 0 | M77: =AVERAGE(M76,M69) -> 0 | N77: =AVERAGE(N76,N69) -> 0 | O77: =AVERAGE(O76,O69) -> 0 | P77: =AVERAGE(P76,P69) -> 0 | Q77: =AVERAGE(Q76,Q69) -> 0 | ... AG77: =AVERAGE(AG76,AG69) -> 0 | AI77: =AVERAGE(AI76,AI69) -> 0 | AJ77: =AVERAGE(AJ76,AJ69) -> 0 | AK77: =AVERAGE(AK76,AK69) -> 0 | AL77: =AVERAGE(AL76,AL69) -> 0 | AM77: =AVERAGE(AM76,AM69) -> 0 | AN77: =AVERAGE(AN76,AN69) -> 0 | AO77: =AVERAGE(AO76,AO69) -> 0 | AP77: =AVERAGE(AP76,AP69) -> 0 | ... AT77: =AVERAGE(AT76,AT69) -> 0
B79: Телочки на н.п. | D79: голов | J79: 0 | K79: =J87 -> 0 | L79: =K87 -> 0 | M79: =L87 -> 0 | N79: =M87 -> 0 | O79: =N87 -> 0 | P79: =O87 -> 0 | Q79: =P87 -> 0 | R79: =Q87 -> 0 | ... AG79: =AF87 -> 68.5199 | AI79: 0 | AJ79: =AI87 -> 0 | AK79: =AJ87 -> 0 | AL79: =AK87 -> 0 | AM79: =AL87 -> 0 | AN79: =AM87 -> 0 | AO79: =AN87 -> 0 | AP79: =AO87 -> 0 | AQ79: =AP87 -> 0 | ... AT79: =AS87 -> 0
B80: + | C80: Перевод из приплода | D80: голов | E80: 1 | J80: =-J74 -> 0 | K80: =-K74 -> 0 | L80: =-L74 -> 0 | M80: =-M74 -> 0 | N80: =-N74 -> 0 | O80: =-O74 -> 0 | P80: =-P74 -> 0 | Q80: =-Q74 -> 0 | ... AG80: =-AG74 -> 0 | AI80: =SUMIF($J$37:$AG$37,AI$37,$J80:$AG80) -> 0 | AJ80: =SUMIF($J$37:$AG$37,AJ$37,$J80:$AG80) -> 0 | AK80: =-AK74 -> 69.38286 | AL80: =-AL74 -> 85.497029 | AM80: =-AM74 -> 105.35371 | AN80: =-AN74 -> 127.5 | AO80: =-AO74 -> 127.5 | AP80: =-AP74 -> 127.5 | AQ80: =-AQ74 -> 127.5 | AR80: =-AR74 -> 127.5 | ... AT80: =-AT74 -> 127.5
B81: + | C81: Покупка | D81: голов | J81: 0 | K81: 0 | L81: 0 | M81: 0 | N81: 0 | O81: 0 | P81: 0 | Q81: 0 | R81: 0 | S81: 0 | T81: 0 | U81: 0 | V81: 0 | W81: 0 | X81: 0 | Y81: 0 | Z81: 0 | AA81: 0 | AB81: 0 | AC81: 0 | AD81: 0 | AE81: 0 | AF81: 0 | AG81: 0 | AI81: =SUMIF($J$37:$AG$37,AI$37,$J81:$AG81) -> 0 | AJ81: =SUMIF($J$37:$AG$37,AJ$37,$J81:$AG81) -> 0 | AK81: 0 | AL81: 0 | AM81: 0 | AN81: 0 | AO81: 0 | AP81: 0 | AQ81: 0 | AR81: 0 | AS81: 0 | AT81: 0
B82: - | C82: Падеж телочек | D82: голов | E82: 0.03 | G82: =E82/12 -> 0.0025 | J82: =-$E$82*SUM(J80:J81) -> 0 | K82: =-$E$82*SUM(K80:K81) -> 0 | L82: =-$E$82*SUM(L80:L81) -> 0 | M82: =-$E$82*SUM(M80:M81) -> 0 | N82: =-$E$82*SUM(N80:N81) -> 0 | O82: =-$E$82*SUM(O80:O81) -> 0 | P82: =-$E$82*SUM(P80:P81) -> 0 | Q82: =-$E$82*SUM(Q80:Q81) -> 0 | ... Y82: =-$E$82*SUM(Y80:Y81) -> 0 | Z82: =-$G$82*SUM(Z80:Z81) -> 0 | AA82: =IF(AA$35>17,-$G82*AA$79,0) -> 0 | AB82: =IF(AB$35>17,-$G82*AB$79,0) -> -0.17345715 | AC82: =IF(AC$35>17,-$G82*AC$79,0) -> -0.17302351 | AD82: =IF(AD$35>17,-$G82*AD$79,0) -> -0.17259095 | AE82: =IF(AE$35>17,-$G82*AE$79,0) -> -0.17215947 | AF82: =IF(AF$35>17,-$G82*AF$79,0) -> -0.17172907 | AG82: =IF(AG$35>17,-$G82*AG$79,0) -> -0.17129975 | AI82: =SUMIF($J$37:$AG$37,AI$37,$J82:$AG82) -> 0 | AJ82: =SUMIF($J$37:$AG$37,AJ$37,$J82:$AG82) -> 0 | AK82: =-$E$82*SUM(AK80:AK81) -> -2.0814858 | AL82: =-$E$82*SUM(AL80:AL81) -> -2.5649109 | AM82: =-$E$82*SUM(AM80:AM81) -> -3.1606114 | AN82: =-$E$82*SUM(AN80:AN81) -> -3.825 | AO82: =-$E$82*SUM(AO80:AO81) -> -3.825 | AP82: =-$E$82*SUM(AP80:AP81) -> -3.825 | AQ82: =-$E$82*SUM(AQ80:AQ81) -> -3.825 | AR82: =-$E$82*SUM(AR80:AR81) -> -3.825 | ... AT82: =-$E$82*SUM(AT80:AT81) -> -3.825
B83: - | C83: Продажа как племенной скот | J83: =-(J55-MIN(J55,J41)) -> 0 | K83: =-(J55-MIN(J55,J41)) -> 0 | L83: =-(K55-MIN(K55,K41)) -> 0 | M83: =-(L55-MIN(L55,L41)) -> 0 | N83: =-(M55-MIN(M55,M41)) -> 0 | O83: =-(N55-MIN(N55,N41)) -> 0 | P83: =-(O55-MIN(O55,O41)) -> 0 | Q83: =-(P55-MIN(P55,P41)) -> 0 | R83: =-(Q55-MIN(Q55,Q41)) -> 0 | ... AG83: =-(AF55-MIN(AF55,AF41)) -> 0 | AI83: =SUMIF($J$37:$AG$37,AI$37,$J83:$AG83) -> 0 | AJ83: =SUMIF($J$37:$AG$37,AJ$37,$J83:$AG83) -> 0 | AK83: =-(AI55-MIN(AI55,AI41)) -> 0 | AL83: =-(AI55-MIN(AI55,AI41)) -> 0 | AM83: =-(AI55-MIN(AI55,AI41)) -> 0
B84: Телочки до распределения | D84: голов | J84: =SUM(J79:J82) -> 0 | K84: =SUM(K79:K82) -> 0 | L84: =SUM(L79:L82) -> 0 | M84: =SUM(M79:M82) -> 0 | N84: =SUM(N79:N82) -> 0 | O84: =SUM(O79:O82) -> 0 | P84: =SUM(P79:P82) -> 0 | Q84: =SUM(Q79:Q82) -> 0 | ... AG84: =SUM(AG79:AG82) -> 68.3486 | AI84: =SUM(AI79:AI82) -> 0 | AJ84: =SUM(AJ79:AJ82) -> 0 | AK84: =SUM(AK79:AK82) -> 67.301374 | AL84: =SUM(AL79:AL82) -> 82.932118 | AM84: =SUM(AM79:AM82) -> 102.1931 | AN84: =SUM(AN79:AN82) -> 123.675 | AO84: =SUM(AO79:AO82) -> 123.675 | AP84: =SUM(AP79:AP82) -> 123.675 | ... AT84: =SUM(AT79:AT82) -> 123.675
B85: - | C85: Перевод в маточное поголовье | D85: голов | E85: 1 | F85: 0 | J85: 0 | K85: 0 | L85: 0 | M85: 0 | N85: 0 | O85: 0 | P85: 0 | Q85: 0 | R85: 0 | S85: 0 | T85: 0 | U85: 0 | V85: 0 | W85: 0 | X85: 0 | Y85: 0 | Z85: 0 | AA85: 0 | AB85: 0 | AC85: 0 | AD85: 0 | AE85: 0 | AF85: 0 | AG85: 0 | AI85: 0 | AJ85: 0 | AK85: =-MIN(OFFSET(AK84,,-$F85,,),AK84)*$E85 -> -67.301374 | AL85: =-MIN(OFFSET(AL84,,-$F85,,),AL84)*$E85 -> -82.932118 | AM85: =-MIN(OFFSET(AM84,,-$F85,,),AM84)*$E85 -> -102.1931 | AN85: =-MIN(OFFSET(AN84,,-$F85,,),AN84)*$E85 -> -123.675 | AO85: =-MIN(OFFSET(AO84,,-$F85,,),AO84)*$E85 -> -123.675 | AP85: =-MIN(OFFSET(AP84,,-$F85,,),AP84)*$E85 -> -123.675 | AQ85: =-MIN(OFFSET(AQ84,,-$F85,,),AQ84)*$E85 -> -123.675 | AR85: =-MIN(OFFSET(AR84,,-$F85,,),AR84)*$E85 -> -123.675 | ... AT85: =-MIN(OFFSET(AT84,,-$F85,,),AT84)*$E85 -> -123.675
B86: - | C86: Продажа как племенной скот | D86: голов | J86: =MAX(0,(J50+(-OFFSET(J84,,-$F85,,)*$E85)+J53+J54)) -> 0 | K86: 0 | L86: 0 | M86: 0 | N86: 0 | O86: 0 | P86: 0 | Q86: 0 | R86: 0 | S86: 0 | T86: 0 | U86: 0 | V86: 0 | W86: 0 | X86: 0 | Y86: 0 | Z86: 0 | AA86: 0 | AB86: 0 | AC86: 0 | AD86: 0 | AE86: 0 | AF86: 0 | AG86: 0 | AI86: =MAX(0,(AI50+(-OFFSET(AI84,,-$F85,,)*$E85)+AI53+AI54)) -> 0 | AJ86: 0 | AK86: 0 | AL86: 0 | AM86: 0 | AN86: 0 | AO86: 0 | AP86: 0 | AQ86: 0 | AR86: 0 | AS86: 0 | AT86: 0
B87: Телочки на к.п. | D87: голов | J87: =SUM(J84:J86) -> 0 | K87: =SUM(K84:K86) -> 0 | L87: =SUM(L84:L86) -> 0 | M87: =SUM(M84:M86) -> 0 | N87: =SUM(N84:N86) -> 0 | O87: =SUM(O84:O86) -> 0 | P87: =SUM(P84:P86) -> 0 | Q87: =SUM(Q84:Q86) -> 0 | ... AG87: =SUM(AG84:AG86) -> 68.3486 | AI87: =SUM(AI84:AI86) -> 0 | AJ87: =SUM(AJ84:AJ86) -> 0 | AK87: =SUM(AK84:AK86) -> 0 | AL87: =SUM(AL84:AL86) -> 0 | AM87: =SUM(AM84:AM86) -> 0 | AN87: =SUM(AN84:AN86) -> 0 | AO87: =SUM(AO84:AO86) -> 0 | AP87: =SUM(AP84:AP86) -> 0 | ... AT87: =SUM(AT84:AT86) -> 0
B88: Среднее количество телочек | D88: голов | J88: =AVERAGE(J79+J80,J87) -> 0 | K88: =AVERAGE(K79+K80,K87) -> 0 | L88: =AVERAGE(L79+L80,L87) -> 0 | M88: =AVERAGE(M79+M80,M87) -> 0 | N88: =AVERAGE(N79+N80,N87) -> 0 | O88: =AVERAGE(O79+O80,O87) -> 0 | P88: =AVERAGE(P79+P80,P87) -> 0 | Q88: =AVERAGE(Q79+Q80,Q87) -> 0 | ... AG88: =AVERAGE(AG79+AG80,AG87) -> 68.43425 | AI88: =AVERAGE(AI79+AI80,AI87) -> 0 | AJ88: =AVERAGE(AJ79+AJ80,AJ87) -> 0 | AK88: =AVERAGE(AK79+AK80,AK87) -> 34.69143 | AL88: =AVERAGE(AL79+AL80,AL87) -> 42.748515 | AM88: =AVERAGE(AM79+AM80,AM87) -> 52.676857 | AN88: =AVERAGE(AN79+AN80,AN87) -> 63.75 | AO88: =AVERAGE(AO79+AO80,AO87) -> 63.75 | AP88: =AVERAGE(AP79+AP80,AP87) -> 63.75 | ... AT88: =AVERAGE(AT79+AT80,AT87) -> 63.75
B90: Бычки на н.п. | D90: голов | J90: 0 | K90: =J96 -> 0 | L90: =K96 -> 0 | M90: =L96 -> 0 | N90: =M96 -> 0 | O90: =N96 -> 0 | P90: =O96 -> 0 | Q90: =P96 -> 0 | R90: =Q96 -> 0 | ... AG90: =AF96 -> 68.5199 | AI90: 0 | AJ90: =AI96 -> 0 | AK90: =AJ96 -> 0 | AL90: =AK96 -> 0 | AM90: =AL96 -> 0 | AN90: =AM96 -> 0 | AO90: =AN96 -> 0 | AP90: =AO96 -> 0 | AQ90: =AP96 -> 0 | ... AT90: =AS96 -> 0
B91: + | C91: Перевод из приплода | D91: голов | J91: =-J75 -> 0 | K91: =-K75 -> 0 | L91: =-L75 -> 0 | M91: =-M75 -> 0 | N91: =-N75 -> 0 | O91: =-O75 -> 0 | P91: =-P75 -> 0 | Q91: =-Q75 -> 0 | ... AG91: =-AG75 -> 0 | AI91: =SUMIF($J$37:$AG$37,AI$37,$J91:$AG91) -> 0 | AJ91: =SUMIF($J$37:$AG$37,AJ$37,$J91:$AG91) -> 0 | AK91: =-AK75 -> 69.38286 | AL91: =-AL75 -> 85.497029 | AM91: =-AM75 -> 105.35371 | AN91: =-AN75 -> 127.5 | AO91: =-AO75 -> 127.5 | AP91: =-AP75 -> 127.5 | AQ91: =-AQ75 -> 127.5 | AR91: =-AR75 -> 127.5 | ... AT91: =-AT75 -> 127.5
B92: - | C92: Перевод в быков-производителей | D92: голов | E92: =0.0666666666666667 -> 0.066666667 | J92: =-MAX(0,($E92*J50)-SUM(J60,J63:J65)) -> 0 | K92: =-MAX(0,($E92*K50)-SUM(K60,K63:K65)) -> 0 | L92: =-MAX(0,($E92*L50)-SUM(L60,L63:L65)) -> 0 | M92: =-MAX(0,($E92*M50)-SUM(M60,M63:M65)) -> 0 | N92: =-MAX(0,($E92*N50)-SUM(N60,N63:N65)) -> 0 | O92: =-MAX(0,($E92*O50)-SUM(O60,O63:O65)) -> 0 | P92: =-MAX(0,($E92*P50)-SUM(P60,P63:P65)) -> 0 | Q92: =-MAX(0,($E92*Q50)-SUM(Q60,Q63:Q65)) -> 0 | ... AG92: =-MAX(0,($E92*AG50)-SUM(AG60,AG63:AG65)) -> 0 | AI92: =SUMIF($J$37:$AG$37,AI$37,$J92:$AG92) -> 0 | AJ92: =SUMIF($J$37:$AG$37,AJ$37,$J92:$AG92) -> 0 | AK92: =-MAX(0,($E92*AK50)-SUM(AK60,AK63:AK65)) -> -0.80358589 | AL92: =-MAX(0,($E92*AL50)-SUM(AL60,AL63:AL65)) -> -5.5751169 | AM92: =-MAX(0,($E92*AM50)-SUM(AM60,AM63:AM65)) -> -6.8699378 | AN92: =-MAX(0,($E92*AN50)-SUM(AN60,AN63:AN65)) -> -8.1012276 | AO92: =-MAX(0,($E92*AO50)-SUM(AO60,AO63:AO65)) -> -5.6 | AP92: =-MAX(0,($E92*AP50)-SUM(AP60,AP63:AP65)) -> -5.6 | AQ92: =-MAX(0,($E92*AQ50)-SUM(AQ60,AQ63:AQ65)) -> -5.6 | AR92: =-MAX(0,($E92*AR50)-SUM(AR60,AR63:AR65)) -> -5.6 | ... AT92: =-MAX(0,($E92*AT50)-SUM(AT60,AT63:AT65)) -> -5.6
B93: - | C93: Падеж бычков | D93: голов | E93: 0.03 | G93: =E93/12 -> 0.0025 | J93: =-$E93*SUM(J90:J91) -> 0 | K93: =-$E93*SUM(K90:K91) -> 0 | L93: =-$E93*SUM(L90:L91) -> 0 | M93: =-$E93*SUM(M90:M91) -> 0 | N93: =-$E93*SUM(N90:N91) -> 0 | O93: =-$E93*SUM(O90:O91) -> 0 | P93: =-$E93*SUM(P90:P91) -> 0 | Q93: =-$E93*SUM(Q90:Q91) -> 0 | ... Y93: =-$E93*SUM(Y90:Y91) -> 0 | Z93: =-$G93*SUM(Z90:Z91) -> 0 | AA93: =IF(AA$35>17,-$G93*AA$90,0) -> 0 | AB93: =IF(AB$35>17,-$G93*AB$90,0) -> -0.17345715 | AC93: =IF(AC$35>17,-$G93*AC$90,0) -> -0.17302351 | AD93: =IF(AD$35>17,-$G93*AD$90,0) -> -0.17259095 | AE93: =IF(AE$35>17,-$G93*AE$90,0) -> -0.17215947 | AF93: =IF(AF$35>17,-$G93*AF$90,0) -> -0.17172907 | AG93: =IF(AG$35>17,-$G93*AG$90,0) -> -0.17129975 | AI93: =SUMIF($J$37:$AG$37,AI$37,$J93:$AG93) -> 0 | AJ93: =SUMIF($J$37:$AG$37,AJ$37,$J93:$AG93) -> 0 | AK93: =-$E93*SUM(AK90:AK91) -> -2.0814858 | AL93: =-$E93*SUM(AL90:AL91) -> -2.5649109 | AM93: =-$E93*SUM(AM90:AM91) -> -3.1606114 | AN93: =-$E93*SUM(AN90:AN91) -> -3.825 | AO93: =-$E93*SUM(AO90:AO91) -> -3.825 | AP93: =-$E93*SUM(AP90:AP91) -> -3.825 | AQ93: =-$E93*SUM(AQ90:AQ91) -> -3.825 | AR93: =-$E93*SUM(AR90:AR91) -> -3.825 | ... AT93: =-$E93*SUM(AT90:AT91) -> -3.825
B94: Бычки промежуточно | AJ94: =SUM(AJ90:AJ93) -> 0 | AK94: =SUM(AK90:AK93) -> 66.497788 | AL94: =SUM(AL90:AL93) -> 77.357002 | AM94: =SUM(AM90:AM93) -> 95.323165 | AN94: =SUM(AN90:AN93) -> 115.57377 | AO94: =SUM(AO90:AO93) -> 118.075 | AP94: =SUM(AP90:AP93) -> 118.075 | AQ94: =SUM(AQ90:AQ93) -> 118.075 | ... AT94: =SUM(AT90:AT93) -> 118.075
B95: - | C95: Продажа на финишный откорм | D95: голов | J95: 0 | K95: 0 | L95: 0 | M95: 0 | N95: 0 | O95: 0 | P95: 0 | Q95: 0 | R95: 0 | S95: 0 | T95: 0 | U95: 0 | V95: 0 | W95: 0 | X95: 0 | Y95: 0 | Z95: 0 | AA95: 0 | AB95: 0 | AC95: 0 | AD95: 0 | AE95: 0 | AF95: 0 | AG95: 0 | AI95: =SUMIF($J$37:$AG$37,AI$37,$J95:$AG95) -> 0 | AJ95: =SUMIF($J$37:$AG$37,AJ$37,$J95:$AG95) -> 0 | AK95: =-AK94 -> -66.497788 | AL95: =-AL94 -> -77.357002 | AM95: =-AM94 -> -95.323165 | AN95: =-AN94 -> -115.57377 | AO95: =-AO94 -> -118.075 | AP95: =-AP94 -> -118.075 | AQ95: =-AQ94 -> -118.075 | AR95: =-AR94 -> -118.075 | ... AT95: =-AT94 -> -118.075
B96: Бычки на к.п. | D96: голов | J96: =SUM(J90:J95) -> 0 | K96: =SUM(K90:K95) -> 0 | L96: =SUM(L90:L95) -> 0 | M96: =SUM(M90:M95) -> 0 | N96: =SUM(N90:N95) -> 0 | O96: =SUM(O90:O95) -> 0 | P96: =SUM(P90:P95) -> 0 | Q96: =SUM(Q90:Q95) -> 0 | ... AG96: =SUM(AG90:AG95) -> 68.3486 | AI96: =SUM(AI90:AI95) -> 0 | AJ96: =SUM(AJ94:AJ95) -> 0 | AK96: =SUM(AK94:AK95) -> 0 | AL96: =SUM(AL94:AL95) -> 0 | AM96: =SUM(AM94:AM95) -> 0 | AN96: =SUM(AN94:AN95) -> 0 | AO96: =SUM(AO94:AO95) -> 0 | AP96: =SUM(AP94:AP95) -> 0 | AQ96: =SUM(AQ94:AQ95) -> 0 | ... AT96: =SUM(AT94:AT95) -> 0
B97: Среднее количество бычков | D97: голов | J97: =AVERAGE(J90,J96) -> 0 | K97: =AVERAGE(K90,K96) -> 0 | L97: =AVERAGE(L90,L96) -> 0 | M97: =AVERAGE(M90,M96) -> 0 | N97: =AVERAGE(N90,N96) -> 0 | O97: =AVERAGE(O90,O96) -> 0 | P97: =AVERAGE(P90,P96) -> 0 | Q97: =AVERAGE(Q90,Q96) -> 0 | ... AG97: =AVERAGE(AG90,AG96) -> 68.43425 | AI97: =AVERAGE(AI90+AI91,AI96) -> 0 | AJ97: =AVERAGE(AJ90+AJ91,AJ96) -> 0 | AK97: =AVERAGE(AK90+AK91,AK96) -> 34.69143 | AL97: =AVERAGE(AL90+AL91,AL96) -> 42.748515 | AM97: =AVERAGE(AM90+AM91,AM96) -> 52.676857 | AN97: =AVERAGE(AN90+AN91,AN96) -> 63.75 | AO97: =AVERAGE(AO90+AO91,AO96) -> 63.75 | AP97: =AVERAGE(AP90+AP91,AP96) -> 63.75 | ... AT97: =AVERAGE(AT90+AT91,AT96) -> 63.75
C99: Максимальное количество | AI99: =SUM(AI55,AI66,AI94) -> 212.00749 | AJ99: =SUM(AJ55,AJ66,AJ94) -> 177.25379 | AK99: =SUM(AK55,AK66,AK94) -> 278.55085 | AL99: =SUM(AL55,AL66,AL94) -> 338.65939 | AM99: =SUM(AM55,AM66,AM94) -> 417.31304 | AN99: =SUM(AN55,AN66,AN94) -> 505.24877 | AO99: =SUM(AO55,AO66,AO94) -> 507.75 | AP99: =SUM(AP55,AP66,AP94) -> 507.75 | ... AT99: =SUM(AT55,AT66,AT94) -> 507.75
C100: Максимальное количество + без выбраковки+без падежей | AI100: =AI99-AI53-AI63-AI82-AI93-AI54 -> 214 | AJ100: =AJ99-AJ53-AJ63-AJ82-AJ93-AJ54 -> 212.00749 | AK100: =AK99-AK53-AK63-AK82-AK93-AK54 -> 315.59951 | AL100: =AL99-AL53-AL63-AL82-AL93-AL54 -> 382.72062 | AM100: =AM99-AM53-AM63-AM82-AM93-AM54 -> 471.60748 | AN100: =AN99-AN53-AN63-AN82-AN93-AN54 -> 571.03029 | AO100: =AO99-AO53-AO63-AO82-AO93-AO54 -> 574.4 | AP100: =AP99-AP53-AP63-AP82-AP93-AP54 -> 574.4 | ... AT100: =AT99-AT53-AT63-AT82-AT93-AT54 -> 574.4
C102: Среднее количество КРС | D102: голов | J102: =J58+J67+J77+J88+J97 -> 214 | K102: =K58+K67+K77+K88+K97 -> 213.75 | L102: =L58+L67+L77+L88+L97 -> 213.25063 | M102: =M58+M67+M77+M88+M97 -> 212.7525 | N102: =N58+N67+N77+N88+N97 -> 212.25562 | O102: =O58+O67+O77+O88+O97 -> 211.75998 | P102: =P58+P67+P77+P88+P97 -> 211.26558 | Q102: =Q58+Q67+Q77+Q88+Q97 -> 210.77241 | ... AG102: =AG58+AG67+AG77+AG88+AG97 -> 311.26178 | AI102: =AI58+AI67+AI77+AI88+AI97 -> 206.00374 | AJ102: =AJ58+AJ67+AJ77+AJ88+AJ97 -> 194.63064 | AK102: =AK58+AK67+AK77+AK88+AK97 -> 264.03629 | AL102: =AL58+AL67+AL77+AL88+AL97 -> 322.17476 | AM102: =AM58+AM67+AM77+AM88+AM97 -> 394.26795 | AN102: =AN58+AN67+AN77+AN88+AN97 -> 445.76304 | AO102: =AO58+AO67+AO77+AO88+AO97 -> 447.5 | AP102: =AP58+AP67+AP77+AP88+AP97 -> 447.5 | ... AT102: =AT58+AT67+AT77+AT88+AT97 -> 447.5
B104: Итого КРС на н.п. | D104: голов | J104: =J50+J60+J69+J79+J90 -> 0 | K104: =K50+K60+K69+K79+K90 -> 214 | L104: =L50+L60+L69+L79+L90 -> 213.5 | M104: =M50+M60+M69+M79+M90 -> 213.00125 | N104: =N50+N60+N69+N79+N90 -> 212.50375 | O104: =O50+O60+O69+O79+O90 -> 212.00749 | P104: =P50+P60+P69+P79+P90 -> 211.51247 | Q104: =Q50+Q60+Q69+Q79+Q90 -> 211.01869 | ... AG104: =AG50+AG60+AG69+AG79+AG90 -> 311.65134 | AI104: =AI50+AI60+AI69+AI79+AI90+AI51+AI61 -> 214 | AJ104: =AJ50+AJ60+AJ69+AJ79+AJ90+AJ51+AJ61 -> 212.00749 | AK104: =AK50+AK60+AK69+AK79+AK90 -> 177.25379 | AL104: =AL50+AL60+AL69+AL79+AL90 -> 212.05307 | AM104: =AM50+AM60+AM69+AM79+AM90 -> 261.30239 | AN104: =AN50+AN60+AN69+AN79+AN90 -> 316.52607 | AO104: =AO50+AO60+AO69+AO79+AO90 -> 320 | AP104: =AP50+AP60+AP69+AP79+AP90 -> 320 | AQ104: =AQ50+AQ60+AQ69+AQ79+AQ90 -> 320 | AR104: =AR50+AR60+AR69+AR79+AR90 -> 320 | ... AT104: =AT50+AT60+AT69+AT79+AT90 -> 320
B105: Итого КРС на к.п. | D105: голов | J105: =J57+J66+J76+J87+J96 -> 214 | K105: =K57+K66+K76+K87+K96 -> 213.5 | L105: =L57+L66+L76+L87+L96 -> 213.00125 | M105: =M57+M66+M76+M87+M96 -> 212.50375 | N105: =N57+N66+N76+N87+N96 -> 212.00749 | O105: =O57+O66+O76+O87+O96 -> 211.51247 | P105: =P57+P66+P76+P87+P96 -> 211.01869 | Q105: =Q57+Q66+Q76+Q87+Q96 -> 210.52614 | ... AG105: =AG57+AG66+AG76+AG87+AG96 -> 310.87222 | AI105: =AI57+AI66+AI76+AI87+AI96 -> 212.00749 | AJ105: =AJ57+AJ66+AJ76+AJ87+AJ96 -> 177.25379 | AK105: =AK57+AK66+AK76+AK87+AK96 -> 212.05307 | AL105: =AL57+AL66+AL76+AL87+AL96 -> 261.30239 | AM105: =AM57+AM66+AM76+AM87+AM96 -> 316.52607 | AN105: =AN57+AN66+AN76+AN87+AN96 -> 320 | AO105: =AO57+AO66+AO76+AO87+AO96 -> 320 | AP105: =AP57+AP66+AP76+AP87+AP96 -> 320 | ... AT105: =AT57+AT66+AT76+AT87+AT96 -> 320
AJ106: =AJ105/AI105-1 -> -0.16392675 | AK106: =AK105/AJ105-1 -> 0.1963246 | AL106: =AL105/AK105-1 -> 0.23225 | AM106: =AM105/AL105-1 -> 0.21134013 | AN106: =AN105/AM105-1 -> 0.010975169 | AO106: =AO105/AN105-1 -> 0 | AP106: =AP105/AO105-1 -> 0 | AQ106: =AQ105/AP105-1 -> 0 | ... AT106: =AT105/AS105-1 -> 0
B108: Стоимость поголовья на к.п. | D108: тыс. тенге | AI108: =SUM(AI109:AI112) -> 236948.09 | AJ108: =SUM(AJ109:AJ112) -> 220352.57 | AK108: =SUM(AK109:AK112) -> 285911.07 | AL108: =SUM(AL109:AL112) -> 385783.74 | AM108: =SUM(AM109:AM112) -> 509605.6 | AN108: =SUM(AN109:AN112) -> 561944.64 | AO108: =SUM(AO109:AO112) -> 606900.21 | AP108: =SUM(AP109:AP112) -> 649383.23 | ... AT108: =SUM(AT109:AT112) -> 808230.32
C109: Маточное поголовье | D109: тыс. тенге | AI109: =AI115*AI57/1000 -> 213848.09 | AJ109: =AJ115*AJ57/1000 -> 194827.07 | AK109: =AK115*AK57/1000 -> 264083.22 | AL109: =AL115*AL57/1000 -> 356331.13 | AM109: =AM115*AM57/1000 -> 470046.25 | AN109: =AN115*AN57/1000 -> 510000.18 | AO109: =AO115*AO57/1000 -> 550800.19 | AP109: =AP115*AP57/1000 -> 589356.21 | ... AT109: =AT115*AT57/1000 -> 733519.95
C110: Быки-производители | D110: тыс. тенге | AI110: =AI116*AI66/1000 -> 23100 | AJ110: =AJ116*AJ66/1000 -> 25525.5 | AK110: =AK116*AK66/1000 -> 21827.848 | AL110: =AL116*AL66/1000 -> 29452.615 | AM110: =AM116*AM66/1000 -> 39559.354 | AN110: =AN116*AN66/1000 -> 51944.463 | AO110: =AO116*AO66/1000 -> 56100.02 | AP110: =AP116*AP66/1000 -> 60027.021 | ... AT110: =AT116*AT66/1000 -> 74710.366
C111: Телочки | D111: тыс. тенге | AI111: =AI87*AI117/1000 -> 0 | AJ111: =AJ87*AJ117/1000 -> 0 | AK111: =AK87*AK117/1000 -> 0 | AL111: =AL87*AL117/1000 -> 0 | AM111: =AM87*AM117/1000 -> 0 | AN111: =AN87*AN117/1000 -> 0 | AO111: =AO87*AO117/1000 -> 0 | AP111: =AP87*AP117/1000 -> 0 | ... AT111: =AT87*AT117/1000 -> 0
C112: Бычки | D112: тыс. тенге | AI112: =ROUND(AI96*AI118/1000,-1) -> 0 | AJ112: =ROUND(AJ96*AJ118/1000,-1) -> 0 | AK112: =ROUND(AK96*AK118/1000,-1) -> 0 | AL112: =ROUND(AL96*AL118/1000,-1) -> 0 | AM112: =ROUND(AM96*AM118/1000,-1) -> 0 | AN112: =ROUND(AN96*AN118/1000,-1) -> 0 | AO112: =ROUND(AO96*AO118/1000,-1) -> 0 | AP112: =ROUND(AP96*AP118/1000,-1) -> 0 | ... AT112: =ROUND(AT96*AT118/1000,-1) -> 0
B114: Средняя цена за 1 голову
C115: Маточное поголовье | D115: тенге/голова | AI115: =$E$175*AI182 -> 1080000 | AJ115: =$E$175*AJ182 -> 1193400 | AK115: =$E$175*AK182 -> 1312740 | AL115: =$E$175*AL182 -> 1437450.3 | AM115: =$E$175*AM182 -> 1566820.8 | AN115: =$E$175*AN182 -> 1700000.6 | AO115: =$E$175*AO182 -> 1836000.6 | AP115: =$E$175*AP182 -> 1964520.7 | ... AT115: =$E$175*AT182 -> 2445066.5
C116: Быки-производители | D116: тенге/голова | AI116: =$E$176*AI183 -> 1650000 | AJ116: =$E$176*AJ183 -> 1823250 | AK116: =$E$176*AK183 -> 2005575 | AL116: =$E$176*AL183 -> 2196104.6 | AM116: =$E$176*AM183 -> 2393754 | AN116: =$E$176*AN183 -> 2597223.1 | AO116: =$E$176*AO183 -> 2805001 | AP116: =$E$176*AP183 -> 3001351.1 | ... AT116: =$E$176*AT183 -> 3735518.3
C117: Телочки | D117: тенге/голова | AI117: =$E$174*AI181 -> 608080 | AJ117: =$E$174*AJ181 -> 671928.4 | AK117: =$E$174*AK181 -> 739121.24 | AL117: =$E$174*AL181 -> 809337.76 | AM117: =$E$174*AM181 -> 882178.16 | AN117: =$E$174*AN181 -> 957163.3 | AO117: =$E$174*AO181 -> 1033736.4 | AP117: =$E$174*AP181 -> 1106097.9 | ... AT117: =$E$174*AT181 -> 1376663
C118: Бычки | D118: тенге/голова | AI118: =$E$177*AI184 -> 728200 | AJ118: =$E$177*AJ184 -> 804661 | AK118: =$E$177*AK184 -> 885127.1 | AL118: =$E$177*AL184 -> 969214.17 | AM118: =$E$177*AM184 -> 1056443.5 | AN118: =$E$177*AN184 -> 1146241.1 | AO118: =$E$177*AO184 -> 1237940.4 | AP118: =$E$177*AP184 -> 1324596.3 | ... AT118: =$E$177*AT184 -> 1648608.7
B120: Изменение стоимости поголовья | D120: тыс. тенге | J120: =SUM(J121:J124) -> 119100 | AI120: =SUM(AI121:AI124) -> 117848.09 | AJ120: =SUM(AJ121:AJ124) -> -16595.516 | AK120: =SUM(AK121:AK124) -> 65558.501 | AL120: =SUM(AL121:AL124) -> 99872.669 | AM120: =SUM(AM121:AM124) -> 123821.86 | AN120: =SUM(AN121:AN124) -> 52339.04 | AO120: =SUM(AO121:AO124) -> 44955.571 | AP120: =SUM(AP121:AP124) -> 42483.015 | ... AT120: =SUM(AT121:AT124) -> 38487.158
C121: Маточное поголовье | D121: тыс. тенге | J121: =F22 -> 110000 | AI121: =AI109-J121 -> 103848.09 | AJ121: =AJ109-AI109 -> -19021.016 | AK121: =AK109-AJ109 -> 69256.153 | AL121: =AL109-AK109 -> 92247.901 | AM121: =AM109-AL109 -> 113715.12 | AN121: =AN109-AM109 -> 39953.931 | AO121: =AO109-AN109 -> 40800.014 | AP121: =AP109-AO109 -> 38556.014 | AQ121: =AQ109-AP109 -> 38308.153 | ... AT121: =AT109-AS109 -> 34929.522
...

Sheet Cattle Feeding Cycle
C1: 46235
A3: х | B3: Рационы питания
B4: Кол-во дней в месяце | J4: =J5-C1 -> 30 | K4: =K5-J5 -> 30 | L4: =L5-K5 -> 31 | M4: =M5-L5 -> 30 | N4: =N5-M5 -> 31 | O4: =O5-N5 -> 31 | P4: =P5-O5 -> 28 | Q4: =Q5-P5 -> 31 | R4: =R5-Q5 -> 30 | ... AG4: =AG5-AF5 -> 31 | AI4: =SUM(J4:N4) -> 152 | AJ4: =DATE(AJ5,12,31)-DATE(AI5,12,31) -> 365 | AK4: =DATE(AK5,12,31)-DATE(AJ5,12,31) -> 366 | AL4: =DATE(AL5,12,31)-DATE(AK5,12,31) -> 365 | AM4: =DATE(AM5,12,31)-DATE(AL5,12,31) -> 365 | AN4: =DATE(AN5,12,31)-DATE(AM5,12,31) -> 365 | AO4: =DATE(AO5,12,31)-DATE(AN5,12,31) -> 366 | AP4: =DATE(AP5,12,31)-DATE(AO5,12,31) -> 365 | AQ4: =DATE(AQ5,12,31)-DATE(AP5,12,31) -> 365 | ... AT4: =DATE(AT5,12,31)-DATE(AS5,12,31) -> 365
B5: Типовой суточный рацион питания на 1 КРС | J5: 46265 | K5: =EOMONTH(J5,1) -> 46295 | L5: =EOMONTH(K5,1) -> 46326 | M5: =EOMONTH(L5,1) -> 46356 | N5: =EOMONTH(M5,1) -> 46387 | O5: =EOMONTH(N5,1) -> 46418 | P5: =EOMONTH(O5,1) -> 46446 | Q5: =EOMONTH(P5,1) -> 46477 | R5: =EOMONTH(Q5,1) -> 46507 | ... AG5: =EOMONTH(AF5,1) -> 46965 | AI5: =AI146 -> 2026 | AJ5: =AJ146 -> 2027 | AK5: =AK146 -> 2028 | AL5: =AL146 -> 2029 | AM5: =AM146 -> 2030 | AN5: =AN146 -> 2031 | AO5: =AO146 -> 2032 | AP5: =AP146 -> 2033 | ... AT5: =AT146 -> 2037
B7: Маточное поголовье полный год
C8: Зеленая масса | D8: кг | J8: 32 | K8: 32 | L8: 32 | M8: 0 | N8: 0 | O8: 0 | P8: 0 | Q8: 0 | R8: 0 | S8: 32 | T8: 32 | U8: 32 | V8: 32 | W8: 32 | X8: 32 | Y8: 0 | Z8: 0 | AA8: 0 | AB8: 0 | AC8: 0 | AD8: 0 | AE8: 32 | AF8: 32 | AG8: 32 | AI8: =SUMPRODUCT(J8:N8,J$4:N$4) -> 2912 | AJ8: =SUMPRODUCT(O8:Z8,O$4:Z$4) -> 5888 | AK8: =AJ8 -> 5888 | AL8: =AK8 -> 5888 | AM8: =AL8 -> 5888 | AN8: =AM8 -> 5888 | AO8: =AN8 -> 5888 | AP8: =AO8 -> 5888 | AQ8: =AP8 -> 5888 | AR8: =AQ8 -> 5888 | ... AT8: =AS8 -> 5888
C9: Концентраты | D9: кг | J9: 0 | K9: 0 | L9: 0 | M9: 2 | N9: 2 | O9: 2 | P9: 2 | Q9: 2 | R9: 2 | S9: 0 | T9: 0 | U9: 0 | V9: 0 | W9: 0 | X9: 0 | Y9: 2 | Z9: 2 | AA9: 2 | AB9: 2 | AC9: 2 | AD9: 2 | AE9: 0 | AF9: 0 | AG9: 0 | AI9: =SUMPRODUCT(J9:N9,J$4:N$4) -> 122 | AJ9: =SUMPRODUCT(O9:Z9,O$4:Z$4) -> 362 | AK9: =AJ9 -> 362 | AL9: =AK9 -> 362 | AM9: =AL9 -> 362 | AN9: =AM9 -> 362 | AO9: =AN9 -> 362 | AP9: =AO9 -> 362 | AQ9: =AP9 -> 362 | AR9: =AQ9 -> 362 | ... AT9: =AS9 -> 362
C10: Соль поваренная | D10: кг | J10: 0.05 | K10: 0.05 | L10: 0.05 | M10: 0.06 | N10: 0.06 | O10: 0.057 | P10: 0.057 | Q10: 0.057 | R10: 0.057 | S10: 0.05 | T10: 0.05 | U10: 0.05 | V10: 0.05 | W10: 0.05 | X10: 0.05 | Y10: 0.06 | Z10: 0.06 | AA10: 0.057 | AB10: 0.057 | AC10: 0.057 | AD10: 0.057 | AE10: 0.05 | AF10: 0.05 | AG10: 0.05 | AI10: =SUMPRODUCT(J10:N10,J$4:N$4) -> 8.21 | AJ10: =SUMPRODUCT(O10:Z10,O$4:Z$4) -> 19.7 | AK10: =AJ10 -> 19.7 | AL10: =AK10 -> 19.7 | AM10: =AL10 -> 19.7 | AN10: =AM10 -> 19.7 | AO10: =AN10 -> 19.7 | AP10: =AO10 -> 19.7 | AQ10: =AP10 -> 19.7 | AR10: =AQ10 -> 19.7 | ... AT10: =AS10 -> 19.7
C11: Сено | D11: кг | J11: 0 | K11: 0 | L11: 0 | M11: 8 | N11: 8 | O11: 6 | P11: 6 | Q11: 6 | R11: 6 | S11: 0 | T11: 0 | U11: 0 | V11: 0 | W11: 0 | X11: 0 | Y11: 8 | Z11: 8 | AA11: 6 | AB11: 6 | AC11: 6 | AD11: 6 | AE11: 0 | AF11: 0 | AG11: 0 | AI11: =SUMPRODUCT(J11:N11,J$4:N$4) -> 488 | AJ11: =SUMPRODUCT(O11:Z11,O$4:Z$4) -> 1208 | AK11: =AJ11 -> 1208 | AL11: =AK11 -> 1208 | AM11: =AL11 -> 1208 | AN11: =AM11 -> 1208 | AO11: =AN11 -> 1208 | AP11: =AO11 -> 1208 | AQ11: =AP11 -> 1208 | AR11: =AQ11 -> 1208 | ... AT11: =AS11 -> 1208
C12: Солома | D12: кг | J12: 0 | K12: 0 | L12: 0 | M12: 2 | N12: 2 | O12: 2 | P12: 2 | Q12: 2 | R12: 2 | S12: 0 | T12: 0 | U12: 0 | V12: 0 | W12: 0 | X12: 0 | Y12: 2 | Z12: 2 | AA12: 2 | AB12: 2 | AC12: 2 | AD12: 2 | AE12: 0 | AF12: 0 | AG12: 0 | AI12: =SUMPRODUCT(J12:N12,J$4:N$4) -> 122 | AJ12: =SUMPRODUCT(O12:Z12,O$4:Z$4) -> 362 | AK12: =AJ12 -> 362 | AL12: =AK12 -> 362 | AM12: =AL12 -> 362 | AN12: =AM12 -> 362 | AO12: =AN12 -> 362 | AP12: =AO12 -> 362 | AQ12: =AP12 -> 362 | AR12: =AQ12 -> 362 | ... AT12: =AS12 -> 362
C13: Отруби/шрот | D13: кг | J13: 0 | K13: 0 | L13: 0 | M13: 1 | N13: 1 | O13: 1 | P13: 1 | Q13: 1 | R13: 1 | S13: 0 | T13: 0 | U13: 0 | V13: 0 | W13: 0 | X13: 0 | Y13: 1 | Z13: 1 | AA13: 1 | AB13: 1 | AC13: 1 | AD13: 1 | AE13: 0 | AF13: 0 | AG13: 0 | AI13: =SUMPRODUCT(J13:N13,J$4:N$4) -> 61 | AJ13: =SUMPRODUCT(O13:Z13,O$4:Z$4) -> 181 | AK13: =AJ13 -> 181 | AL13: =AK13 -> 181 | AM13: =AL13 -> 181 | AN13: =AM13 -> 181 | AO13: =AN13 -> 181 | AP13: =AO13 -> 181 | AQ13: =AP13 -> 181 | AR13: =AQ13 -> 181 | ... AT13: =AS13 -> 181
C14: Диаммонийфосфат (премикс) | D14: кг | J14: 0 | K14: 0 | L14: 0 | M14: 0.04 | N14: 0.04 | O14: 0.03 | P14: 0.03 | Q14: 0.03 | R14: 0.03 | S14: 0 | T14: 0 | U14: 0 | V14: 0 | W14: 0 | X14: 0 | Y14: 0.04 | Z14: 0.04 | AA14: 0.03 | AB14: 0.03 | AC14: 0.03 | AD14: 0.03 | AE14: 0 | AF14: 0 | AG14: 0 | AI14: =SUMPRODUCT(J14:N14,J$4:N$4) -> 2.44 | AJ14: =SUMPRODUCT(O14:Z14,O$4:Z$4) -> 6.04 | AK14: =AJ14 -> 6.04 | AL14: =AK14 -> 6.04 | AM14: =AL14 -> 6.04 | AN14: =AM14 -> 6.04 | AO14: =AN14 -> 6.04 | AP14: =AO14 -> 6.04 | AQ14: =AP14 -> 6.04 | AR14: =AQ14 -> 6.04 | ... AT14: =AS14 -> 6.04
C15: Монокальцийфосфат (премикс) | D15: кг | J15: 0 | K15: 0 | L15: 0 | M15: 0.045 | N15: 0.045 | O15: 0.055 | P15: 0.055 | Q15: 0.055 | R15: 0.055 | S15: 0 | T15: 0 | U15: 0 | V15: 0 | W15: 0 | X15: 0 | Y15: 0.045 | Z15: 0.045 | AA15: 0.055 | AB15: 0.055 | AC15: 0.055 | AD15: 0.055 | AE15: 0 | AF15: 0 | AG15: 0 | AI15: =SUMPRODUCT(J15:N15,J$4:N$4) -> 2.745 | AJ15: =SUMPRODUCT(O15:Z15,O$4:Z$4) -> 9.345 | AK15: =AJ15 -> 9.345 | AL15: =AK15 -> 9.345 | AM15: =AL15 -> 9.345 | AN15: =AM15 -> 9.345 | AO15: =AN15 -> 9.345 | AP15: =AO15 -> 9.345 | AQ15: =AP15 -> 9.345 | AR15: =AQ15 -> 9.345 | ... AT15: =AS15 -> 9.345
B17: Маточное поголовье 9 мес.
C18: Зеленая масса | D18: кг | R18: 0 | S18: 32 | T18: 32 | U18: 32 | V18: 32 | W18: 32 | X18: 32 | Y18: 0 | Z18: 0 | AA18: 0 | AB18: 0 | AC18: 0 | AD18: 0 | AE18: 32 | AF18: 32 | AG18: 32 | AI18: =SUMPRODUCT(J18:N18,J$4:N$4) -> 0 | AJ18: =SUMPRODUCT(O18:Z18,O$4:Z$4) -> 5888 | AK18: =AJ18 -> 5888 | AL18: =AK18 -> 5888 | AM18: =AL18 -> 5888 | AN18: =AM18 -> 5888 | AO18: =AN18 -> 5888 | AP18: =AO18 -> 5888 | AQ18: =AP18 -> 5888 | AR18: =AQ18 -> 5888 | ... AT18: =AS18 -> 5888
C19: Концентраты | D19: кг | R19: 2 | S19: 0 | T19: 0 | U19: 0 | V19: 0 | W19: 0 | X19: 0 | Y19: 2 | Z19: 2 | AA19: 2 | AB19: 2 | AC19: 2 | AD19: 2 | AE19: 0 | AF19: 0 | AG19: 0 | AI19: =SUMPRODUCT(J19:N19,J$4:N$4) -> 0 | AJ19: =SUMPRODUCT(O19:Z19,O$4:Z$4) -> 182 | AK19: =AJ19 -> 182 | AL19: =AK19 -> 182 | AM19: =AL19 -> 182 | AN19: =AM19 -> 182 | AO19: =AN19 -> 182 | AP19: =AO19 -> 182 | AQ19: =AP19 -> 182 | AR19: =AQ19 -> 182 | ... AT19: =AS19 -> 182
C20: Соль поваренная | D20: кг | R20: 0.057 | S20: 0.05 | T20: 0.05 | U20: 0.05 | V20: 0.05 | W20: 0.05 | X20: 0.05 | Y20: 0.06 | Z20: 0.06 | AA20: 0.057 | AB20: 0.057 | AC20: 0.057 | AD20: 0.057 | AE20: 0.05 | AF20: 0.05 | AG20: 0.05 | AI20: =SUMPRODUCT(J20:N20,J$4:N$4) -> 0 | AJ20: =SUMPRODUCT(O20:Z20,O$4:Z$4) -> 14.57 | AK20: =AJ20 -> 14.57 | AL20: =AK20 -> 14.57 | AM20: =AL20 -> 14.57 | AN20: =AM20 -> 14.57 | AO20: =AN20 -> 14.57 | AP20: =AO20 -> 14.57 | AQ20: =AP20 -> 14.57 | AR20: =AQ20 -> 14.57 | ... AT20: =AS20 -> 14.57
C21: Сено | D21: кг | R21: 7 | S21: 0 | T21: 0 | U21: 0 | V21: 0 | W21: 0 | X21: 0 | Y21: 8 | Z21: 8 | AA21: 7 | AB21: 7 | AC21: 7 | AD21: 7 | AE21: 0 | AF21: 0 | AG21: 0 | AI21: =SUMPRODUCT(J21:N21,J$4:N$4) -> 0 | AJ21: =SUMPRODUCT(O21:Z21,O$4:Z$4) -> 698 | AK21: =AJ21 -> 698 | AL21: =AK21 -> 698 | AM21: =AL21 -> 698 | AN21: =AM21 -> 698 | AO21: =AN21 -> 698 | AP21: =AO21 -> 698 | AQ21: =AP21 -> 698 | AR21: =AQ21 -> 698 | ... AT21: =AS21 -> 698
C22: Солома | D22: кг | R22: 2 | S22: 0 | T22: 0 | U22: 0 | V22: 0 | W22: 0 | X22: 0 | Y22: 2 | Z22: 2 | AA22: 2 | AB22: 2 | AC22: 2 | AD22: 2 | AE22: 0 | AF22: 0 | AG22: 0 | AI22: =SUMPRODUCT(J22:N22,J$4:N$4) -> 0 | AJ22: =SUMPRODUCT(O22:Z22,O$4:Z$4) -> 182 | AK22: =AJ22 -> 182 | AL22: =AK22 -> 182 | AM22: =AL22 -> 182 | AN22: =AM22 -> 182 | AO22: =AN22 -> 182 | AP22: =AO22 -> 182 | AQ22: =AP22 -> 182 | AR22: =AQ22 -> 182 | ... AT22: =AS22 -> 182
C23: Отруби/шрот | D23: кг | R23: 1 | S23: 0 | T23: 0 | U23: 0 | V23: 0 | W23: 0 | X23: 0 | Y23: 1 | Z23: 1 | AA23: 1 | AB23: 1 | AC23: 1 | AD23: 1 | AE23: 0 | AF23: 0 | AG23: 0 | AI23: =SUMPRODUCT(J23:N23,J$4:N$4) -> 0 | AJ23: =SUMPRODUCT(O23:Z23,O$4:Z$4) -> 91 | AK23: =AJ23 -> 91 | AL23: =AK23 -> 91 | AM23: =AL23 -> 91 | AN23: =AM23 -> 91 | AO23: =AN23 -> 91 | AP23: =AO23 -> 91 | AQ23: =AP23 -> 91 | AR23: =AQ23 -> 91 | ... AT23: =AS23 -> 91
C24: Диаммонийфосфат (премикс) | D24: кг | R24: 0.03 | S24: 0 | T24: 0 | U24: 0 | V24: 0 | W24: 0 | X24: 0 | Y24: 0.04 | Z24: 0.04 | AA24: 0.03 | AB24: 0.03 | AC24: 0.03 | AD24: 0.03 | AE24: 0 | AF24: 0 | AG24: 0 | AI24: =SUMPRODUCT(J24:N24,J$4:N$4) -> 0 | AJ24: =SUMPRODUCT(O24:Z24,O$4:Z$4) -> 3.34 | AK24: =AJ24 -> 3.34 | AL24: =AK24 -> 3.34 | AM24: =AL24 -> 3.34 | AN24: =AM24 -> 3.34 | AO24: =AN24 -> 3.34 | AP24: =AO24 -> 3.34 | AQ24: =AP24 -> 3.34 | AR24: =AQ24 -> 3.34 | ... AT24: =AS24 -> 3.34
C25: Монокальцийфосфат (премикс) | D25: кг | R25: 0.055 | S25: 0 | T25: 0 | U25: 0 | V25: 0 | W25: 0 | X25: 0 | Y25: 0.045 | Z25: 0.045 | AA25: 0.055 | AB25: 0.055 | AC25: 0.055 | AD25: 0.055 | AE25: 0 | AF25: 0 | AG25: 0 | AI25: =SUMPRODUCT(J25:N25,J$4:N$4) -> 0 | AJ25: =SUMPRODUCT(O25:Z25,O$4:Z$4) -> 4.395 | AK25: =AJ25 -> 4.395 | AL25: =AK25 -> 4.395 | AM25: =AL25 -> 4.395 | AN25: =AM25 -> 4.395 | AO25: =AN25 -> 4.395 | AP25: =AO25 -> 4.395 | AQ25: =AP25 -> 4.395 | AR25: =AQ25 -> 4.395 | ... AT25: =AS25 -> 4.395
B27: Быки-производители | M27: =M28*M4 -> 0 | N27: =N28*N4 -> 0
C28: Зеленая масса | D28: кг | J28: 12 | K28: 12 | L28: 12 | M28: 0 | N28: 0 | O28: 0 | P28: 0 | Q28: 0 | R28: 0 | S28: 12 | T28: 12 | U28: 12 | V28: 12 | W28: 12 | X28: 12 | Y28: 0 | Z28: 0 | AA28: 0 | AB28: 0 | AC28: 0 | AD28: 0 | AE28: 12 | AF28: 12 | AG28: 12 | AI28: =SUMPRODUCT(J28:N28,J$4:N$4) -> 1092 | AJ28: =SUMPRODUCT(O28:Z28,O$4:Z$4) -> 2208 | AK28: =AJ28 -> 2208 | AL28: =AK28 -> 2208 | AM28: =AL28 -> 2208 | AN28: =AM28 -> 2208 | AO28: =AN28 -> 2208 | AP28: =AO28 -> 2208 | AQ28: =AP28 -> 2208 | AR28: =AQ28 -> 2208 | ... AT28: =AS28 -> 2208
C29: Сено | D29: кг | J29: 0 | K29: 0 | L29: 0 | M29: 8 | N29: 8 | O29: 8 | P29: 8 | Q29: 8 | R29: 8 | S29: 0 | T29: 0 | U29: 0 | V29: 0 | W29: 0 | X29: 0 | Y29: 8 | Z29: 8 | AA29: 8 | AB29: 8 | AC29: 8 | AD29: 8 | AE29: 0 | AF29: 0 | AG29: 0 | AI29: =SUMPRODUCT(J29:N29,J$4:N$4) -> 488 | AJ29: =SUMPRODUCT(O29:Z29,O$4:Z$4) -> 1448 | AK29: =AJ29 -> 1448 | AL29: =AK29 -> 1448 | AM29: =AL29 -> 1448 | AN29: =AM29 -> 1448 | AO29: =AN29 -> 1448 | AP29: =AO29 -> 1448 | AQ29: =AP29 -> 1448 | AR29: =AQ29 -> 1448 | ... AT29: =AS29 -> 1448
C30: Отруби/шрот | D30: кг | J30: 0 | K30: 0 | L30: 0 | M30: 1 | N30: 1 | O30: 1 | P30: 1 | Q30: 1 | R30: 1 | S30: 0 | T30: 0 | U30: 0 | V30: 0 | W30: 0 | X30: 0 | Y30: 1 | Z30: 1 | AA30: 1 | AB30: 1 | AC30: 1 | AD30: 1 | AE30: 0 | AF30: 0 | AG30: 0 | AI30: =SUMPRODUCT(J30:N30,J$4:N$4) -> 61 | AJ30: =SUMPRODUCT(O30:Z30,O$4:Z$4) -> 181 | AK30: =AJ30 -> 181 | AL30: =AK30 -> 181 | AM30: =AL30 -> 181 | AN30: =AM30 -> 181 | AO30: =AN30 -> 181 | AP30: =AO30 -> 181 | AQ30: =AP30 -> 181 | AR30: =AQ30 -> 181 | ... AT30: =AS30 -> 181
C31: Концентраты | D31: кг | J31: 0 | K31: 0 | L31: 0 | M31: =3.5-0.72 -> 2.78 | N31: =3.5-0.72 -> 2.78 | O31: =3.5-0.72 -> 2.78 | P31: =3.5-0.72 -> 2.78 | Q31: =3.5-0.72 -> 2.78 | R31: =3.5-0.72 -> 2.78 | S31: 0 | T31: 0 | U31: 0 | V31: 0 | W31: 0 | X31: 0 | Y31: =3.5-0.72 -> 2.78 | Z31: =3.5-0.72 -> 2.78 | AA31: =3.5-0.72 -> 2.78 | AB31: =3.5-0.72 -> 2.78 | AC31: =3.5-0.72 -> 2.78 | AD31: =3.5-0.72 -> 2.78 | AE31: 0 | AF31: 0 | AG31: 0 | AI31: =SUMPRODUCT(J31:N31,J$4:N$4) -> 169.58 | AJ31: =SUMPRODUCT(O31:Z31,O$4:Z$4) -> 503.18 | AK31: =AJ31 -> 503.18 | AL31: =AK31 -> 503.18 | AM31: =AL31 -> 503.18 | AN31: =AM31 -> 503.18 | AO31: =AN31 -> 503.18 | AP31: =AO31 -> 503.18 | AQ31: =AP31 -> 503.18 | AR31: =AQ31 -> 503.18 | ... AT31: =AS31 -> 503.18
C32: БМВД (премикс) | D32: кг | J32: 0 | K32: 0 | L32: 0 | M32: 0.72 | N32: 0.72 | O32: 0.72 | P32: 0.72 | Q32: 0.72 | R32: 0.72 | S32: 0 | T32: 0 | U32: 0 | V32: 0 | W32: 0 | X32: 0 | Y32: 0.72 | Z32: 0.72 | AA32: 0.72 | AB32: 0.72 | AC32: 0.72 | AD32: 0.72 | AE32: 0 | AF32: 0 | AG32: 0 | AI32: =SUMPRODUCT(J32:N32,J$4:N$4) -> 43.92 | AJ32: =SUMPRODUCT(O32:Z32,O$4:Z$4) -> 130.32 | AK32: =AJ32 -> 130.32 | AL32: =AK32 -> 130.32 | AM32: =AL32 -> 130.32 | AN32: =AM32 -> 130.32 | AO32: =AN32 -> 130.32 | AP32: =AO32 -> 130.32 | AQ32: =AP32 -> 130.32 | AR32: =AQ32 -> 130.32 | ... AT32: =AS32 -> 130.32
C33: Соль поваренная | D33: кг | J33: 0.05 | K33: 0.05 | L33: 0.05 | M33: 0.045 | N33: 0.045 | O33: 0.045 | P33: 0.045 | Q33: 0.045 | R33: 0.045 | S33: 0.05 | T33: 0.05 | U33: 0.05 | V33: 0.05 | W33: 0.05 | X33: 0.05 | Y33: 0.045 | Z33: 0.045 | AA33: 0.045 | AB33: 0.045 | AC33: 0.045 | AD33: 0.045 | AE33: 0.05 | AF33: 0.05 | AG33: 0.05 | AI33: =SUMPRODUCT(J33:N33,J$4:N$4) -> 7.295 | AJ33: =SUMPRODUCT(O33:Z33,O$4:Z$4) -> 17.345 | AK33: =AJ33 -> 17.345 | AL33: =AK33 -> 17.345 | AM33: =AL33 -> 17.345 | AN33: =AM33 -> 17.345 | AO33: =AN33 -> 17.345 | AP33: =AO33 -> 17.345 | AQ33: =AP33 -> 17.345 | AR33: =AQ33 -> 17.345 | ... AT33: =AS33 -> 17.345
B35: Молодняк
C36: Молоко | D36: л | J36: 0 | K36: 0 | L36: 0 | M36: 0 | N36: 6 | O36: 7 | P36: 6 | Q36: 5 | R36: 4 | S36: 4 | T36: 5 | U36: 0 | V36: 0 | W36: 0 | X36: 0 | Y36: 0 | Z36: 6 | AA36: 7 | AB36: 6 | AC36: 5 | AD36: 4 | AE36: 4 | AF36: 5 | AG36: 5 | AI36: =SUMPRODUCT(J36:N36,J$4:N$4) -> 186 | AJ36: =SUMPRODUCT(O36:Z36,O$4:Z$4) -> 1120 | AK36: =AJ36 -> 1120 | AL36: =AK36 -> 1120 | AM36: =AL36 -> 1120 | AN36: =AM36 -> 1120 | AO36: =AN36 -> 1120 | AP36: =AO36 -> 1120 | AQ36: =AP36 -> 1120 | AR36: =AQ36 -> 1120 | ... AT36: =AS36 -> 1120
C37: Сено | D37: кг | J37: 0 | K37: 0 | L37: 0 | M37: 0 | N37: 0 | O37: 0.3 | P37: 0.5 | Q37: 1 | R37: 1.2 | S37: 0 | T37: 0 | U37: 0 | V37: 0 | W37: 0 | X37: 0 | Y37: 0 | Z37: 0 | AA37: 0.3 | AB37: 0.5 | AC37: 1 | AD37: 1.2 | AE37: 0 | AF37: 0 | AG37: 0 | AI37: =SUMPRODUCT(J37:N37,J$4:N$4) -> 0 | AJ37: =SUMPRODUCT(O37:Z37,O$4:Z$4) -> 90.3 | AK37: =AJ37 -> 90.3 | AL37: =AK37 -> 90.3 | AM37: =AL37 -> 90.3 | AN37: =AM37 -> 90.3 | AO37: =AN37 -> 90.3 | AP37: =AO37 -> 90.3 | AQ37: =AP37 -> 90.3 | AR37: =AQ37 -> 90.3 | ... AT37: =AS37 -> 90.3
C38: Силос | D38: кг | J38: 0 | K38: 0 | L38: 0 | M38: 0 | N38: 0 | O38: 0 | P38: 0 | Q38: 0 | R38: 0 | S38: 0 | T38: 0 | U38: 0 | V38: 0 | W38: 0 | X38: 0 | Y38: 0 | Z38: 0 | AA38: 0 | AB38: 0 | AC38: 0 | AD38: 0 | AE38: 0 | AF38: 0 | AG38: 0 | AI38: =SUMPRODUCT(J38:N38,J$4:N$4) -> 0 | AJ38: =SUMPRODUCT(O38:Z38,O$4:Z$4) -> 0 | AK38: =AJ38 -> 0 | AL38: =AK38 -> 0 | AM38: =AL38 -> 0 | AN38: =AM38 -> 0 | AO38: =AN38 -> 0 | AP38: =AO38 -> 0 | AQ38: =AP38 -> 0 | AR38: =AQ38 -> 0 | ... AT38: =AS38 -> 0
C39: Концентраты | D39: кг | J39: 0 | K39: 0 | L39: 0 | M39: 0 | N39: 0 | O39: 0.2 | P39: 0.4 | Q39: 0.6 | R39: 0.7 | S39: 0 | T39: 0 | U39: 0 | V39: 0 | W39: 0 | X39: 0 | Y39: 0 | Z39: 0 | AA39: 0.2 | AB39: 0.4 | AC39: 0.6 | AD39: 0.7 | AE39: 0 | AF39: 0 | AG39: 0 | AI39: =SUMPRODUCT(J39:N39,J$4:N$4) -> 0 | AJ39: =SUMPRODUCT(O39:Z39,O$4:Z$4) -> 57 | AK39: =AJ39 -> 57 | AL39: =AK39 -> 57 | AM39: =AL39 -> 57 | AN39: =AM39 -> 57 | AO39: =AN39 -> 57 | AP39: =AO39 -> 57 | AQ39: =AP39 -> 57 | AR39: =AQ39 -> 57 | ... AT39: =AS39 -> 57
C40: Соль поваренная | D40: кг | J40: 0 | K40: 0 | L40: 0 | M40: 0 | N40: 0 | O40: 0.008 | P40: 0.012 | Q40: 0.016 | R40: 0.018 | S40: 0.022 | T40: 0.027 | U40: 0 | V40: 0 | W40: 0 | X40: 0 | Y40: 0 | Z40: 0 | AA40: 0.008 | AB40: 0.012 | AC40: 0.016 | AD40: 0.018 | AE40: 0.022 | AF40: 0.027 | AG40: 0.027 | AI40: =SUMPRODUCT(J40:N40,J$4:N$4) -> 0 | AJ40: =SUMPRODUCT(O40:Z40,O$4:Z$4) -> 3.112 | AK40: =AJ40 -> 3.112 | AL40: =AK40 -> 3.112 | AM40: =AL40 -> 3.112 | AN40: =AM40 -> 3.112 | AO40: =AN40 -> 3.112 | AP40: =AO40 -> 3.112 | AQ40: =AP40 -> 3.112 | AR40: =AQ40 -> 3.112 | ... AT40: =AS40 -> 3.112
C41: Кормовой фосфат | D41: кг | J41: 0 | K41: 0 | L41: 0 | M41: 0 | N41: 0 | O41: 0.01 | P41: 0.02 | Q41: 0.03 | R41: 0.03 | S41: 0.04 | T41: 0.03 | U41: 0 | V41: 0 | W41: 0 | X41: 0 | Y41: 0 | Z41: 0 | AA41: 0.01 | AB41: 0.02 | AC41: 0.03 | AD41: 0.03 | AE41: 0.04 | AF41: 0.03 | AG41: 0.03 | AI41: =SUMPRODUCT(J41:N41,J$4:N$4) -> 0 | AJ41: =SUMPRODUCT(O41:Z41,O$4:Z$4) -> 4.84 | AK41: =AJ41 -> 4.84 | AL41: =AK41 -> 4.84 | AM41: =AL41 -> 4.84 | AN41: =AM41 -> 4.84 | AO41: =AN41 -> 4.84 | AP41: =AO41 -> 4.84 | AQ41: =AP41 -> 4.84 | AR41: =AQ41 -> 4.84 | ... AT41: =AS41 -> 4.84
C42: Зеленая масса | D42: кг | J42: 0 | K42: 0 | L42: 0 | M42: 0 | N42: 0 | O42: 0 | P42: 0 | Q42: 0 | R42: 0 | S42: 0 | T42: 9 | U42: 0 | V42: 0 | W42: 0 | X42: 0 | Y42: 0 | Z42: 0 | AA42: 0 | AB42: 0 | AC42: 0 | AD42: 0 | AE42: 0 | AF42: 9 | AG42: 9 | AI42: =SUMPRODUCT(J42:N42,J$4:N$4) -> 0 | AJ42: =SUMPRODUCT(O42:Z42,O$4:Z$4) -> 270 | AK42: =AJ42 -> 270 | AL42: =AK42 -> 270 | AM42: =AL42 -> 270 | AN42: =AM42 -> 270 | AO42: =AN42 -> 270 | AP42: =AO42 -> 270 | AQ42: =AP42 -> 270 | AR42: =AQ42 -> 270 | ... AT42: =AS42 -> 270
B44: Телочки предыдущего периода
C45: Зеленая масса | D45: кг | J45: 29 | K45: 29 | L45: 29 | M45: 0 | N45: 0 | O45: 0 | P45: 0 | Q45: 0 | AI45: =SUMPRODUCT(J45:N45,J$4:N$4) -> 2639 | AJ45: =SUMPRODUCT(O45:Z45,O$4:Z$4) -> 0 | AK45: =AJ45 -> 0 | AL45: =AK45 -> 0 | AM45: =AL45 -> 0 | AN45: =AM45 -> 0 | AO45: =AN45 -> 0 | AP45: =AO45 -> 0 | AQ45: =AP45 -> 0 | AR45: =AQ45 -> 0 | ... AT45: =AS45 -> 0
C46: Концентраты | D46: кг | J46: 0 | K46: 0 | L46: 0 | M46: 0 | N46: 0 | O46: 0 | P46: 0 | Q46: 0 | AI46: =SUMPRODUCT(J46:N46,J$4:N$4) -> 0 | AJ46: =SUMPRODUCT(O46:Z46,O$4:Z$4) -> 0 | AK46: =AJ46 -> 0 | AL46: =AK46 -> 0 | AM46: =AL46 -> 0 | AN46: =AM46 -> 0 | AO46: =AN46 -> 0 | AP46: =AO46 -> 0 | AQ46: =AP46 -> 0 | AR46: =AQ46 -> 0 | ... AT46: =AS46 -> 0
C47: Соль поваренная | D47: кг | J47: 0.03 | K47: 0.03 | L47: 0.03 | M47: 0.03 | N47: 0.03 | O47: 0.03 | P47: 0.03 | Q47: 0.03 | AI47: =SUMPRODUCT(J47:N47,J$4:N$4) -> 4.56 | AJ47: =SUMPRODUCT(O47:Z47,O$4:Z$4) -> 2.7 | AK47: =AJ47 -> 2.7 | AL47: =AK47 -> 2.7 | AM47: =AL47 -> 2.7 | AN47: =AM47 -> 2.7 | AO47: =AN47 -> 2.7 | AP47: =AO47 -> 2.7 | AQ47: =AP47 -> 2.7 | AR47: =AQ47 -> 2.7 | ... AT47: =AS47 -> 2.7
C48: Кормовой фосфат | D48: кг | J48: 0.03 | K48: 0.03 | L48: 0.03 | M48: 0.03 | N48: 0.03 | O48: 0.03 | P48: 0.03 | Q48: 0.03 | AI48: =SUMPRODUCT(J48:N48,J$4:N$4) -> 4.56 | AJ48: =SUMPRODUCT(O48:Z48,O$4:Z$4) -> 2.7 | AK48: =AJ48 -> 2.7 | AL48: =AK48 -> 2.7 | AM48: =AL48 -> 2.7 | AN48: =AM48 -> 2.7 | AO48: =AN48 -> 2.7 | AP48: =AO48 -> 2.7 | AQ48: =AP48 -> 2.7 | AR48: =AQ48 -> 2.7 | ... AT48: =AS48 -> 2.7
C49: Сено | D49: кг | J49: 0 | K49: 0 | L49: 0 | M49: 4 | N49: 4 | O49: 4 | P49: 4 | Q49: 4 | AI49: =SUMPRODUCT(J49:N49,J$4:N$4) -> 244 | AJ49: =SUMPRODUCT(O49:Z49,O$4:Z$4) -> 360 | AK49: =AJ49 -> 360 | AL49: =AK49 -> 360 | AM49: =AL49 -> 360 | AN49: =AM49 -> 360 | AO49: =AN49 -> 360 | AP49: =AO49 -> 360 | AQ49: =AP49 -> 360 | AR49: =AQ49 -> 360 | ... AT49: =AS49 -> 360
C50: Сенаж | D50: кг | J50: 0 | K50: 0 | L50: 0 | M50: 5 | N50: 5 | O50: 5 | P50: 5 | Q50: 5 | AI50: =SUMPRODUCT(J50:N50,J$4:N$4) -> 305 | AJ50: =SUMPRODUCT(O50:Z50,O$4:Z$4) -> 450 | AK50: =AJ50 -> 450 | AL50: =AK50 -> 450 | AM50: =AL50 -> 450 | AN50: =AM50 -> 450 | AO50: =AN50 -> 450 | AP50: =AO50 -> 450 | AQ50: =AP50 -> 450 | AR50: =AQ50 -> 450 | ... AT50: =AS50 -> 450
C51: Дерть ячменная | D51: кг | J51: 0 | K51: 0 | L51: 0 | M51: 0 | N51: 0 | O51: 0 | P51: 0 | Q51: 0 | AI51: =SUMPRODUCT(J51:N51,J$4:N$4) -> 0 | AJ51: =SUMPRODUCT(O51:Z51,O$4:Z$4) -> 0 | AK51: =AJ51 -> 0 | AL51: =AK51 -> 0 | AM51: =AL51 -> 0 | AN51: =AM51 -> 0 | AO51: =AN51 -> 0 | AP51: =AO51 -> 0 | AQ51: =AP51 -> 0 | AR51: =AQ51 -> 0 | ... AT51: =AS51 -> 0
C52: Зерноотходы | D52: кг | J52: 0 | K52: 0 | L52: 0 | M52: 0 | N52: 0 | O52: 0 | P52: 0 | Q52: 0 | AI52: =SUMPRODUCT(J52:N52,J$4:N$4) -> 0 | AJ52: =SUMPRODUCT(O52:Z52,O$4:Z$4) -> 0 | AK52: =AJ52 -> 0 | AL52: =AK52 -> 0 | AM52: =AL52 -> 0 | AN52: =AM52 -> 0 | AO52: =AN52 -> 0 | AP52: =AO52 -> 0 | AQ52: =AP52 -> 0 | AR52: =AQ52 -> 0 | ... AT52: =AS52 -> 0
B54: Телочки текущего периода
C55: Зеленая масса | D55: кг | U55: 29 | V55: 29 | W55: 29 | X55: 29 | Y55: 0 | Z55: 0 | AA55: 0 | AB55: 0 | AC55: 0 | AD55: 0 | AE55: 29 | AF55: 29 | AG55: 29 | AI55: =SUMPRODUCT(J55:N55,J$4:N$4) -> 0 | AJ55: =SUMPRODUCT(O55:Z55,O$4:Z$4) -> 3567 | AK55: =AJ55 -> 3567 | AL55: =AK55 -> 3567 | AM55: =AL55 -> 3567 | AN55: =AM55 -> 3567 | AO55: =AN55 -> 3567 | AP55: =AO55 -> 3567 | AQ55: =AP55 -> 3567 | AR55: =AQ55 -> 3567 | ... AT55: =AS55 -> 3567
C56: Концентраты | D56: кг | U56: 0 | V56: 0 | W56: 0 | X56: 0 | Y56: 0 | Z56: 0 | AA56: 0 | AB56: 0 | AC56: 0 | AD56: 0 | AE56: 0 | AF56: 0 | AG56: 0 | AI56: =SUMPRODUCT(J56:N56,J$4:N$4) -> 0 | AJ56: =SUMPRODUCT(O56:Z56,O$4:Z$4) -> 0 | AK56: =AJ56 -> 0 | AL56: =AK56 -> 0 | AM56: =AL56 -> 0 | AN56: =AM56 -> 0 | AO56: =AN56 -> 0 | AP56: =AO56 -> 0 | AQ56: =AP56 -> 0 | AR56: =AQ56 -> 0 | ... AT56: =AS56 -> 0
C57: Соль поваренная | D57: кг | U57: 0.03 | V57: 0.03 | W57: 0.03 | X57: 0.03 | Y57: 0.03 | Z57: 0.03 | AA57: 0.03 | AB57: 0.03 | AC57: 0.03 | AD57: 0.03 | AE57: 0.03 | AF57: 0.03 | AG57: 0.03 | AI57: =SUMPRODUCT(J57:N57,J$4:N$4) -> 0 | AJ57: =SUMPRODUCT(O57:Z57,O$4:Z$4) -> 5.52 | AK57: =AJ57 -> 5.52 | AL57: =AK57 -> 5.52 | AM57: =AL57 -> 5.52 | AN57: =AM57 -> 5.52 | AO57: =AN57 -> 5.52 | AP57: =AO57 -> 5.52 | AQ57: =AP57 -> 5.52 | AR57: =AQ57 -> 5.52 | ... AT57: =AS57 -> 5.52
C58: Кормовой фосфат | D58: кг | U58: 0.03 | V58: 0.03 | W58: 0.03 | X58: 0.03 | Y58: 0.03 | Z58: 0.03 | AA58: 0.03 | AB58: 0.03 | AC58: 0.03 | AD58: 0.03 | AE58: 0.03 | AF58: 0.03 | AG58: 0.03 | AI58: =SUMPRODUCT(J58:N58,J$4:N$4) -> 0 | AJ58: =SUMPRODUCT(O58:Z58,O$4:Z$4) -> 5.52 | AK58: =AJ58 -> 5.52 | AL58: =AK58 -> 5.52 | AM58: =AL58 -> 5.52 | AN58: =AM58 -> 5.52 | AO58: =AN58 -> 5.52 | AP58: =AO58 -> 5.52 | AQ58: =AP58 -> 5.52 | AR58: =AQ58 -> 5.52 | ... AT58: =AS58 -> 5.52
C59: Сено | D59: кг | U59: 0 | V59: 0 | W59: 0 | X59: 0 | Y59: 4 | Z59: 4 | AA59: 4 | AB59: 4 | AC59: 3.5 | AD59: 3.5 | AE59: 0 | AF59: 0 | AG59: 0 | AI59: =SUMPRODUCT(J59:N59,J$4:N$4) -> 0 | AJ59: =SUMPRODUCT(O59:Z59,O$4:Z$4) -> 244 | AK59: =AJ59 -> 244 | AL59: =AK59 -> 244 | AM59: =AL59 -> 244 | AN59: =AM59 -> 244 | AO59: =AN59 -> 244 | AP59: =AO59 -> 244 | AQ59: =AP59 -> 244 | AR59: =AQ59 -> 244 | ... AT59: =AS59 -> 244
C60: Сенаж | D60: кг | U60: 0 | V60: 0 | W60: 0 | X60: 0 | Y60: 5 | Z60: 5 | AA60: 5 | AB60: 5 | AC60: 7 | AD60: 7 | AE60: 0 | AF60: 0 | AG60: 0 | AI60: =SUMPRODUCT(J60:N60,J$4:N$4) -> 0 | AJ60: =SUMPRODUCT(O60:Z60,O$4:Z$4) -> 305 | AK60: =AJ60 -> 305 | AL60: =AK60 -> 305 | AM60: =AL60 -> 305 | AN60: =AM60 -> 305 | AO60: =AN60 -> 305 | AP60: =AO60 -> 305 | AQ60: =AP60 -> 305 | AR60: =AQ60 -> 305 | ... AT60: =AS60 -> 305
C61: Дерть ячменная | D61: кг | U61: 0 | V61: 0 | W61: 0 | X61: 0 | Y61: 0 | Z61: 0 | AA61: 0 | AB61: 0 | AC61: 0 | AD61: 0 | AE61: 0 | AF61: 0 | AG61: 0 | AI61: =SUMPRODUCT(J61:N61,J$4:N$4) -> 0 | AJ61: =SUMPRODUCT(O61:Z61,O$4:Z$4) -> 0 | AK61: =AJ61 -> 0 | AL61: =AK61 -> 0 | AM61: =AL61 -> 0 | AN61: =AM61 -> 0 | AO61: =AN61 -> 0 | AP61: =AO61 -> 0 | AQ61: =AP61 -> 0 | AR61: =AQ61 -> 0 | ... AT61: =AS61 -> 0
C62: Зерноотходы | D62: кг | U62: 0 | V62: 0 | W62: 0 | X62: 0 | Y62: 0 | Z62: 0 | AA62: 0 | AB62: 0 | AC62: 0 | AD62: 0 | AE62: 0 | AF62: 0 | AG62: 0 | AI62: =SUMPRODUCT(J62:N62,J$4:N$4) -> 0 | AJ62: =SUMPRODUCT(O62:Z62,O$4:Z$4) -> 0 | AK62: =AJ62 -> 0 | AL62: =AK62 -> 0 | AM62: =AL62 -> 0 | AN62: =AM62 -> 0 | AO62: =AN62 -> 0 | AP62: =AO62 -> 0 | AQ62: =AP62 -> 0 | AR62: =AQ62 -> 0 | ... AT62: =AS62 -> 0
B64: Бычки
C65: Зеленая масса | D65: кг | U65: 30 | V65: 30 | W65: 30 | X65: 30 | AI65: =SUMPRODUCT(J65:N65,J$4:N$4) -> 0 | AJ65: =SUMPRODUCT(O65:Z65,O$4:Z$4) -> 3690 | AK65: =AJ65 -> 3690 | AL65: =AK65 -> 3690 | AM65: =AL65 -> 3690 | AN65: =AM65 -> 3690 | AO65: =AN65 -> 3690 | AP65: =AO65 -> 3690 | AQ65: =AP65 -> 3690 | AR65: =AQ65 -> 3690 | ... AT65: =AS65 -> 3690
C66: Концентраты | D66: кг | U66: 0 | V66: 0 | W66: 0 | X66: 0 | AI66: =SUMPRODUCT(J66:N66,J$4:N$4) -> 0 | AJ66: =SUMPRODUCT(O66:Z66,O$4:Z$4) -> 0 | AK66: =AJ66 -> 0 | AL66: =AK66 -> 0 | AM66: =AL66 -> 0 | AN66: =AM66 -> 0 | AO66: =AN66 -> 0 | AP66: =AO66 -> 0 | AQ66: =AP66 -> 0 | AR66: =AQ66 -> 0 | ... AT66: =AS66 -> 0
C67: Соль поваренная | D67: кг | U67: 0.04 | V67: 0.04 | W67: 0.04 | X67: 0.04 | AI67: =SUMPRODUCT(J67:N67,J$4:N$4) -> 0 | AJ67: =SUMPRODUCT(O67:Z67,O$4:Z$4) -> 4.92 | AK67: =AJ67 -> 4.92 | AL67: =AK67 -> 4.92 | AM67: =AL67 -> 4.92 | AN67: =AM67 -> 4.92 | AO67: =AN67 -> 4.92 | AP67: =AO67 -> 4.92 | AQ67: =AP67 -> 4.92 | AR67: =AQ67 -> 4.92 | ... AT67: =AS67 -> 4.92
C68: Кормовой фосфат | D68: кг | U68: 0.04 | V68: 0.04 | W68: 0.04 | X68: 0.04 | AI68: =SUMPRODUCT(J68:N68,J$4:N$4) -> 0 | AJ68: =SUMPRODUCT(O68:Z68,O$4:Z$4) -> 4.92 | AK68: =AJ68 -> 4.92 | AL68: =AK68 -> 4.92 | AM68: =AL68 -> 4.92 | AN68: =AM68 -> 4.92 | AO68: =AN68 -> 4.92 | AP68: =AO68 -> 4.92 | AQ68: =AP68 -> 4.92 | AR68: =AQ68 -> 4.92 | ... AT68: =AS68 -> 4.92
C69: Сено | D69: кг | U69: 0 | V69: 0 | W69: 0 | X69: 0 | AI69: =SUMPRODUCT(J69:N69,J$4:N$4) -> 0 | AJ69: =SUMPRODUCT(O69:Z69,O$4:Z$4) -> 0 | AK69: =AJ69 -> 0 | AL69: =AK69 -> 0 | AM69: =AL69 -> 0 | AN69: =AM69 -> 0 | AO69: =AN69 -> 0 | AP69: =AO69 -> 0 | AQ69: =AP69 -> 0 | AR69: =AQ69 -> 0 | ... AT69: =AS69 -> 0
C70: Солома | D70: кг | U70: 0 | V70: 0 | W70: 0 | X70: 0 | AI70: =SUMPRODUCT(J70:N70,J$4:N$4) -> 0 | AJ70: =SUMPRODUCT(O70:Z70,O$4:Z$4) -> 0 | AK70: =AJ70 -> 0 | AL70: =AK70 -> 0 | AM70: =AL70 -> 0 | AN70: =AM70 -> 0 | AO70: =AN70 -> 0 | AP70: =AO70 -> 0 | AQ70: =AP70 -> 0 | AR70: =AQ70 -> 0 | ... AT70: =AS70 -> 0
C71: Силос | D71: кг | U71: 0 | V71: 0 | W71: 0 | X71: 0 | AI71: =SUMPRODUCT(J71:N71,J$4:N$4) -> 0 | AJ71: =SUMPRODUCT(O71:Z71,O$4:Z$4) -> 0 | AK71: =AJ71 -> 0 | AL71: =AK71 -> 0 | AM71: =AL71 -> 0 | AN71: =AM71 -> 0 | AO71: =AN71 -> 0 | AP71: =AO71 -> 0 | AQ71: =AP71 -> 0 | AR71: =AQ71 -> 0 | ... AT71: =AS71 -> 0
B73: Товарные бычки
C74: Зеленая масса | D74: кг | S74: 30 | T74: 30 | U74: 30 | V74: 30 | W74: 30 | X74: 30 | AI74: =SUMPRODUCT(J74:N74,J$4:N$4) -> 0 | AJ74: =SUMPRODUCT(O74:Z74,O$4:Z$4) -> 5520 | AK74: =AJ74 -> 5520 | AL74: =AK74 -> 5520 | AM74: =AL74 -> 5520 | AN74: =AM74 -> 5520 | AO74: =AN74 -> 5520 | AP74: =AO74 -> 5520 | AQ74: =AP74 -> 5520 | AR74: =AQ74 -> 5520 | ... AT74: =AS74 -> 5520
C75: Концентраты | D75: кг | S75: 0 | T75: 0 | U75: 0 | V75: 0 | W75: 0 | X75: 0 | AI75: =SUMPRODUCT(J75:N75,J$4:N$4) -> 0 | AJ75: =SUMPRODUCT(O75:Z75,O$4:Z$4) -> 0 | AK75: =AJ75 -> 0 | AL75: =AK75 -> 0 | AM75: =AL75 -> 0 | AN75: =AM75 -> 0 | AO75: =AN75 -> 0 | AP75: =AO75 -> 0 | AQ75: =AP75 -> 0 | AR75: =AQ75 -> 0 | ... AT75: =AS75 -> 0
C76: Соль поваренная | D76: кг | S76: 0.04 | T76: 0.04 | U76: 0.04 | V76: 0.04 | W76: 0.04 | X76: 0.04 | AI76: =SUMPRODUCT(J76:N76,J$4:N$4) -> 0 | AJ76: =SUMPRODUCT(O76:Z76,O$4:Z$4) -> 7.36 | AK76: =AJ76 -> 7.36 | AL76: =AK76 -> 7.36 | AM76: =AL76 -> 7.36 | AN76: =AM76 -> 7.36 | AO76: =AN76 -> 7.36 | AP76: =AO76 -> 7.36 | AQ76: =AP76 -> 7.36 | AR76: =AQ76 -> 7.36 | ... AT76: =AS76 -> 7.36
C77: Кормовой фосфат | D77: кг | S77: 0.04 | T77: 0.04 | U77: 0.04 | V77: 0.04 | W77: 0.04 | X77: 0.04 | AI77: =SUMPRODUCT(J77:N77,J$4:N$4) -> 0 | AJ77: =SUMPRODUCT(O77:Z77,O$4:Z$4) -> 7.36 | AK77: =AJ77 -> 7.36 | AL77: =AK77 -> 7.36 | AM77: =AL77 -> 7.36 | AN77: =AM77 -> 7.36 | AO77: =AN77 -> 7.36 | AP77: =AO77 -> 7.36 | AQ77: =AP77 -> 7.36 | AR77: =AQ77 -> 7.36 | ... AT77: =AS77 -> 7.36
C78: Сено | D78: кг | S78: 0 | T78: 0 | U78: 0 | V78: 0 | W78: 0 | X78: 0 | AI78: =SUMPRODUCT(J78:N78,J$4:N$4) -> 0 | AJ78: =SUMPRODUCT(O78:Z78,O$4:Z$4) -> 0 | AK78: =AJ78 -> 0 | AL78: =AK78 -> 0 | AM78: =AL78 -> 0 | AN78: =AM78 -> 0 | AO78: =AN78 -> 0 | AP78: =AO78 -> 0 | AQ78: =AP78 -> 0 | AR78: =AQ78 -> 0 | ... AT78: =AS78 -> 0
C79: Солома | D79: кг | S79: 0 | T79: 0 | U79: 0 | V79: 0 | W79: 0 | X79: 0 | AI79: =SUMPRODUCT(J79:N79,J$4:N$4) -> 0 | AJ79: =SUMPRODUCT(O79:Z79,O$4:Z$4) -> 0 | AK79: =AJ79 -> 0 | AL79: =AK79 -> 0 | AM79: =AL79 -> 0 | AN79: =AM79 -> 0 | AO79: =AN79 -> 0 | AP79: =AO79 -> 0 | AQ79: =AP79 -> 0 | AR79: =AQ79 -> 0 | ... AT79: =AS79 -> 0
C80: Силос | D80: кг | S80: 0 | T80: 0 | U80: 0 | V80: 0 | W80: 0 | X80: 0 | AI80: =SUMPRODUCT(J80:N80,J$4:N$4) -> 0 | AJ80: =SUMPRODUCT(O80:Z80,O$4:Z$4) -> 0 | AK80: =AJ80 -> 0 | AL80: =AK80 -> 0 | AM80: =AL80 -> 0 | AN80: =AM80 -> 0 | AO80: =AN80 -> 0 | AP80: =AO80 -> 0 | AQ80: =AP80 -> 0 | AR80: =AQ80 -> 0 | ... AT80: =AS80 -> 0
A84: х | B84: Цена на корма
J85: ='Operating Model'!AI31 -> 0.11 | O85: ='Operating Model'!AJ31 -> 0.105 | AA85: ='Operating Model'!AK31 -> 0.1 | AI85: ='Operating Model'!AI31 -> 0.11 | AJ85: ='Operating Model'!AJ31 -> 0.105 | AK85: ='Operating Model'!AK31 -> 0.1 | AL85: ='Operating Model'!AL31 -> 0.095 | AM85: ='Operating Model'!AM31 -> 0.09 | AN85: ='Operating Model'!AN31 -> 0.085 | AO85: ='Operating Model'!AO31 -> 0.08 | AP85: ='Operating Model'!AP31 -> 0.07 | ... AT85: ='Operating Model'!AT31 -> 0.05
C87: Молоко | D87: тг/л | J87: 0 | K87: 0 | L87: 0 | M87: 0 | N87: 0 | O87: 0 | P87: 0 | Q87: 0 | R87: 0 | S87: 0 | T87: 0 | U87: 0 | V87: 0 | W87: 0 | X87: 0 | Y87: 0 | Z87: 0 | AA87: 0 | AB87: 0 | AC87: 0 | AD87: 0 | AE87: 0 | AF87: 0 | AG87: 0 | AI87: 0 | AJ87: 0 | AK87: 0 | AL87: 0 | AM87: 0 | AN87: 0 | AO87: 0 | AP87: 0 | AQ87: 0 | AR87: 0 | AS87: 0 | AT87: 0
A88: грубые корма | C88: Зеленая масса | D88: тг/кг | J88: 0 | K88: 0 | L88: 0 | M88: 0 | N88: 0 | O88: =J88*(1+$O$85) -> 0 | P88: =O88 -> 0 | Q88: =P88 -> 0 | R88: =Q88 -> 0 | S88: =R88 -> 0 | T88: =S88 -> 0 | U88: =T88 -> 0 | V88: =U88 -> 0 | W88: =V88 -> 0 | ... Z88: =Y88 -> 0 | AA88: =Z88*(1+$AA$85) -> 0 | AB88: =AA88 -> 0 | AC88: =AB88 -> 0 | AD88: =AC88 -> 0 | AE88: =AD88 -> 0 | AF88: =AE88 -> 0 | AG88: =AF88 -> 0 | AI88: =J88 -> 0 | AJ88: =AI88*(1+$AA$85) -> 0 | AK88: =AJ88*(1+$AA$85) -> 0 | AL88: =AK88*(1+$AA$85) -> 0 | AM88: =AL88*(1+$AA$85) -> 0 | AN88: =AM88*(1+$AA$85) -> 0 | AO88: =AN88*(1+$AA$85) -> 0 | AP88: =AO88*(1+$AA$85) -> 0 | AQ88: =AP88*(1+$AA$85) -> 0 | ... AT88: =AS88*(1+$AA$85) -> 0
A89: концентрат | C89: Концентраты | D89: тг/кг | J89: 80 | K89: 80 | L89: 80 | M89: 80 | N89: 80 | O89: =J89*(1+$O$85) -> 88.4 | P89: =O89 -> 88.4 | Q89: =P89 -> 88.4 | R89: =Q89 -> 88.4 | S89: =R89 -> 88.4 | T89: =S89 -> 88.4 | U89: =T89 -> 88.4 | V89: =U89 -> 88.4 | W89: =V89 -> 88.4 | ... Z89: =Y89 -> 88.4 | AA89: =Z89*(1+$AA$85) -> 97.24 | AB89: =AA89 -> 97.24 | AC89: =AB89 -> 97.24 | AD89: =AC89 -> 97.24 | AE89: =AD89 -> 97.24 | AF89: =AE89 -> 97.24 | AG89: =AF89 -> 97.24 | AI89: =J89 -> 80 | AJ89: =AI89*(1+AJ$85) -> 88.4 | AK89: =AJ89*(1+AK$85) -> 97.24 | AL89: =AK89*(1+AL$85) -> 106.4778 | AM89: =AL89*(1+AM$85) -> 116.0608 | AN89: =AM89*(1+AN$85) -> 125.92597 | AO89: =AN89*(1+AO$85) -> 136.00005 | AP89: =AO89*(1+AP$85) -> 145.52005 | AQ89: =AP89*(1+AQ$85) -> 154.97885 | ... AT89: =AS89*(1+AT$85) -> 181.11604
A90: премикс | C90: Соль поваренная | D90: тг/кг | J90: 145 | K90: 145 | L90: 145 | M90: 145 | N90: 145 | O90: =J90*(1+$O$85) -> 160.225 | P90: =O90 -> 160.225 | Q90: =P90 -> 160.225 | R90: =Q90 -> 160.225 | S90: =R90 -> 160.225 | T90: =S90 -> 160.225 | U90: =T90 -> 160.225 | V90: =U90 -> 160.225 | W90: =V90 -> 160.225 | ... Z90: =Y90 -> 160.225 | AA90: =Z90*(1+$AA$85) -> 176.2475 | AB90: =AA90 -> 176.2475 | AC90: =AB90 -> 176.2475 | AD90: =AC90 -> 176.2475 | AE90: =AD90 -> 176.2475 | AF90: =AE90 -> 176.2475 | AG90: =AF90 -> 176.2475 | AI90: =J90 -> 145 | AJ90: =AI90*(1+AJ$85) -> 160.225 | AK90: =AJ90*(1+AK$85) -> 176.2475 | AL90: =AK90*(1+AL$85) -> 192.99101 | AM90: =AL90*(1+AM$85) -> 210.3602 | AN90: =AM90*(1+AN$85) -> 228.24082 | AO90: =AN90*(1+AO$85) -> 246.50009 | AP90: =AO90*(1+AP$85) -> 263.75509 | AQ90: =AP90*(1+AQ$85) -> 280.89917 | ... AT90: =AS90*(1+AT$85) -> 328.27282
A91: грубые корма | C91: Сено | D91: тг/кг | J91: 28 | K91: 28 | L91: 28 | M91: 28 | N91: 28 | O91: =J91*(1+$O$85) -> 30.94 | P91: =O91 -> 30.94 | Q91: =P91 -> 30.94 | R91: =Q91 -> 30.94 | S91: =R91 -> 30.94 | T91: =S91 -> 30.94 | U91: =T91 -> 30.94 | V91: =U91 -> 30.94 | W91: =V91 -> 30.94 | ... Z91: =Y91 -> 30.94 | AA91: =Z91*(1+$AA$85) -> 34.034 | AB91: =AA91 -> 34.034 | AC91: =AB91 -> 34.034 | AD91: =AC91 -> 34.034 | AE91: =AD91 -> 34.034 | AF91: =AE91 -> 34.034 | AG91: =AF91 -> 34.034 | AI91: =J91 -> 28 | AJ91: =AI91*(1+AJ$85) -> 30.94 | AK91: =AJ91*(1+AK$85) -> 34.034 | AL91: =AK91*(1+AL$85) -> 37.26723 | AM91: =AL91*(1+AM$85) -> 40.621281 | AN91: =AM91*(1+AN$85) -> 44.07409 | AO91: =AN91*(1+AO$85) -> 47.600017 | AP91: =AO91*(1+AP$85) -> 50.932018 | AQ91: =AP91*(1+AQ$85) -> 54.242599 | ... AT91: =AS91*(1+AT$85) -> 63.390613
A92: грубые корма | C92: Солома | D92: тг/кг | J92: 15 | K92: 15 | L92: 15 | M92: 15 | N92: 15 | O92: =J92*(1+$O$85) -> 16.575 | P92: =O92 -> 16.575 | Q92: =P92 -> 16.575 | R92: =Q92 -> 16.575 | S92: =R92 -> 16.575 | T92: =S92 -> 16.575 | U92: =T92 -> 16.575 | V92: =U92 -> 16.575 | W92: =V92 -> 16.575 | ... Z92: =Y92 -> 16.575 | AA92: =Z92*(1+$AA$85) -> 18.2325 | AB92: =AA92 -> 18.2325 | AC92: =AB92 -> 18.2325 | AD92: =AC92 -> 18.2325 | AE92: =AD92 -> 18.2325 | AF92: =AE92 -> 18.2325 | AG92: =AF92 -> 18.2325 | AI92: =J92 -> 15 | AJ92: =AI92*(1+AJ$85) -> 16.575 | AK92: =AJ92*(1+AK$85) -> 18.2325 | AL92: =AK92*(1+AL$85) -> 19.964588 | AM92: =AL92*(1+AM$85) -> 21.7614 | AN92: =AM92*(1+AN$85) -> 23.611119 | AO92: =AN92*(1+AO$85) -> 25.500009 | AP92: =AO92*(1+AP$85) -> 27.28501 | AQ92: =AP92*(1+AQ$85) -> 29.058535 | ... AT92: =AS92*(1+AT$85) -> 33.959257
A93: сочные корма | C93: Отруби/шроты | D93: тг/кг | J93: 120 | K93: 120 | L93: 120 | M93: 120 | N93: 120 | O93: =J93*(1+$O$85) -> 132.6 | P93: =O93 -> 132.6 | Q93: =P93 -> 132.6 | R93: =Q93 -> 132.6 | S93: =R93 -> 132.6 | T93: =S93 -> 132.6 | U93: =T93 -> 132.6 | V93: =U93 -> 132.6 | W93: =V93 -> 132.6 | ... Z93: =Y93 -> 132.6 | AA93: =Z93*(1+$AA$85) -> 145.86 | AB93: =AA93 -> 145.86 | AC93: =AB93 -> 145.86 | AD93: =AC93 -> 145.86 | AE93: =AD93 -> 145.86 | AF93: =AE93 -> 145.86 | AG93: =AF93 -> 145.86 | AI93: =J93 -> 120 | AJ93: =AI93*(1+AJ$85) -> 132.6 | AK93: =AJ93*(1+AK$85) -> 145.86 | AL93: =AK93*(1+AL$85) -> 159.7167 | AM93: =AL93*(1+AM$85) -> 174.0912 | AN93: =AM93*(1+AN$85) -> 188.88896 | AO93: =AN93*(1+AO$85) -> 204.00007 | AP93: =AO93*(1+AP$85) -> 218.28008 | AQ93: =AP93*(1+AQ$85) -> 232.46828 | ... AT93: =AS93*(1+AT$85) -> 271.67406
A94: премикс | C94: Кормовой фосфат | D94: тг/кг | J94: 145 | K94: 145 | L94: 145 | M94: 145 | N94: 145 | O94: =J94*(1+$O$85) -> 160.225 | P94: =O94 -> 160.225 | Q94: =P94 -> 160.225 | R94: =Q94 -> 160.225 | S94: =R94 -> 160.225 | T94: =S94 -> 160.225 | U94: =T94 -> 160.225 | V94: =U94 -> 160.225 | W94: =V94 -> 160.225 | ... Z94: =Y94 -> 160.225 | AA94: =Z94*(1+$AA$85) -> 176.2475 | AB94: =AA94 -> 176.2475 | AC94: =AB94 -> 176.2475 | AD94: =AC94 -> 176.2475 | AE94: =AD94 -> 176.2475 | AF94: =AE94 -> 176.2475 | AG94: =AF94 -> 176.2475 | AI94: =J94 -> 145 | AJ94: =AI94*(1+AJ$85) -> 160.225 | AK94: =AJ94*(1+AK$85) -> 176.2475 | AL94: =AK94*(1+AL$85) -> 192.99101 | AM94: =AL94*(1+AM$85) -> 210.3602 | AN94: =AM94*(1+AN$85) -> 228.24082 | AO94: =AN94*(1+AO$85) -> 246.50009 | AP94: =AO94*(1+AP$85) -> 263.75509 | AQ94: =AP94*(1+AQ$85) -> 280.89917 | ... AT94: =AS94*(1+AT$85) -> 328.27282
A95: премикс | C95: Диаммонийфосфат | D95: тг/кг | J95: 145 | K95: 145 | L95: 145 | M95: 145 | N95: 145 | O95: =J95*(1+$O$85) -> 160.225 | P95: =O95 -> 160.225 | Q95: =P95 -> 160.225 | R95: =Q95 -> 160.225 | S95: =R95 -> 160.225 | T95: =S95 -> 160.225 | U95: =T95 -> 160.225 | V95: =U95 -> 160.225 | W95: =V95 -> 160.225 | ... Z95: =Y95 -> 160.225 | AA95: =Z95*(1+$AA$85) -> 176.2475 | AB95: =AA95 -> 176.2475 | AC95: =AB95 -> 176.2475 | AD95: =AC95 -> 176.2475 | AE95: =AD95 -> 176.2475 | AF95: =AE95 -> 176.2475 | AG95: =AF95 -> 176.2475 | AI95: =J95 -> 145 | AJ95: =AI95*(1+AJ$85) -> 160.225 | AK95: =AJ95*(1+AK$85) -> 176.2475 | AL95: =AK95*(1+AL$85) -> 192.99101 | AM95: =AL95*(1+AM$85) -> 210.3602 | AN95: =AM95*(1+AN$85) -> 228.24082 | AO95: =AN95*(1+AO$85) -> 246.50009 | AP95: =AO95*(1+AP$85) -> 263.75509 | AQ95: =AP95*(1+AQ$85) -> 280.89917 | ... AT95: =AS95*(1+AT$85) -> 328.27282
A96: премикс | C96: Монокальцийфосфат | D96: тг/кг | J96: 145 | K96: 145 | L96: 145 | M96: 145 | N96: 145 | O96: =J96*(1+$O$85) -> 160.225 | P96: =O96 -> 160.225 | Q96: =P96 -> 160.225 | R96: =Q96 -> 160.225 | S96: =R96 -> 160.225 | T96: =S96 -> 160.225 | U96: =T96 -> 160.225 | V96: =U96 -> 160.225 | W96: =V96 -> 160.225 | ... Z96: =Y96 -> 160.225 | AA96: =Z96*(1+$AA$85) -> 176.2475 | AB96: =AA96 -> 176.2475 | AC96: =AB96 -> 176.2475 | AD96: =AC96 -> 176.2475 | AE96: =AD96 -> 176.2475 | AF96: =AE96 -> 176.2475 | AG96: =AF96 -> 176.2475 | AI96: =J96 -> 145 | AJ96: =AI96*(1+AJ$85) -> 160.225 | AK96: =AJ96*(1+AK$85) -> 176.2475 | AL96: =AK96*(1+AL$85) -> 192.99101 | AM96: =AL96*(1+AM$85) -> 210.3602 | AN96: =AM96*(1+AN$85) -> 228.24082 | AO96: =AN96*(1+AO$85) -> 246.50009 | AP96: =AO96*(1+AP$85) -> 263.75509 | AQ96: =AP96*(1+AQ$85) -> 280.89917 | ... AT96: =AS96*(1+AT$85) -> 328.27282
A97: премикс | C97: БМВД | D97: тг/кг | J97: 145 | K97: 145 | L97: 145 | M97: 145 | N97: 145 | O97: =J97*(1+$O$85) -> 160.225 | P97: =O97 -> 160.225 | Q97: =P97 -> 160.225 | R97: =Q97 -> 160.225 | S97: =R97 -> 160.225 | T97: =S97 -> 160.225 | U97: =T97 -> 160.225 | V97: =U97 -> 160.225 | W97: =V97 -> 160.225 | ... Z97: =Y97 -> 160.225 | AA97: =Z97*(1+$AA$85) -> 176.2475 | AB97: =AA97 -> 176.2475 | AC97: =AB97 -> 176.2475 | AD97: =AC97 -> 176.2475 | AE97: =AD97 -> 176.2475 | AF97: =AE97 -> 176.2475 | AG97: =AF97 -> 176.2475 | AI97: =J97 -> 145 | AJ97: =AI97*(1+AJ$85) -> 160.225 | AK97: =AJ97*(1+AK$85) -> 176.2475 | AL97: =AK97*(1+AL$85) -> 192.99101 | AM97: =AL97*(1+AM$85) -> 210.3602 | AN97: =AM97*(1+AN$85) -> 228.24082 | AO97: =AN97*(1+AO$85) -> 246.50009 | AP97: =AO97*(1+AP$85) -> 263.75509 | AQ97: =AP97*(1+AQ$85) -> 280.89917 | ... AT97: =AS97*(1+AT$85) -> 328.27282
A98: сочные корма | C98: Дерть ячменная | D98: тг/кг | J98: 36 | K98: 36 | L98: 36 | M98: 36 | N98: 36 | O98: =J98*(1+$O$85) -> 39.78 | P98: =O98 -> 39.78 | Q98: =P98 -> 39.78 | R98: =Q98 -> 39.78 | S98: =R98 -> 39.78 | T98: =S98 -> 39.78 | U98: =T98 -> 39.78 | V98: =U98 -> 39.78 | W98: =V98 -> 39.78 | ... Z98: =Y98 -> 39.78 | AA98: =Z98*(1+$AA$85) -> 43.758 | AB98: =AA98 -> 43.758 | AC98: =AB98 -> 43.758 | AD98: =AC98 -> 43.758 | AE98: =AD98 -> 43.758 | AF98: =AE98 -> 43.758 | AG98: =AF98 -> 43.758 | AI98: =J98 -> 36 | AJ98: =AI98*(1+AJ$85) -> 39.78 | AK98: =AJ98*(1+AK$85) -> 43.758 | AL98: =AK98*(1+AL$85) -> 47.91501 | AM98: =AL98*(1+AM$85) -> 52.227361 | AN98: =AM98*(1+AN$85) -> 56.666687 | AO98: =AN98*(1+AO$85) -> 61.200022 | AP98: =AO98*(1+AP$85) -> 65.484023 | AQ98: =AP98*(1+AQ$85) -> 69.740485 | ... AT98: =AS98*(1+AT$85) -> 81.502217
A99: концентрат | C99: Зерноотходы | D99: тг/кг | J99: 63 | K99: 63 | L99: 63 | M99: 63 | N99: 63 | O99: =J99*(1+$O$85) -> 69.615 | P99: =O99 -> 69.615 | Q99: =P99 -> 69.615 | R99: =Q99 -> 69.615 | S99: =R99 -> 69.615 | T99: =S99 -> 69.615 | U99: =T99 -> 69.615 | V99: =U99 -> 69.615 | W99: =V99 -> 69.615 | ... Z99: =Y99 -> 69.615 | AA99: =Z99*(1+$AA$85) -> 76.5765 | AB99: =AA99 -> 76.5765 | AC99: =AB99 -> 76.5765 | AD99: =AC99 -> 76.5765 | AE99: =AD99 -> 76.5765 | AF99: =AE99 -> 76.5765 | AG99: =AF99 -> 76.5765 | AI99: =J99 -> 63 | AJ99: =AI99*(1+AJ$85) -> 69.615 | AK99: =AJ99*(1+AK$85) -> 76.5765 | AL99: =AK99*(1+AL$85) -> 83.851267 | AM99: =AL99*(1+AM$85) -> 91.397882 | AN99: =AM99*(1+AN$85) -> 99.166702 | AO99: =AN99*(1+AO$85) -> 107.10004 | AP99: =AO99*(1+AP$85) -> 114.59704 | AQ99: =AP99*(1+AQ$85) -> 122.04585 | ... AT99: =AS99*(1+AT$85) -> 142.62888
A101: х | B101: Расчет привесов исходя из цикла
C103: Маточное поголовье | D103: г/сут | F103: 0 | J103: 0 | K103: 0 | L103: 0 | M103: 0 | N103: 0 | O103: 0 | P103: 0 | Q103: 0 | R103: 0 | S103: 0 | T103: 0 | U103: 0 | V103: 0 | W103: 0 | X103: 0 | Y103: 0 | Z103: 0 | AA103: 0 | AB103: 0 | AC103: 0 | AD103: 0 | AE103: 0 | AF103: 0 | AG103: 0 | AI103: 600 | AJ103: =AI103 -> 600 | AK103: =AJ103 -> 600 | AL103: =AK103 -> 600 | AM103: =AL103 -> 600 | AN103: =AM103 -> 600 | AO103: =AN103 -> 600 | AP103: =AO103 -> 600 | AQ103: =AP103 -> 600 | ... AT103: =AS103 -> 600
C104: Быки производители | D104: г/сут | F104: 0 | J104: 0 | K104: 0 | L104: 0 | M104: 0 | N104: 0 | O104: 0 | P104: 0 | Q104: 0 | R104: 0 | S104: 0 | T104: 0 | U104: 0 | V104: 0 | W104: 0 | X104: 0 | Y104: 0 | Z104: 0 | AA104: 0 | AB104: 0 | AC104: 0 | AD104: 0 | AE104: 0 | AF104: 0 | AG104: 0 | AI104: 750 | AJ104: =AI104 -> 750 | AK104: =AJ104 -> 750 | AL104: =AK104 -> 750 | AM104: =AL104 -> 750 | AN104: =AM104 -> 750 | AO104: =AN104 -> 750 | AP104: =AO104 -> 750 | AQ104: =AP104 -> 750 | ... AT104: =AS104 -> 750
C105: Молодняк | D105: г/сут | F105: 850 | J105: 0 | K105: 0 | L105: 0 | M105: 0 | N105: 0 | O105: 0 | P105: 0 | Q105: 0 | R105: 0 | S105: 0 | T105: 0 | U105: 0 | V105: 0 | W105: 0 | X105: 0 | Y105: 0 | Z105: 0 | AA105: 0 | AB105: 0 | AC105: 0 | AD105: 0 | AE105: 0 | AF105: 0 | AG105: 0 | AI105: =25+F105/1000*30*AK115 -> 203.5 | AJ105: =AI105 -> 203.5 | AK105: =AJ105 -> 203.5 | AL105: =AK105 -> 203.5 | AM105: =AL105 -> 203.5 | AN105: =AM105 -> 203.5 | AO105: =AN105 -> 203.5 | AP105: =AO105 -> 203.5 | AQ105: =AP105 -> 203.5 | ... AT105: =AS105 -> 203.5
C106: Телочки | D106: г/сут | F106: 810 | J106: 0 | K106: 0 | L106: 0 | M106: 0 | N106: 0 | O106: 0 | P106: 0 | Q106: 0 | R106: 0 | S106: 0 | T106: 0 | U106: 0 | V106: 0 | W106: 0 | X106: 0 | Y106: 0 | Z106: 0 | AA106: 0 | AB106: 0 | AC106: 0 | AD106: 0 | AE106: 0 | AF106: 0 | AG106: 0 | AI106: =F106/1000*30*AL116+AI105 -> 276.4 | AJ106: =AI106 -> 276.4 | AK106: =AJ106 -> 276.4 | AL106: =AK106 -> 276.4 | AM106: =AL106 -> 276.4 | AN106: =AM106 -> 276.4 | AO106: =AN106 -> 276.4 | AP106: =AO106 -> 276.4 | AQ106: =AP106 -> 276.4 | ... AT106: =AS106 -> 276.4
C107: Бычки | D107: г/сут | F107: 850 | J107: 0 | K107: 0 | L107: 0 | M107: 0 | N107: 0 | O107: 0 | P107: 0 | Q107: 0 | R107: 0 | S107: 0 | T107: 0 | U107: 0 | V107: 0 | W107: 0 | X107: 0 | Y107: 0 | Z107: 0 | AA107: 0 | AB107: 0 | AC107: 0 | AD107: 0 | AE107: 0 | AF107: 0 | AG107: 0 | AI107: =F107/1000*30*AK118+AI105 -> 331 | AJ107: =AI107 -> 331 | AK107: =AJ107 -> 331 | AL107: =AK107 -> 331 | AM107: =AL107 -> 331 | AN107: =AM107 -> 331 | AO107: =AN107 -> 331 | AP107: =AO107 -> 331 | AQ107: =AP107 -> 331 | ... AT107: =AS107 -> 331
C108: Закупаемые бычки | D108: г/сут | F108: 800 | J108: 0 | K108: 0 | L108: 0 | M108: 0 | N108: 0 | O108: 0 | P108: 0 | Q108: 0 | R108: 0 | S108: 0 | T108: 0 | U108: 0 | V108: 0 | W108: 0 | X108: 0 | Y108: 0 | Z108: 0 | AA108: 0 | AB108: 0 | AC108: 0 | AD108: 0 | AE108: 0 | AF108: 0 | AG108: 0 | AI108: =F108/1000*30*AK119+AI105 -> 347.5 | AJ108: =AI108 -> 347.5 | AK108: =AJ108 -> 347.5 | AL108: =AK108 -> 347.5 | AM108: =AL108 -> 347.5 | AN108: =AM108 -> 347.5 | AO108: =AN108 -> 347.5 | AP108: =AO108 -> 347.5 | AQ108: =AP108 -> 347.5 | ... AT108: =AS108 -> 347.5
A110: х | B110: Расчет циклов
C112: Маточное поголовье полный год | D112: мес | J112: =IF('Cattle Feeding Cycle'!J225<0,1,0) -> 0 | K112: =IF('Cattle Feeding Cycle'!K225<0,1,0) -> 0 | L112: =IF('Cattle Feeding Cycle'!L225<0,1,0) -> 0 | M112: =IF('Cattle Feeding Cycle'!M225<0,1,0) -> 0 | N112: =IF('Cattle Feeding Cycle'!N225<0,1,0) -> 0 | O112: =IF('Cattle Feeding Cycle'!O225<0,1,0) -> 0 | P112: =IF('Cattle Feeding Cycle'!P225<0,1,0) -> 0 | Q112: =IF('Cattle Feeding Cycle'!Q225<0,1,0) -> 0 | ... AG112: =IF('Cattle Feeding Cycle'!AG225<0,1,0) -> 1 | AI112: =SUMIF($J$145:$AF$145,AI$145,$J112:$AF112) -> 0 | AJ112: =SUMIF($J$145:$AF$145,AJ$145,$J112:$AF112) -> 9 | AK112: 9 | AL112: 9 | AM112: 9 | AN112: 9 | AO112: 9 | AP112: 9 | AQ112: 9 | AR112: 9 | AS112: 9 | AT112: 9
C113: Маточное поголовье 9 мес. | D113: мес
C114: Быки производители | D114: мес | J114: =IF('Cattle Feeding Cycle'!J245<0,1,0) -> 1 | K114: =IF('Cattle Feeding Cycle'!K245<0,1,0) -> 1 | L114: =IF('Cattle Feeding Cycle'!L245<0,1,0) -> 1 | M114: =IF('Cattle Feeding Cycle'!M245<0,1,0) -> 1 | N114: =IF('Cattle Feeding Cycle'!N245<0,1,0) -> 1 | O114: =IF('Cattle Feeding Cycle'!O245<0,1,0) -> 1 | P114: =IF('Cattle Feeding Cycle'!P245<0,1,0) -> 1 | Q114: =IF('Cattle Feeding Cycle'!Q245<0,1,0) -> 1 | ... AG114: =IF('Cattle Feeding Cycle'!AG245<0,1,0) -> 1 | AI114: =SUMIF($J$145:$AF$145,AI$145,$J114:$AF114) -> 5 | AJ114: =SUMIF($J$145:$AF$145,AJ$145,$J114:$AF114) -> 12 | AK114: 12 | AL114: 12 | AM114: 12 | AN114: 12 | AO114: 12 | AP114: 12 | AQ114: 12 | AR114: 12 | AS114: 12 | AT114: 12
C115: Молодняк | D115: мес | J115: =IF('Cattle Feeding Cycle'!J192<0,1,0) -> 0 | K115: =IF('Cattle Feeding Cycle'!K192<0,1,0) -> 0 | L115: =IF('Cattle Feeding Cycle'!L192<0,1,0) -> 0 | M115: =IF('Cattle Feeding Cycle'!M192<0,1,0) -> 0 | N115: =IF('Cattle Feeding Cycle'!N192<0,1,0) -> 0 | O115: =IF('Cattle Feeding Cycle'!O192<0,1,0) -> 0 | P115: =IF('Cattle Feeding Cycle'!P192<0,1,0) -> 0 | Q115: =IF('Cattle Feeding Cycle'!Q192<0,1,0) -> 0 | ... AG115: =IF('Cattle Feeding Cycle'!AG192<0,1,0) -> 1 | AI115: =SUMIF($J$145:$AF$145,AI$145,$J115:$AF115) -> 0 | AJ115: =SUMIF($J$145:$AF$145,AJ$145,$J115:$AF115) -> 0 | AK115: 7 | AL115: 7 | AM115: 7 | AN115: 7 | AO115: 7 | AP115: 7 | AQ115: 7 | AR115: 7 | AS115: 7 | AT115: 7
C116: Телочки - предыдыщего года | D116: мес | J116: =IF('Cattle Feeding Cycle'!J203<0,1,0) -> 1 | K116: =IF('Cattle Feeding Cycle'!K203<0,1,0) -> 1 | L116: =IF('Cattle Feeding Cycle'!L203<0,1,0) -> 1 | M116: =IF('Cattle Feeding Cycle'!M203<0,1,0) -> 1 | N116: =IF('Cattle Feeding Cycle'!N203<0,1,0) -> 1 | O116: =IF('Cattle Feeding Cycle'!O203<0,1,0) -> 1 | P116: =IF('Cattle Feeding Cycle'!P203<0,1,0) -> 1 | Q116: =IF('Cattle Feeding Cycle'!Q203<0,1,0) -> 1 | ... AG116: =IF('Cattle Feeding Cycle'!AG203<0,1,0) -> 0 | AI116: =SUMIF($J$145:$AF$145,AI$145,$J116:$AF116) -> 5 | AJ116: =SUMIF($J$145:$AG$145,AJ$145,$J116:$AG116) -> 3 | AK116: 3 | AL116: 3 | AM116: 3 | AN116: 3 | AO116: 3 | AP116: 3 | AQ116: 3 | AR116: 3 | AS116: 3 | AT116: 3
C117: Телочки - текущего периода | D117: мес | J117: 0 | K117: 0 | L117: 0 | M117: 0 | N117: 0 | O117: 0 | P117: 0 | Q117: 0 | R117: 0 | S117: 0 | T117: 0 | U117: 0 | V117: 0 | W117: 0 | X117: 0 | Y117: 0 | Z117: 0 | AA117: 0 | AB117: 0 | AC117: 0 | AD117: 0 | AE117: 0 | AF117: 0 | AG117: 0 | AI117: =SUMIF($J$145:$AF$145,AI$145,$J117:$AF117) -> 0 | AJ117: =SUMIF($J$145:$AG$145,AJ$145,$J117:$AG117) -> 0 | AK117: 5
...

Sheet Loans
B1: Займы Большой Фермы Управляющей компании
B2: Дата выдачи | E2: 46235
B3: Сумма займа АКК | D3: тыс. тенге | E3: =Input!G56 -> 358330.37
B4: Ставка вознагр. | D4: % | E4: =Output!D190 -> 0.05
B5: Срок | D5: лет | E5: 10
B6: Льготный период | D6: лет | E6: 2
B8: Погашение процентов | D8: мес. | E8: 12 | G8: каждые 12 мес.
B9: Погашение ОД | D9: мес. | E9: 12 | G9: каждые 12 мес.
B11: Погашение ОД | D11: 2026 | E11: 0 | F11: =$E$3*E11 -> 0
D12: =D11+1 -> 2027 | E12: 0 | F12: =$E$3*E12 -> 0
C13: =100%/9 -> 0.11111111 | D13: =D12+1 -> 2028 | E13: 0.11 | F13: =$E$3*E13 -> 39416.341
D14: =D13+1 -> 2029 | E14: 0.11 | F14: =$E$3*E14 -> 39416.341
D15: =D14+1 -> 2030 | E15: 0.11 | F15: =$E$3*E15 -> 39416.341
D16: =D15+1 -> 2031 | E16: 0.11 | F16: =$E$3*E16 -> 39416.341
D17: =D16+1 -> 2032 | E17: 0.11 | F17: =$E$3*E17 -> 39416.341
D18: =D17+1 -> 2033 | E18: 0.11 | F18: =$E$3*E18 -> 39416.341
D19: =D18+1 -> 2034 | E19: 0.11 | F19: =$E$3*E19 -> 39416.341
D20: =D19+1 -> 2035 | E20: 0.11 | F20: =$E$3*E20 -> 39416.341
D21: =D20+1 -> 2036 | E21: =100%-SUM(E11:E20) -> 0.12 | F21: =$E$3*E21 -> 42999.645
E22: =SUM(E11:E21) -> 1 | F22: =SUM(F11:F21) -> 358330.37
J23: =YEAR(J26) -> 2026 | K23: =YEAR(K26) -> 2026 | L23: =YEAR(L26) -> 2026 | M23: =YEAR(M26) -> 2026 | N23: =YEAR(N26) -> 2026 | O23: =YEAR(O26) -> 2027 | P23: =YEAR(P26) -> 2027 | Q23: =YEAR(Q26) -> 2027 | ... DY23: =YEAR(DY26) -> 2036
J24: 1 | K24: =J24+1 -> 2 | L24: =K24+1 -> 3 | M24: =L24+1 -> 4 | N24: =M24+1 -> 5 | O24: =N24+1 -> 6 | P24: =O24+1 -> 7 | Q24: =P24+1 -> 8 | R24: =Q24+1 -> 9 | ... DY24: =DX24+1 -> 120
A25: х | B25: График финансовых обязательств
B26: Инвестиционный кредит | J26: ='Operating Model'!J280 -> 46265 | K26: =EDATE(J26,1) -> 46295 | L26: =EDATE(K26,1) -> 46325 | M26: =EDATE(L26,1) -> 46356 | N26: =EDATE(M26,1) -> 46386 | O26: =EDATE(N26,1) -> 46417 | P26: =EDATE(O26,1) -> 46446 | Q26: =EDATE(P26,1) -> 46474 | R26: =EDATE(Q26,1) -> 46505 | ... DY26: =EDATE(DX26,1) -> 49884
B27: Средства доступные для погашения займа БВУ | D27: тыс. тенге
B28: Сумма займа БВУ | D28: тыс. тенге | J28: =E3 -> 358330.37
B31: ОД на начало | D31: тыс. тенге | J31: =E3 -> 358330.37 | K31: =J37 -> 358330.37 | L31: =K37 -> 358330.37 | M31: =L37 -> 358330.37 | N31: =M37 -> 358330.37 | O31: =N37 -> 358330.37 | P31: =O37 -> 358330.37 | Q31: =P37 -> 358330.37 | R31: =Q37 -> 358330.37 | ... DY31: =DX37 -> 42999.645
B32: Начисление процентов | D32: тыс. тенге | J32: =J31*$E$4*(J26-E2)/365 -> 1472.5906 | K32: =K31*$E$4*(K26-J26)/365 -> 1472.5906 | L32: =L31*$E$4*(L26-K26)/365 -> 1472.5906 | M32: =M31*$E$4*(M26-L26)/365 -> 1521.6769 | N32: =N31*$E$4*(N26-M26)/365 -> 1472.5906 | O32: =O31*$E$4*(O26-N26)/365 -> 1521.6769 | P32: =P31*$E$4*(P26-O26)/365 -> 1423.5042 | Q32: =Q31*$E$4*(Q26-P26)/365 -> 1374.4179 | R32: =R31*$E$4*(R26-Q26)/365 -> 1521.6769 | ... DY32: =DY31*$E$4*(DY26-DX26)/365 -> 176.71087
B33: Погашение процентов | D33: тыс. тенге | J33: 0 | K33: 0 | L33: 0 | M33: 0 | N33: 0 | O33: 0 | P33: 0 | Q33: 0 | R33: 0 | S33: 0 | T33: 0 | U33: 0 | V33: 0 | W33: 0 | X33: 0 | Y33: 0 | Z33: 0 | AA33: 0 | AB33: 0 | AC33: 0 | AD33: 0 | AE33: 0 | AF33: 0 | AG33: =AG34*(1/9) -> 3965.0865 | AH33: 0 | AI33: 0 | AJ33: 0 | AK33: 0 | AL33: 0 | AM33: 0 | AN33: 0 | AO33: 0 | AP33: 0 | AQ33: 0 | AR33: 0 | AS33: =SUM(AH32:AS32)+$AG$33 -> 19910.788 | AT33: 0 | AU33: 0 | AV33: 0 | AW33: 0 | AX33: 0 | AY33: 0 | AZ33: 0 | BA33: 0 | BB33: 0 | BC33: 0 | BD33: 0 | BE33: =SUM(AT32:BE32)+$AG$33 -> 17939.971 | BF33: 0 | BG33: 0 | BH33: 0 | BI33: 0 | BJ33: 0 | BK33: 0 | BL33: 0 | BM33: 0 | BN33: 0 | BO33: 0 | BP33: 0 | BQ33: =SUM(BF32:BQ32)+$AG$33 -> 15969.154 | BR33: 0 | BS33: 0 | BT33: 0 | BU33: 0 | BV33: 0 | BW33: 0 | BX33: 0 | BY33: 0 | BZ33: 0 | CA33: 0 | CB33: 0 | CC33: =SUM(BR32:CC32)+$AG$33 -> 14025.825 | CD33: 0 | CE33: 0 | CF33: 0 | CG33: 0 | CH33: 0 | CI33: 0 | CJ33: 0 | CK33: 0 | CL33: 0 | CM33: 0 | CN33: 0 | CO33: =SUM(CD32:CO32)+$AG$33 -> 12027.52 | CP33: 0 | CQ33: 0 | CR33: 0 | CS33: 0 | CT33: 0 | CU33: 0 | CV33: 0 | CW33: 0 | CX33: 0 | CY33: 0 | CZ33: 0 | DA33: =SUM(CP32:DA32)+$AG$33 -> 10056.703 | DB33: 0 | DC33: 0 | DD33: 0 | DE33: 0 | DF33: 0 | DG33: 0 | DH33: 0 | DI33: 0 | DJ33: 0 | DK33: 0 | DL33: 0 | DM33: =SUM(DB32:DM32)+$AG$33 -> 8085.8858 | DN33: 0 | DO33: 0 | DP33: 0 | DQ33: 0 | DR33: 0 | DS33: 0 | DT33: 0 | DU33: 0 | DV33: 0 | DW33: 0 | DX33: 0 | DY33: =SUM(DN32:DY32)+$AG$33 -> 6120.9591
AG34: =SUM(J32:AG32) -> 35685.778 | AS34: =SUM(AH32:AS32) -> 15945.702
B35: Накопленные проценты | D35: тыс. тенге | J35: =J32-J33 -> 1472.5906 | K35: =K32-K33+J35 -> 2945.1812 | L35: =L32-L33+K35 -> 4417.7717 | M35: =M32-M33+L35 -> 5939.4487 | N35: =N32-N33+M35 -> 7412.0392 | O35: =O32-O33+N35 -> 8933.7162 | P35: =P32-P33+O35 -> 10357.22 | Q35: =Q32-Q33+P35 -> 11731.638 | R35: =R32-R33+Q35 -> 13253.315 | ... DY35: =DY32-DY33+DX35 -> -1.4551915e-11
B36: Погашение ОД (10 лет - льготный период 2 года) | D36: тыс. тенге | J36: 0 | K36: 0 | L36: 0 | M36: 0 | N36: 0 | O36: 0 | P36: 0 | Q36: 0 | R36: 0 | S36: 0 | T36: 0 | U36: 0 | V36: 0 | W36: 0 | X36: 0 | Y36: 0 | Z36: 0 | AA36: 0 | AB36: 0 | AC36: 0 | AD36: 0 | AE36: 0 | AF36: 0 | AG36: =F13 -> 39416.341 | AH36: 0 | AI36: 0 | AJ36: 0 | AK36: 0 | AL36: 0 | AM36: 0 | AN36: 0 | AO36: 0 | AP36: 0 | AQ36: 0 | AR36: 0 | AS36: =F14 -> 39416.341 | AT36: 0 | AU36: 0 | AV36: 0 | AW36: 0 | AX36: 0 | AY36: 0 | AZ36: 0 | BA36: 0 | BB36: 0 | BC36: 0 | BD36: 0 | BE36: =F15 -> 39416.341 | BF36: 0 | BG36: 0 | BH36: 0 | BI36: 0 | BJ36: 0 | BK36: 0 | BL36: 0 | BM36: 0 | BN36: 0 | BO36: 0 | BP36: 0 | BQ36: =F16 -> 39416.341 | BR36: 0 | BS36: 0 | BT36: 0 | BU36: 0 | BV36: 0 | BW36: 0 | BX36: 0 | BY36: 0 | BZ36: 0 | CA36: 0 | CB36: 0 | CC36: =F17 -> 39416.341 | CD36: 0 | CE36: 0 | CF36: 0 | CG36: 0 | CH36: 0 | CI36: 0 | CJ36: 0 | CK36: 0 | CL36: 0 | CM36: 0 | CN36: 0 | CO36: =F18 -> 39416.341 | CP36: 0 | CQ36: 0 | CR36: 0 | CS36: 0 | CT36: 0 | CU36: 0 | CV36: 0 | CW36: 0 | CX36: 0 | CY36: 0 | CZ36: 0 | DA36: =F19 -> 39416.341 | DB36: 0 | DC36: 0 | DD36: 0 | DE36: 0 | DF36: 0 | DG36: 0 | DH36: 0 | DI36: 0 | DJ36: 0 | DK36: 0 | DL36: 0 | DM36: =F20 -> 39416.341 | DN36: 0 | DO36: 0 | DP36: 0 | DQ36: 0 | DR36: 0 | DS36: 0 | DT36: 0 | DU36: 0 | DV36: 0 | DW36: 0 | DX36: 0 | DY36: =F21 -> 42999.645
B37: ОД на конец | D37: тыс. тенге | J37: =J31-J36 -> 358330.37 | K37: =K31-K36 -> 358330.37 | L37: =L31-L36 -> 358330.37 | M37: =M31-M36 -> 358330.37 | N37: =N31-N36 -> 358330.37 | O37: =O31-O36 -> 358330.37 | P37: =P31-P36 -> 358330.37 | Q37: =Q31-Q36 -> 358330.37 | ... DY37: =DY31-DY36 -> -7.2759576e-11
B43: Займы 2ой год
B44: Дата выдачи | E44: 46235
B45: Сумма займа АКК | D45: тыс. тенге | E45: =Input!K56 -> 0
B46: Ставка вознагр. | D46: % | E46: =Output!L190 -> 0
B47: Срок | D47: лет | E47: 10
B48: Льготный период | D48: лет | E48: 2
B50: Погашение процентов | D50: мес. | E50: 12 | G50: каждые 12 мес.
B51: Погашение ОД | D51: мес. | E51: 12 | G51: каждые 12 мес.
B53: Погашение ОД | D53: 2026 | E53: 0 | F53: =$E$3*E53 -> 0
D54: =D53+1 -> 2027 | E54: 0 | F54: =$E$3*E54 -> 0
D55: =D54+1 -> 2028 | E55: 0.03 | F55: =$E$3*E55 -> 10749.911
D56: =D55+1 -> 2029 | E56: 0.03 | F56: =$E$3*E56 -> 10749.911
D57: =D56+1 -> 2030 | E57: 0.05 | F57: =$E$3*E57 -> 17916.519
D58: =D57+1 -> 2031 | E58: 0.05 | F58: =$E$3*E58 -> 17916.519
D59: =D58+1 -> 2032 | E59: 0.1 | F59: =$E$3*E59 -> 35833.037
D60: =D59+1 -> 2033 | E60: 0.1 | F60: =$E$3*E60 -> 35833.037
D61: =D60+1 -> 2034 | E61: 0.2 | F61: =$E$3*E61 -> 71666.075
D62: =D61+1 -> 2035 | E62: 0.2 | F62: =$E$3*E62 -> 71666.075
D63: =D62+1 -> 2036 | E63: =100%-SUM(E53:E62) -> 0.24 | F63: =$E$3*E63 -> 85999.29
E64: =SUM(E53:E63) -> 1 | F64: =SUM(F53:F63) -> 358330.37
J67: =YEAR(J70) -> 2026 | K67: =YEAR(K70) -> 2026 | L67: =YEAR(L70) -> 2026 | M67: =YEAR(M70) -> 2026 | N67: =YEAR(N70) -> 2026 | O67: =YEAR(O70) -> 2027 | P67: =YEAR(P70) -> 2027 | Q67: =YEAR(Q70) -> 2027 | ... DY67: =YEAR(DY70) -> 2036
J68: 1 | K68: =J68+1 -> 2 | L68: =K68+1 -> 3 | M68: =L68+1 -> 4 | N68: =M68+1 -> 5 | O68: =N68+1 -> 6 | P68: =O68+1 -> 7 | Q68: =P68+1 -> 8 | R68: =Q68+1 -> 9 | ... DY68: =DX68+1 -> 120
A69: х | B69: График финансовых обязательств
B70: Инвестиционный кредит | J70: =J26 -> 46265 | K70: =EDATE(J70,1) -> 46295 | L70: =EDATE(K70,1) -> 46325 | M70: =EDATE(L70,1) -> 46356 | N70: =EDATE(M70,1) -> 46386 | O70: =EDATE(N70,1) -> 46417 | P70: =EDATE(O70,1) -> 46446 | Q70: =EDATE(P70,1) -> 46474 | R70: =EDATE(Q70,1) -> 46505 | ... DY70: =EDATE(DX70,1) -> 49884
B71: Средства доступные для погашения займа БВУ | D71: тыс. тенге
B72: Сумма займа БВУ | D72: тыс. тенге | J72: 0 | S72: =E45 -> 0
B75: ОД на начало | D75: тыс. тенге | J75: 0 | K75: =J80 -> 0 | L75: =K80 -> 0 | M75: =L80 -> 0 | N75: =M80 -> 0 | O75: =N80 -> 0 | P75: =O80 -> 0 | Q75: =P80 -> 0 | R75: =Q80 -> 0 | S75: =E45 -> 0 | T75: =S80 -> 0 | U75: =T80 -> 0 | V75: =U80 -> 0 | W75: =V80 -> 0 | X75: =W80 -> 0 | Y75: =X80 -> 0 | Z75: =Y80 -> 0 | AA75: =Z80 -> 0 | ... DY75: =DX80 -> 0
B76: Начисление процентов | D76: тыс. тенге | J76: =J75*$E$46*(J70-E44)/365 -> 0 | K76: =K75*$E$46*(K70-J70)/365 -> 0 | L76: =L75*$E$46*(L70-K70)/365 -> 0 | M76: =M75*$E$46*(M70-L70)/365 -> 0 | N76: =N75*$E$46*(N70-M70)/365 -> 0 | O76: =O75*$E$46*(O70-N70)/365 -> 0 | P76: =P75*$E$46*(P70-O70)/365 -> 0 | Q76: =Q75*$E$46*(Q70-P70)/365 -> 0 | R76: =R75*$E$46*(R70-Q70)/365 -> 0 | ... DY76: =DY75*$E$46*(DY70-DX70)/365 -> 0
B77: Погашение процентов | D77: тыс. тенге | J77: 0 | K77: 0 | L77: 0 | M77: 0 | N77: 0 | O77: 0 | P77: 0 | Q77: 0 | R77: 0 | S77: 0 | T77: 0 | U77: =SUM(J76:U76) -> 0 | V77: 0 | W77: 0 | X77: 0 | Y77: 0 | Z77: 0 | AA77: 0 | AB77: 0 | AC77: 0 | AD77: 0 | AE77: 0 | AF77: 0 | AG77: =SUM(V76:AG76) -> 0 | AH77: 0 | AI77: 0 | AJ77: 0 | AK77: 0 | AL77: 0 | AM77: 0 | AN77: 0 | AO77: 0 | AP77: 0 | AQ77: 0 | AR77: 0 | AS77: =SUM(AH76:AS76) -> 0 | AT77: 0 | AU77: 0 | AV77: 0 | AW77: 0 | AX77: 0 | AY77: 0 | AZ77: 0 | BA77: 0 | BB77: 0 | BC77: 0 | BD77: 0 | BE77: =SUM(AT76:BE76) -> 0 | BF77: 0 | BG77: 0 | BH77: 0 | BI77: 0 | BJ77: 0 | BK77: 0 | BL77: 0 | BM77: 0 | BN77: 0 | BO77: 0 | BP77: 0 | BQ77: =SUM(BF76:BQ76) -> 0 | BR77: 0 | BS77: 0 | BT77: 0 | BU77: 0 | BV77: 0 | BW77: 0 | BX77: 0 | BY77: 0 | BZ77: 0 | CA77: 0 | CB77: 0 | CC77: =SUM(BR76:CC76) -> 0 | CD77: 0 | CE77: 0 | CF77: 0 | CG77: 0 | CH77: 0 | CI77: 0 | CJ77: 0 | CK77: 0 | CL77: 0 | CM77: 0 | CN77: 0 | CO77: =SUM(CD76:CO76) -> 0 | CP77: 0 | CQ77: 0 | CR77: 0 | CS77: 0 | CT77: 0 | CU77: 0 | CV77: 0 | CW77: 0 | CX77: 0 | CY77: 0 | CZ77: 0 | DA77: =SUM(CP76:DA76) -> 0 | DB77: 0 | DC77: 0 | DD77: 0 | DE77: 0 | DF77: 0 | DG77: 0 | DH77: 0 | DI77: 0 | DJ77: 0 | DK77: 0 | DL77: 0 | DM77: =SUM(DB76:DM76) -> 0 | DN77: 0 | DO77: 0 | DP77: 0 | DQ77: 0 | DR77: 0 | DS77: 0 | DT77: 0 | DU77: 0 | DV77: 0 | DW77: 0 | DX77: 0 | DY77: =SUM(DN76:DY76) -> 0
B78: Накопленные проценты | D78: тыс. тенге | J78: =J76-J77+I78 -> 0 | K78: =K76-K77+J78 -> 0 | L78: =L76-L77+K78 -> 0 | M78: =M76-M77+L78 -> 0 | N78: =N76-N77+M78 -> 0 | O78: =O76-O77+N78 -> 0 | P78: =P76-P77+O78 -> 0 | Q78: =Q76-Q77+P78 -> 0 | ... DY78: =DY76-DY77+DX78 -> 0
B79: Погашение ОД (10 лет - льготный период 2 года) | D79: тыс. тенге | J79: 0 | K79: 0 | L79: 0 | M79: 0 | N79: 0 | O79: 0 | P79: 0 | Q79: 0 | R79: 0 | S79: 0 | T79: 0 | U79: 0 | V79: 0 | W79: 0 | X79: 0 | Y79: 0 | Z79: 0 | AA79: 0 | AB79: 0 | AC79: 0 | AD79: 0 | AE79: 0 | AF79: 0 | AG79: =$E$45*E55 -> 0 | AH79: 0 | AI79: 0 | AJ79: 0 | AK79: 0 | AL79: 0 | AM79: 0 | AN79: 0 | AO79: 0 | AP79: 0 | AQ79: 0 | AR79: 0 | AS79: =$E$45*E56 -> 0 | AT79: 0 | AU79: 0 | AV79: 0 | AW79: 0 | AX79: 0 | AY79: 0 | AZ79: 0 | BA79: 0 | BB79: 0 | BC79: 0 | BD79: 0 | BE79: =$E$45*E57 -> 0 | BF79: 0 | BG79: 0 | BH79: 0 | BI79: 0 | BJ79: 0 | BK79: 0 | BL79: 0 | BM79: 0 | BN79: 0 | BO79: 0 | BP79: 0 | BQ79: =$E$45*E58 -> 0 | BR79: 0 | BS79: 0 | BT79: 0 | BU79: 0 | BV79: 0 | BW79: 0 | BX79: 0 | BY79: 0 | BZ79: 0 | CA79: 0 | CB79: 0 | CC79: =$E$45*E59 -> 0 | CD79: 0 | CE79: 0 | CF79: 0 | CG79: 0 | CH79: 0 | CI79: 0 | CJ79: 0 | CK79: 0 | CL79: 0 | CM79: 0 | CN79: 0 | CO79: =$E$45*E60 -> 0 | CP79: 0 | CQ79: 0 | CR79: 0 | CS79: 0 | CT79: 0 | CU79: 0 | CV79: 0 | CW79: 0 | CX79: 0 | CY79: 0 | CZ79: 0 | DA79: =$E$45*E61 -> 0 | DB79: 0 | DC79: 0 | DD79: 0 | DE79: 0 | DF79: 0 | DG79: 0 | DH79: 0 | DI79: 0 | DJ79: 0 | DK79: 0 | DL79: 0 | DM79: =$E$45*E62 -> 0 | DN79: 0 | DO79: 0 | DP79: 0 | DQ79: 0 | DR79: 0 | DS79: 0 | DT79: 0 | DU79: 0 | DV79: 0 | DW79: 0 | DX79: 0 | DY79: =$E$45*E63 -> 0
B80: ОД на конец | D80: тыс. тенге | J80: =J75-J79 -> 0 | K80: =K75-K79 -> 0 | L80: =L75-L79 -> 0 | M80: =M75-M79 -> 0 | N80: =N75-N79 -> 0 | O80: =O75-O79 -> 0 | P80: =P75-P79 -> 0 | Q80: =Q75-Q79 -> 0 | ... DY80: =DY75-DY79 -> 0

Sheet Staff
AI1: ='Operating Model'!AI2 -> 46387 | AJ1: ='Operating Model'!AJ2 -> 46752 | AK1: ='Operating Model'!AK2 -> 47118 | AL1: ='Operating Model'!AL2 -> 47483 | AM1: ='Operating Model'!AM2 -> 47848 | AN1: ='Operating Model'!AN2 -> 48213 | AO1: ='Operating Model'!AO2 -> 48579 | AP1: ='Operating Model'!AP2 -> 48944 | ... AT1: ='Operating Model'!AT2 -> 50405
A2: х | B2: Расчет заработной платы
A4: х | B4: Макроэкономические показатели
J5: =J13 -> 46265 | K5: =EOMONTH(J5,1) -> 46295 | L5: =EOMONTH(K5,1) -> 46326 | M5: =EOMONTH(L5,1) -> 46356 | N5: =EOMONTH(M5,1) -> 46387 | O5: =EOMONTH(N5,1) -> 46418 | P5: =EOMONTH(O5,1) -> 46446 | Q5: =EOMONTH(P5,1) -> 46477 | R5: =EOMONTH(Q5,1) -> 46507 | ... AG5: =EOMONTH(AF5,1) -> 46965 | AI5: =AI13 -> 2026 | AJ5: =AJ13 -> 2027 | AK5: =AK13 -> 2028 | AL5: =AL13 -> 2029 | AM5: =AM13 -> 2030 | AN5: =AN13 -> 2031 | AO5: =AO13 -> 2032 | AP5: =AP13 -> 2033 | ... AT5: =AT13 -> 2037
B6: ИПЦ в KZ, ср. | D6: % | E6: https://www.imf.org/external/datamapper/profile/KAZ | F6: IMF | J6: =AI6 -> 0.11 | K6: 0 | L6: =K6 -> 0 | M6: =L6 -> 0 | N6: =M6 -> 0 | O6: =AJ6 -> 0.105 | P6: 0 | Q6: =P6 -> 0 | R6: =Q6 -> 0 | S6: =R6 -> 0 | T6: =S6 -> 0 | U6: =T6 -> 0 | V6: =U6 -> 0 | W6: =V6 -> 0 | X6: =W6 -> 0 | ... Z6: =Y6 -> 0 | AA6: =AK6 -> 0.1 | AB6: 0 | AC6: =AB6 -> 0 | AD6: =AC6 -> 0 | AE6: =AD6 -> 0 | AF6: =AE6 -> 0 | AG6: =AF6 -> 0 | AI6: ='Operating Model'!AI31 -> 0.11 | AJ6: ='Operating Model'!AJ31 -> 0.105 | AK6: ='Operating Model'!AK31 -> 0.1 | AL6: ='Operating Model'!AL31 -> 0.095 | AM6: ='Operating Model'!AM31 -> 0.09 | AN6: ='Operating Model'!AN31 -> 0.085 | AO6: ='Operating Model'!AO31 -> 0.08 | AP6: ='Operating Model'!AP31 -> 0.07 | ... AT6: ='Operating Model'!AT31 -> 0.05
C7: Фактор | G7: =1/12 -> 0.083333333
A9: х | B9: Налоговые ставки
J10: 1 | K10: =J10+1 -> 2 | L10: =K10+1 -> 3 | M10: =L10+1 -> 4 | N10: =M10+1 -> 5 | O10: =N10+1 -> 6 | P10: =O10+1 -> 7 | Q10: =P10+1 -> 8 | R10: =Q10+1 -> 9 | ... AG10: =AF10+1 -> 24 | AI10: 5 | AJ10: 12 | AK10: 12 | AL10: 12 | AM10: 12 | AN10: 12 | AO10: 12 | AP10: 12 | AQ10: 12 | AR10: 12 | AS10: 12 | AT10: 12
J12: =YEAR(J14) -> 2026 | K12: =YEAR(K14) -> 2026 | L12: =YEAR(L14) -> 2026 | M12: =YEAR(M14) -> 2026 | N12: =YEAR(N14) -> 2026 | O12: =YEAR(O14) -> 2027 | P12: =YEAR(P14) -> 2027 | Q12: =YEAR(Q14) -> 2027 | ... AG12: =YEAR(AG14) -> 2028 | AI12: =YEAR(AI14) -> 2026 | AJ12: =YEAR(AJ14) -> 2027 | AK12: =YEAR(AK14) -> 2028 | AL12: =YEAR(AL14) -> 2029 | AM12: =YEAR(AM14) -> 2030 | AN12: =YEAR(AN14) -> 2031 | AO12: =YEAR(AO14) -> 2032 | AP12: =YEAR(AP14) -> 2033 | ... AT12: =YEAR(AT14) -> 2037
E13: Год | G13: Месяц | J13: 46265 | K13: =EDATE(J13,1) -> 46295 | L13: =EDATE(K13,1) -> 46325 | M13: =EDATE(L13,1) -> 46356 | N13: =EDATE(M13,1) -> 46386 | O13: =EDATE(N13,1) -> 46417 | P13: =EDATE(O13,1) -> 46446 | Q13: =EDATE(P13,1) -> 46474 | R13: =EDATE(Q13,1) -> 46505 | ... AG13: =EDATE(AF13,1) -> 46962 | AI13: =YEAR(AI1) -> 2026 | AJ13: =YEAR(AJ1) -> 2027 | AK13: =YEAR(AK1) -> 2028 | AL13: =YEAR(AL1) -> 2029 | AM13: =YEAR(AM1) -> 2030 | AN13: =YEAR(AN1) -> 2031 | AO13: =YEAR(AO1) -> 2032 | AP13: =YEAR(AP1) -> 2033 | ... AT13: =YEAR(AT1) -> 2037
J14: 46265 | K14: =EOMONTH(J14,1) -> 46295 | L14: =EOMONTH(K14,1) -> 46326 | M14: =EOMONTH(L14,1) -> 46356 | N14: =EOMONTH(M14,1) -> 46387 | O14: =EOMONTH(N14,1) -> 46418 | P14: =EOMONTH(O14,1) -> 46446 | Q14: =EOMONTH(P14,1) -> 46477 | R14: =EOMONTH(Q14,1) -> 46507 | ... AG14: =EOMONTH(AF14,1) -> 46965 | AI14: 46387 | AJ14: =EOMONTH(AI14,12) -> 46752 | AK14: =EOMONTH(AJ14,12) -> 47118 | AL14: =EOMONTH(AK14,12) -> 47483 | AM14: =EOMONTH(AL14,12) -> 47848 | AN14: =EOMONTH(AM14,12) -> 48213 | AO14: =EOMONTH(AN14,12) -> 48579 | AP14: =EOMONTH(AO14,12) -> 48944 | AQ14: =EOMONTH(AP14,12) -> 49309 | ... AT14: =EOMONTH(AS14,12) -> 50405
C16: Месячный расчетный показатель | D16: тенге | J16: 3932 | K16: 3932 | L16: 3932 | M16: 3932 | N16: 3932 | O16: =N16*(1+O$6) -> 4344.86 | P16: =O16 -> 4344.86 | Q16: =P16 -> 4344.86 | R16: =Q16 -> 4344.86 | S16: =R16 -> 4344.86 | T16: =S16 -> 4344.86 | U16: =T16 -> 4344.86 | V16: =U16 -> 4344.86 | W16: =V16 -> 4344.86 | ... Z16: =Y16 -> 4344.86 | AA16: =Z16*(1+AA6) -> 4779.346 | AB16: =AA16 -> 4779.346 | AC16: =AB16 -> 4779.346 | AD16: =AC16 -> 4779.346 | AE16: =AD16 -> 4779.346 | AF16: =AE16 -> 4779.346 | AG16: =AF16 -> 4779.346 | AI16: 3932 | AJ16: =AI16*(1+AJ6) -> 4344.86 | AK16: =AJ16*(1+AK6) -> 4779.346 | AL16: =AK16*(1+AL6) -> 5233.3839 | AM16: =AL16*(1+AM6) -> 5704.3884 | AN16: =AM16*(1+AN6) -> 6189.2614 | AO16: =AN16*(1+AO6) -> 6684.4023 | AP16: =AO16*(1+AP6) -> 7152.3105 | AQ16: =AP16*(1+AQ6) -> 7617.2107 | ... AT16: =AS16*(1+AT6) -> 8901.8533
C17: Минимальная заработная плата | D17: тыс. тенге / мес. | J17: 93 | K17: =J17 -> 93 | L17: =K17 -> 93 | M17: =L17 -> 93 | N17: =M17 -> 93 | O17: =N17*(1+O$6) -> 102.765 | P17: =O17 -> 102.765 | Q17: =P17 -> 102.765 | R17: =Q17 -> 102.765 | S17: =R17 -> 102.765 | T17: =S17 -> 102.765 | U17: =T17 -> 102.765 | V17: =U17 -> 102.765 | W17: =V17 -> 102.765 | ... Z17: =Y17 -> 102.765 | AA17: =Z17*(1+AA$6) -> 113.0415 | AB17: =AA17 -> 113.0415 | AC17: =AB17 -> 113.0415 | AD17: =AC17 -> 113.0415 | AE17: =AD17 -> 113.0415 | AF17: =AE17 -> 113.0415 | AG17: =AF17 -> 113.0415 | AI17: 85 | AJ17: =AI17*(1+AJ$6) -> 93.925 | AK17: =AJ17*(1+AK$6) -> 103.3175 | AL17: =AK17*(1+AL$6) -> 113.13266 | AM17: =AL17*(1+AM$6) -> 123.3146 | AN17: =AM17*(1+AN$6) -> 133.79634 | AO17: =AN17*(1+AO$6) -> 144.50005 | AP17: =AO17*(1+AP$6) -> 154.61505 | AQ17: =AP17*(1+AQ$6) -> 164.66503 | ... AT17: =AS17*(1+AT$6) -> 192.43579
C18: Максимальный объект расчета исчислений (для СО) | D18: тыс. тенге / мес. | E18: Tax code, RoK | F18: 7 | J18: =$F18*J$17 -> 651 | K18: =$F18*K$17 -> 651 | L18: =$F18*L$17 -> 651 | M18: =$F18*M$17 -> 651 | N18: =$F18*N$17 -> 651 | O18: =$F18*O$17 -> 719.355 | P18: =$F18*P$17 -> 719.355 | Q18: =$F18*Q$17 -> 719.355 | ... AG18: =$F18*AG$17 -> 791.2905 | AI18: =$F18*AI$17 -> 595 | AJ18: =$F18*AJ$17 -> 657.475 | AK18: =$F18*AK$17 -> 723.2225 | AL18: =$F18*AL$17 -> 791.92864 | AM18: =$F18*AM$17 -> 863.20221 | AN18: =$F18*AN$17 -> 936.5744 | AO18: =$F18*AO$17 -> 1011.5004 | AP18: =$F18*AP$17 -> 1082.3054 | ... AT18: =$F18*AT$17 -> 1347.0505
C19: Максимальный объект расчета исчислений (для ОСМС) | D19: тыс. тенге / мес. | E19: Tax code, RoK | F19: 10 | J19: =$F19*J$17 -> 930 | K19: =$F19*K$17 -> 930 | L19: =$F19*L$17 -> 930 | M19: =$F19*M$17 -> 930 | N19: =$F19*N$17 -> 930 | O19: =$F19*O$17 -> 1027.65 | P19: =$F19*P$17 -> 1027.65 | Q19: =$F19*Q$17 -> 1027.65 | ... AG19: =$F19*AG$17 -> 1130.415 | AI19: =$F19*AI$17 -> 850 | AJ19: =$F19*AJ$17 -> 939.25 | AK19: =$F19*AK$17 -> 1033.175 | AL19: =$F19*AL$17 -> 1131.3266 | AM19: =$F19*AM$17 -> 1233.146 | AN19: =$F19*AN$17 -> 1337.9634 | AO19: =$F19*AO$17 -> 1445.0005 | AP19: =$F19*AP$17 -> 1546.1505 | ... AT19: =$F19*AT$17 -> 1924.3579
C20: Минимальный порог на вычеты | D20: МРП | F20: 300
C22: Уровень социальных отчислений | D22: % | E22: Tax code, RoK | F22: 0.035 | J22: =$F22 -> 0.035 | K22: =$F22 -> 0.035 | L22: =$F22 -> 0.035 | M22: =$F22 -> 0.035 | N22: =$F22 -> 0.035 | O22: =$F22 -> 0.035 | P22: =$F22 -> 0.035 | Q22: =$F22 -> 0.035 | ... AG22: =$F22 -> 0.035 | AI22: =$F22 -> 0.035 | AJ22: =$F22 -> 0.035 | AK22: =$F22 -> 0.035 | AL22: =$F22 -> 0.035 | AM22: =$F22 -> 0.035 | AN22: =$F22 -> 0.035 | AO22: =$F22 -> 0.035 | AP22: =$F22 -> 0.035 | ... AT22: =$F22 -> 0.035
C23: Уровень социального налога | D23: % | E23: Tax code, RoK | F23: 0.095 | J23: =$F23 -> 0.095 | K23: =$F23 -> 0.095 | L23: =$F23 -> 0.095 | M23: =$F23 -> 0.095 | N23: =$F23 -> 0.095 | O23: =$F23 -> 0.095 | P23: =$F23 -> 0.095 | Q23: =$F23 -> 0.095 | ... AG23: =$F23 -> 0.095 | AI23: =$F23 -> 0.095 | AJ23: =$F23 -> 0.095 | AK23: =$F23 -> 0.095 | AL23: =$F23 -> 0.095 | AM23: =$F23 -> 0.095 | AN23: =$F23 -> 0.095 | AO23: =$F23 -> 0.095 | AP23: =$F23 -> 0.095 | ... AT23: =$F23 -> 0.095
C24: Обязательное социальное медицинское страхование | D24: % | E24: Tax code, RoK | F24: 0.03 | J24: =$F24 -> 0.03 | K24: =$F24 -> 0.03 | L24: =$F24 -> 0.03 | M24: =$F24 -> 0.03 | N24: =$F24 -> 0.03 | O24: =$F24 -> 0.03 | P24: =$F24 -> 0.03 | Q24: =$F24 -> 0.03 | ... AG24: =$F24 -> 0.03 | AI24: =$F24 -> 0.03 | AJ24: =$F24 -> 0.03 | AK24: =$F24 -> 0.03 | AL24: =$F24 -> 0.03 | AM24: =$F24 -> 0.03 | AN24: =$F24 -> 0.03 | AO24: =$F24 -> 0.03 | AP24: =$F24 -> 0.03 | ... AT24: =$F24 -> 0.03
C25: Взносы ОСМС работников | D25: % | E25: Tax code, RoK | F25: 0.02 | J25: =$F25 -> 0.02 | K25: =$F25 -> 0.02 | L25: =$F25 -> 0.02 | M25: =$F25 -> 0.02 | N25: =$F25 -> 0.02 | O25: =$F25 -> 0.02 | P25: =$F25 -> 0.02 | Q25: =$F25 -> 0.02 | ... AG25: =$F25 -> 0.02 | AI25: =$F25 -> 0.02 | AJ25: =$F25 -> 0.02 | AK25: =$F25 -> 0.02 | AL25: =$F25 -> 0.02 | AM25: =$F25 -> 0.02 | AN25: =$F25 -> 0.02 | AO25: =$F25 -> 0.02 | AP25: =$F25 -> 0.02 | ... AT25: =$F25 -> 0.02
C27: Пенсионные отчисления | E27: Tax code, RoK | F27: 0.1
C29: Заработная плата
C30: Коэффициент с нэт ЗП в брутто ЗП (в случае резидента РК) | F30: 1.21
A32: х | B32: Результат - ФОТ
B34: ФОТ
B36: Производственный персонал | D36: тыс. тенге | J36: =SUM(J37:J40) -> 1940.3366 | K36: =SUM(K37:K40) -> 1940.3366 | L36: =SUM(L37:L40) -> 1940.3366 | M36: =SUM(M37:M40) -> 1940.3366 | N36: =SUM(N37:N40) -> 1940.3366 | O36: =SUM(O37:O40) -> 2144.072 | P36: =SUM(P37:P40) -> 2144.072 | Q36: =SUM(Q37:Q40) -> 2144.072 | ... AG36: =SUM(AG37:AG40) -> 2358.4792 | AI36: =SUM(AI37:AI40) -> -9701.6832 | AJ36: =SUM(AJ37:AJ40) -> -25728.864 | AK36: =SUM(AK37:AK40) -> -28301.75 | AL36: =SUM(AL37:AL40) -> -30990.417 | AM36: =SUM(AM37:AM40) -> -33779.554 | AN36: =SUM(AN37:AN40) -> -36650.816 | AO36: =SUM(AO37:AO40) -> -39582.881 | AP36: =SUM(AP37:AP40) -> -42353.683 | ... AT36: =SUM(AT37:AT40) -> -52713.913
C37: Персонал | D37: тыс. тенге | J37: =J93 -> 1742.4 | K37: =K93 -> 1742.4 | L37: =L93 -> 1742.4 | M37: =M93 -> 1742.4 | N37: =N93 -> 1742.4 | O37: =O93 -> 1925.352 | P37: =P93 -> 1925.352 | Q37: =Q93 -> 1925.352 | ... AG37: =AG93 -> 2117.8872 | AI37: =AI93 -> -8712 | AJ37: =AJ93 -> -23104.224 | AK37: =AK93 -> -25414.646 | AL37: =AL93 -> -27829.038 | AM37: =AM93 -> -30333.651 | AN37: =AN93 -> -32912.012 | AO37: =AO93 -> -35544.972 | AP37: =AP93 -> -38033.121 | ... AT37: =AT93 -> -47336.488
C38: Социальные отчисления | D38: тыс. тенге | J38: =J143 -> 58.28655 | K38: =K143 -> 58.28655 | L38: =L143 -> 58.28655 | M38: =M143 -> 58.28655 | N38: =N143 -> 58.28655 | O38: =O143 -> 64.414245 | P38: =P143 -> 64.414245 | Q38: =Q143 -> 64.414245 | ... AG38: =AG143 -> 70.862915 | AI38: =-AI143 -> -281.63275 | AJ38: =-AJ143 -> -746.98134 | AK38: =-AK143 -> -821.76641 | AL38: =-AL143 -> -899.91682 | AM38: =-AM143 -> -980.98758 | AN38: =-AN143 -> -1064.4454 | AO38: =-AO143 -> -1149.6706 | AP38: =-AP143 -> -1230.2084 | ... AT38: =-AT143 -> -1531.3451
C39: Социальный налог | D39: тыс. тенге | J39: =J155 -> 87.37809 | K39: =K155 -> 87.37809 | L39: =L155 -> 87.37809 | M39: =M155 -> 87.37809 | N39: =N155 -> 87.37809 | O39: =O155 -> 96.545182 | P39: =P155 -> 96.545182 | Q39: =Q155 -> 96.545182 | ... AG39: =AG155 -> 106.19246 | AI39: =-AI155 -> -446.69045 | AJ39: =-AJ155 -> -1184.5318 | AK39: =-AK155 -> -1302.898 | AL39: =-AL155 -> -1426.5907 | AM39: =-AM155 -> -1554.9057 | AN39: =-AN155 -> -1686.9987 | AO39: =-AO155 -> -1821.8891 | AP39: =-AP155 -> -1949.3605 | ... AT39: =-AT155 -> -2425.9853
C40: ОСМС | D40: тыс. тенге | J40: =J167 -> 52.272 | K40: =K167 -> 52.272 | L40: =L167 -> 52.272 | M40: =M167 -> 52.272 | N40: =N167 -> 52.272 | O40: =O167 -> 57.76056 | P40: =P167 -> 57.76056 | Q40: =Q167 -> 57.76056 | ... AG40: =AG167 -> 63.536616 | AI40: =-AI167 -> -261.36 | AJ40: =-AJ167 -> -693.12672 | AK40: =-AK167 -> -762.43939 | AL40: =-AL167 -> -834.87113 | AM40: =-AM167 -> -910.00954 | AN40: =-AN167 -> -987.36035 | AO40: =-AO167 -> -1066.3492 | AP40: =-AP167 -> -1140.9936 | ... AT40: =-AT167 -> -1420.0946
A43: х | B43: Штатное расписание
B45: Производственный персонал
B46: 1 | C46: Директор фермы | D46: ед. | E46: резидент РК | J46: 1 | K46: =J46 -> 1 | L46: =K46 -> 1 | M46: =L46 -> 1 | N46: =M46 -> 1 | O46: =N46 -> 1 | P46: =O46 -> 1 | Q46: =P46 -> 1 | R46: =Q46 -> 1 | ... AG46: =AF46 -> 1 | AI46: =J46 -> 1 | AJ46: =AI46 -> 1 | AK46: =AJ46 -> 1 | AL46: =AK46 -> 1 | AM46: =AL46 -> 1 | AN46: =AM46 -> 1 | AO46: =AN46 -> 1 | AP46: =AO46 -> 1 | AQ46: =AP46 -> 1 | ... AT46: =AS46 -> 1
B47: 2 | C47: Ветеринар | D47: ед. | E47: резидент РК | J47: 0.5 | K47: =J47 -> 0.5 | L47: =K47 -> 0.5 | M47: =L47 -> 0.5 | N47: =M47 -> 0.5 | O47: =N47 -> 0.5 | P47: =O47 -> 0.5 | Q47: =P47 -> 0.5 | R47: =Q47 -> 0.5 | ... AG47: =AF47 -> 0.5 | AI47: =J47 -> 0.5 | AJ47: =AI47 -> 0.5 | AK47: =AJ47 -> 0.5 | AL47: =AK47 -> 0.5 | AM47: =AL47 -> 0.5 | AN47: =AM47 -> 0.5 | AO47: =AN47 -> 0.5 | AP47: =AO47 -> 0.5 | AQ47: =AP47 -> 0.5 | ... AT47: =AS47 -> 0.5
B48: 3 | C48: Повар | D48: ед. | E48: резидент РК | J48: 0.5 | K48: =J48 -> 0.5 | L48: =K48 -> 0.5 | M48: =L48 -> 0.5 | N48: =M48 -> 0.5 | O48: =N48 -> 0.5 | P48: =O48 -> 0.5 | Q48: =P48 -> 0.5 | R48: =Q48 -> 0.5 | ... AG48: =AF48 -> 0.5 | AI48: =J48 -> 0.5 | AJ48: =AI48 -> 0.5 | AK48: =AJ48 -> 0.5 | AL48: =AK48 -> 0.5 | AM48: =AL48 -> 0.5 | AN48: =AM48 -> 0.5 | AO48: =AN48 -> 0.5 | AP48: =AO48 -> 0.5 | AQ48: =AP48 -> 0.5 | ... AT48: =AS48 -> 0.5
B49: 4 | C49: Тракторист | D49: ед. | E49: резидент РК | J49: 1 | K49: =J49 -> 1 | L49: =K49 -> 1 | M49: =L49 -> 1 | N49: =M49 -> 1 | O49: =N49 -> 1 | P49: =O49 -> 1 | Q49: =P49 -> 1 | R49: =Q49 -> 1 | ... AG49: =AF49 -> 1 | AI49: =J49 -> 1 | AJ49: =AI49 -> 1 | AK49: =AJ49 -> 1 | AL49: =AK49 -> 1 | AM49: =AL49 -> 1 | AN49: =AM49 -> 1 | AO49: =AN49 -> 1 | AP49: =AO49 -> 1 | AQ49: =AP49 -> 1 | ... AT49: =AS49 -> 1
B50: 5 | C50: Бухглатер | D50: ед. | E50: резидент РК | J50: 0.3 | K50: =J50 -> 0.3 | L50: =K50 -> 0.3 | M50: =L50 -> 0.3 | N50: =M50 -> 0.3 | O50: =N50 -> 0.3 | P50: =O50 -> 0.3 | Q50: =P50 -> 0.3 | R50: =Q50 -> 0.3 | ... AG50: =AF50 -> 0.3 | AI50: =J50 -> 0.3 | AJ50: =AI50 -> 0.3 | AK50: =AJ50 -> 0.3 | AL50: =AK50 -> 0.3 | AM50: =AL50 -> 0.3 | AN50: =AM50 -> 0.3 | AO50: =AN50 -> 0.3 | AP50: =AO50 -> 0.3 | AQ50: =AP50 -> 0.3 | ... AT50: =AS50 -> 0.3
C51: Итого | D51: ед. | J51: =SUM(J46:J50) -> 3.3 | K51: =SUM(K46:K50) -> 3.3 | L51: =SUM(L46:L50) -> 3.3 | M51: =SUM(M46:M50) -> 3.3 | N51: =SUM(N46:N50) -> 3.3 | O51: =SUM(O46:O50) -> 3.3 | P51: =SUM(P46:P50) -> 3.3 | Q51: =SUM(Q46:Q50) -> 3.3 | ... AG51: =SUM(AG46:AG50) -> 3.3 | AI51: =SUM(AI46:AI50) -> 3.3 | AJ51: =SUM(AJ46:AJ50) -> 3.3 | AK51: =SUM(AK46:AK50) -> 3.3 | AL51: =SUM(AL46:AL50) -> 3.3 | AM51: =SUM(AM46:AM50) -> 3.3 | AN51: =SUM(AN46:AN50) -> 3.3 | AO51: =SUM(AO46:AO50) -> 3.3 | AP51: =SUM(AP46:AP50) -> 3.3 | ... AT51: =SUM(AT46:AT50) -> 3.3
C53: Итого | D53: ед. | J53: =J51 -> 3.3 | K53: =K51 -> 3.3 | L53: =L51 -> 3.3 | M53: =M51 -> 3.3 | N53: =N51 -> 3.3 | O53: =O51 -> 3.3 | P53: =P51 -> 3.3 | Q53: =Q51 -> 3.3 | ... AT53: =AT51 -> 3.3
A55: х | B55: Заработная плата
B57: Заработная плата (нетто)
B59: Производственный персонал
B60: 1 | C60: =C46 -> Директор фермы | D60: тыс. тенге / мес. | E60: прогноз | F60: 600 | J60: =F60 -> 600 | K60: =J60*(1+K$6) -> 600 | L60: =K60*(1+L$6) -> 600 | M60: =L60*(1+M$6) -> 600 | N60: =M60*(1+N$6) -> 600 | O60: =N60*(1+O$6) -> 663 | P60: =O60*(1+P$6) -> 663 | Q60: =P60*(1+Q$6) -> 663 | R60: =Q60*(1+R$6) -> 663 | ... AG60: =AF60*(1+AG$6) -> 729.3 | AI60: =J60 -> 600 | AJ60: =AI60*(1+AJ$6) -> 663 | AK60: =AJ60*(1+AK$6) -> 729.3 | AL60: =AK60*(1+AL$6) -> 798.5835 | AM60: =AL60*(1+AM$6) -> 870.45602 | AN60: =AM60*(1+AN$6) -> 944.44478 | AO60: =AN60*(1+AO$6) -> 1020.0004 | AP60: =AO60*(1+AP$6) -> 1091.4004 | AQ60: =AP60*(1+AQ$6) -> 1162.3414 | ... AT60: =AS60*(1+AT$6) -> 1358.3703
B61: 2 | C61: =C47 -> Ветеринар | D61: тыс. тенге / мес. | E61: прогноз | F61: 400 | J61: =F61 -> 400 | K61: =J61*(1+K$6) -> 400 | L61: =K61*(1+L$6) -> 400 | M61: =L61*(1+M$6) -> 400 | N61: =M61*(1+N$6) -> 400 | O61: =N61*(1+O$6) -> 442 | P61: =O61*(1+P$6) -> 442 | Q61: =P61*(1+Q$6) -> 442 | R61: =Q61*(1+R$6) -> 442 | ... AG61: =AF61*(1+AG$6) -> 486.2 | AI61: =J61 -> 400 | AJ61: =AI61*(1+AJ$6) -> 442 | AK61: =AJ61*(1+AK$6) -> 486.2 | AL61: =AK61*(1+AL$6) -> 532.389 | AM61: =AL61*(1+AM$6) -> 580.30401 | AN61: =AM61*(1+AN$6) -> 629.62985 | AO61: =AN61*(1+AO$6) -> 680.00024 | AP61: =AO61*(1+AP$6) -> 727.60026 | AQ61: =AP61*(1+AQ$6) -> 774.89427 | ... AT61: =AS61*(1+AT$6) -> 905.58019
B62: 3 | C62: =C48 -> Повар | D62: тыс. тенге / мес. | E62: прогноз | F62: 300 | J62: =F62 -> 300 | K62: =J62*(1+K$6) -> 300 | L62: =K62*(1+L$6) -> 300 | M62: =L62*(1+M$6) -> 300 | N62: =M62*(1+N$6) -> 300 | O62: =N62*(1+O$6) -> 331.5 | P62: =O62*(1+P$6) -> 331.5 | Q62: =P62*(1+Q$6) -> 331.5 | R62: =Q62*(1+R$6) -> 331.5 | ... AG62: =AF62*(1+AG$6) -> 364.65 | AI62: =J62 -> 300 | AJ62: =AI62*(1+AJ$6) -> 331.5 | AK62: =AJ62*(1+AK$6) -> 364.65 | AL62: =AK62*(1+AL$6) -> 399.29175 | AM62: =AL62*(1+AM$6) -> 435.22801 | AN62: =AM62*(1+AN$6) -> 472.22239 | AO62: =AN62*(1+AO$6) -> 510.00018 | AP62: =AO62*(1+AP$6) -> 545.70019 | AQ62: =AP62*(1+AQ$6) -> 581.1707 | ... AT62: =AS62*(1+AT$6) -> 679.18514
B63: 4 | C63: =C49 -> Тракторист | D63: тыс. тенге / мес. | E63: прогноз | F63: 400 | J63: =F63 -> 400 | K63: =J63*(1+K$6) -> 400 | L63: =K63*(1+L$6) -> 400 | M63: =L63*(1+M$6) -> 400 | N63: =M63*(1+N$6) -> 400 | O63: =N63*(1+O$6) -> 442 | P63: =O63*(1+P$6) -> 442 | Q63: =P63*(1+Q$6) -> 442 | R63: =Q63*(1+R$6) -> 442 | ... AG63: =AF63*(1+AG$6) -> 486.2 | AI63: =J63 -> 400 | AJ63: =AI63*(1+AJ$6) -> 442 | AK63: =AJ63*(1+AK$6) -> 486.2 | AL63: =AK63*(1+AL$6) -> 532.389 | AM63: =AL63*(1+AM$6) -> 580.30401 | AN63: =AM63*(1+AN$6) -> 629.62985 | AO63: =AN63*(1+AO$6) -> 680.00024 | AP63: =AO63*(1+AP$6) -> 727.60026 | AQ63: =AP63*(1+AQ$6) -> 774.89427 | ... AT63: =AS63*(1+AT$6) -> 905.58019
B64: 5 | C64: =C50 -> Бухглатер | D64: тыс. тенге / мес. | E64: прогноз | F64: 300 | J64: =F64 -> 300 | K64: =J64*(1+K$6) -> 300 | L64: =K64*(1+L$6) -> 300 | M64: =L64*(1+M$6) -> 300 | N64: =M64*(1+N$6) -> 300 | O64: =N64*(1+O$6) -> 331.5 | P64: =O64*(1+P$6) -> 331.5 | Q64: =P64*(1+Q$6) -> 331.5 | R64: =Q64*(1+R$6) -> 331.5 | ... AG64: =AF64*(1+AG$6) -> 364.65 | AI64: =J64 -> 300 | AJ64: =AI64*(1+AJ$6) -> 331.5 | AK64: =AJ64*(1+AK$6) -> 364.65 | AL64: =AK64*(1+AL$6) -> 399.29175 | AM64: =AL64*(1+AM$6) -> 435.22801 | AN64: =AM64*(1+AN$6) -> 472.22239 | AO64: =AN64*(1+AO$6) -> 510.00018 | AP64: =AO64*(1+AP$6) -> 545.70019 | AQ64: =AP64*(1+AQ$6) -> 581.1707 | ... AT64: =AS64*(1+AT$6) -> 679.18514
A67: х | B67: Расчет ЗП до вычета налогов и социальных отчислений
B69: Производственный персонал
B70: 1 | C70: =C60 -> Директор фермы | D70: тыс. тенге | E70: резидент РК | J70: =J46*J60 -> 600 | K70: =K46*K60 -> 600 | L70: =L46*L60 -> 600 | M70: =M46*M60 -> 600 | N70: =N46*N60 -> 600 | O70: =O46*O60 -> 663 | P70: =P46*P60 -> 663 | Q70: =Q46*Q60 -> 663 | ... AG70: =AG46*AG60 -> 729.3 | AI70: =-SUMIF($J$12:$AG$12,AI$12,$J70:$AG70) -> -3000 | AJ70: =-SUMIF($J$12:$AG$12,AJ$12,$J70:$AG70) -> -7956 | AK70: =-AK46*AK60*AK$10 -> -8751.6 | AL70: =-AL46*AL60*AL$10 -> -9583.002 | AM70: =-AM46*AM60*AM$10 -> -10445.472 | AN70: =-AN46*AN60*AN$10 -> -11333.337 | AO70: =-AO46*AO60*AO$10 -> -12240.004 | AP70: =-AP46*AP60*AP$10 -> -13096.805 | AQ70: =-AQ46*AQ60*AQ$10 -> -13948.097 | AR70: =-AR46*AR60*AR$10 -> -14784.983 | ... AT70: =-AT46*AT60*AT$10 -> -16300.443
B71: 2 | C71: =C61 -> Ветеринар | D71: тыс. тенге | E71: резидент РК | J71: =J47*J61 -> 200 | K71: =K47*K61 -> 200 | L71: =L47*L61 -> 200 | M71: =M47*M61 -> 200 | N71: =N47*N61 -> 200 | O71: =O47*O61 -> 221 | P71: =P47*P61 -> 221 | Q71: =Q47*Q61 -> 221 | ... AG71: =AG47*AG61 -> 243.1 | AI71: =-SUMIF($J$12:$AG$12,AI$12,$J71:$AG71) -> -1000 | AJ71: =-SUMIF($J$12:$AG$12,AJ$12,$J71:$AG71) -> -2652 | AK71: =-AK47*AK61*AK$10 -> -2917.2 | AL71: =-AL47*AL61*AL$10 -> -3194.334 | AM71: =-AM47*AM61*AM$10 -> -3481.8241 | AN71: =-AN47*AN61*AN$10 -> -3777.7791 | AO71: =-AO47*AO61*AO$10 -> -4080.0014 | AP71: =-AP47*AP61*AP$10 -> -4365.6015 | AQ71: =-AQ47*AQ61*AQ$10 -> -4649.3656 | AR71: =-AR47*AR61*AR$10 -> -4928.3276 | ... AT71: =-AT47*AT61*AT$10 -> -5433.4811
B72: 3 | C72: =C62 -> Повар | D72: тыс. тенге | E72: резидент РК | J72: =J48*J62 -> 150 | K72: =K48*K62 -> 150 | L72: =L48*L62 -> 150 | M72: =M48*M62 -> 150 | N72: =N48*N62 -> 150 | O72: =O48*O62 -> 165.75 | P72: =P48*P62 -> 165.75 | Q72: =Q48*Q62 -> 165.75 | ... AG72: =AG48*AG62 -> 182.325 | AI72: =-SUMIF($J$12:$AG$12,AI$12,$J72:$AG72) -> -750 | AJ72: =-SUMIF($J$12:$AG$12,AJ$12,$J72:$AG72) -> -1989 | AK72: =-AK48*AK62*AK$10 -> -2187.9 | AL72: =-AL48*AL62*AL$10 -> -2395.7505 | AM72: =-AM48*AM62*AM$10 -> -2611.368 | AN72: =-AN48*AN62*AN$10 -> -2833.3343 | AO72: =-AO48*AO62*AO$10 -> -3060.0011 | AP72: =-AP48*AP62*AP$10 -> -3274.2012 | AQ72: =-AQ48*AQ62*AQ$10 -> -3487.0242 | AR72: =-AR48*AR62*AR$10 -> -3696.2457 | ... AT72: =-AT48*AT62*AT$10 -> -4075.1109
B73: 4 | C73: =C63 -> Тракторист | D73: тыс. тенге | E73: резидент РК | J73: =J49*J63 -> 400 | K73: =K49*K63 -> 400 | L73: =L49*L63 -> 400 | M73: =M49*M63 -> 400 | N73: =N49*N63 -> 400 | O73: =O49*O63 -> 442 | P73: =P49*P63 -> 442 | Q73: =Q49*Q63 -> 442 | ... AG73: =AG49*AG63 -> 486.2 | AI73: =-SUMIF($J$12:$AG$12,AI$12,$J73:$AG73) -> -2000 | AJ73: =-SUMIF($J$12:$AG$12,AJ$12,$J73:$AG73) -> -5304 | AK73: =-AK49*AK63*AK$10 -> -5834.4 | AL73: =-AL49*AL63*AL$10 -> -6388.668 | AM73: =-AM49*AM63*AM$10 -> -6963.6481 | AN73: =-AN49*AN63*AN$10 -> -7555.5582 | AO73: =-AO49*AO63*AO$10 -> -8160.0029 | AP73: =-AP49*AP63*AP$10 -> -8731.2031 | AQ73: =-AQ49*AQ63*AQ$10 -> -9298.7313 | AR73: =-AR49*AR63*AR$10 -> -9856.6551 | ... AT73: =-AT49*AT63*AT$10 -> -10866.962
B74: 5 | C74: =C64 -> Бухглатер | D74: тыс. тенге | E74: резидент РК | J74: =J50*J64 -> 90 | K74: =K50*K64 -> 90 | L74: =L50*L64 -> 90 | M74: =M50*M64 -> 90 | N74: =N50*N64 -> 90 | O74: =O50*O64 -> 99.45 | P74: =P50*P64 -> 99.45 | Q74: =Q50*Q64 -> 99.45 | ... AG74: =AG50*AG64 -> 109.395 | AI74: =-SUMIF($J$12:$AG$12,AI$12,$J74:$AG74) -> -450 | AJ74: =-SUMIF($J$12:$AG$12,AJ$12,$J74:$AG74) -> -1193.4 | AK74: =-AK50*AK64*AK$10 -> -1312.74 | AL74: =-AL50*AL64*AL$10 -> -1437.4503 | AM74: =-AM50*AM64*AM$10 -> -1566.8208 | AN74: =-AN50*AN64*AN$10 -> -1700.0006 | AO74: =-AO50*AO64*AO$10 -> -1836.0006 | AP74: =-AP50*AP64*AP$10 -> -1964.5207 | AQ74: =-AQ50*AQ64*AQ$10 -> -2092.2145 | AR74: =-AR50*AR64*AR$10 -> -2217.7474 | ... AT74: =-AT50*AT64*AT$10 -> -2445.0665
C75: Итого | D75: тыс. тенге | J75: =SUM(J70:J74) -> 1440 | K75: =SUM(K70:K74) -> 1440 | L75: =SUM(L70:L74) -> 1440 | M75: =SUM(M70:M74) -> 1440 | N75: =SUM(N70:N74) -> 1440 | O75: =SUM(O70:O74) -> 1591.2 | P75: =SUM(P70:P74) -> 1591.2 | Q75: =SUM(Q70:Q74) -> 1591.2 | ... AG75: =SUM(AG70:AG74) -> 1750.32 | AI75: =SUM(AI70:AI74) -> -7200 | AJ75: =SUM(AJ70:AJ74) -> -19094.4 | AK75: =SUM(AK70:AK74) -> -21003.84 | AL75: =SUM(AL70:AL74) -> -22999.205 | AM75: =SUM(AM70:AM74) -> -25069.133 | AN75: =SUM(AN70:AN74) -> -27200.01 | AO75: =SUM(AO70:AO74) -> -29376.01 | AP75: =SUM(AP70:AP74) -> -31432.331 | ... AT75: =SUM(AT70:AT74) -> -39121.064
C77: Итого | D77: тыс. тенге | J77: =J75 -> 1440 | K77: =K75 -> 1440 | L77: =L75 -> 1440 | M77: =M75 -> 1440 | N77: =N75 -> 1440 | O77: =O75 -> 1591.2 | P77: =P75 -> 1591.2 | Q77: =Q75 -> 1591.2 | ... AT77: =AT75 -> -39121.064
B79: Итого ЗП
B80: 1 | C80: Производственный персонал | D80: тыс. тенге | E80: резидент РК | J80: =-J75 -> -1440 | K80: =-K75 -> -1440 | L80: =-L75 -> -1440 | M80: =-M75 -> -1440 | N80: =-N75 -> -1440 | O80: =-O75 -> -1591.2 | P80: =-P75 -> -1591.2 | Q80: =-Q75 -> -1591.2 | ... AG80: =-AG75 -> -1750.32 | AI80: =AI75 -> -7200 | AJ80: =AJ75 -> -19094.4 | AK80: =AK75 -> -21003.84 | AL80: =AL75 -> -22999.205 | AM80: =AM75 -> -25069.133 | AN80: =AN75 -> -27200.01 | AO80: =AO75 -> -29376.01 | AP80: =AP75 -> -31432.331 | ... AT80: =AT75 -> -39121.064
C81: Итого | D81: тыс. тенге | J81: =SUM(J80:J80) -> -1440 | K81: =SUM(K80:K80) -> -1440 | L81: =SUM(L80:L80) -> -1440 | M81: =SUM(M80:M80) -> -1440 | N81: =SUM(N80:N80) -> -1440 | O81: =SUM(O80:O80) -> -1591.2 | P81: =SUM(P80:P80) -> -1591.2 | Q81: =SUM(Q80:Q80) -> -1591.2 | ... AG81: =SUM(AG80:AG80) -> -1750.32 | AI81: =SUM(AI80:AI80) -> -7200 | AJ81: =SUM(AJ80:AJ80) -> -19094.4 | AK81: =SUM(AK80:AK80) -> -21003.84 | AL81: =SUM(AL80:AL80) -> -22999.205 | AM81: =SUM(AM80:AM80) -> -25069.133 | AN81: =SUM(AN80:AN80) -> -27200.01 | AO81: =SUM(AO80:AO80) -> -29376.01 | AP81: =SUM(AP80:AP80) -> -31432.331 | ... AT81: =SUM(AT80:AT80) -> -39121.064
B85: Заработная плата (брутто)
B87: Производственный персонал
B88: 1 | C88: =C70 -> Директор фермы | D88: тыс. тенге | E88: резидент РК | J88: =J70*$F$30 -> 726 | K88: =K70*$F$30 -> 726 | L88: =L70*$F$30 -> 726 | M88: =M70*$F$30 -> 726 | N88: =N70*$F$30 -> 726 | O88: =O70*$F$30 -> 802.23 | P88: =P70*$F$30 -> 802.23 | Q88: =Q70*$F$30 -> 802.23 | ... AG88: =AG70*$F$30 -> 882.453 | AI88: =-SUMIF($J$12:$AG$12,AI$12,$J88:$AG88) -> -3630 | AJ88: =-SUMIF($J$12:$AG$12,AJ$12,$J88:$AG88) -> -9626.76 | AK88: =AK70*$F$30 -> -10589.436 | AL88: =AL70*$F$30 -> -11595.432 | AM88: =AM70*$F$30 -> -12639.021 | AN88: =AN70*$F$30 -> -13713.338 | AO88: =AO70*$F$30 -> -14810.405 | AP88: =AP70*$F$30 -> -15847.134 | AQ88: =AQ70*$F$30 -> -16877.197 | AR88: =AR70*$F$30 -> -17889.829 | ... AT88: =AT70*$F$30 -> -19723.537
B89: 2 | C89: =C71 -> Ветеринар | D89: тыс. тенге | E89: резидент РК | J89: =J71*$F$30 -> 242 | K89: =K71*$F$30 -> 242 | L89: =L71*$F$30 -> 242 | M89: =M71*$F$30 -> 242 | N89: =N71*$F$30 -> 242 | O89: =O71*$F$30 -> 267.41 | P89: =P71*$F$30 -> 267.41 | Q89: =Q71*$F$30 -> 267.41 | ... AG89: =AG71*$F$30 -> 294.151 | AI89: =-SUMIF($J$12:$AG$12,AI$12,$J89:$AG89) -> -1210 | AJ89: =-SUMIF($J$12:$AG$12,AJ$12,$J89:$AG89) -> -3208.92 | AK89: =AK71*$F$30 -> -3529.812 | AL89: =AL71*$F$30 -> -3865.1441 | AM89: =AM71*$F$30 -> -4213.0071 | AN89: =AN71*$F$30 -> -4571.1127 | AO89: =AO71*$F$30 -> -4936.8017 | AP89: =AP71*$F$30 -> -5282.3779 | AQ89: =AQ71*$F$30 -> -5625.7324 | AR89: =AR71*$F$30 -> -5963.2764 | ... AT89: =AT71*$F$30 -> -6574.5122
B90: 3 | C90: =C72 -> Повар | D90: тыс. тенге | E90: резидент РК | J90: =J72*$F$30 -> 181.5 | K90: =K72*$F$30 -> 181.5 | L90: =L72*$F$30 -> 181.5 | M90: =M72*$F$30 -> 181.5 | N90: =N72*$F$30 -> 181.5 | O90: =O72*$F$30 -> 200.5575 | P90: =P72*$F$30 -> 200.5575 | Q90: =Q72*$F$30 -> 200.5575 | ... AG90: =AG72*$F$30 -> 220.61325 | AI90: =-SUMIF($J$12:$AG$12,AI$12,$J90:$AG90) -> -907.5 | AJ90: =-SUMIF($J$12:$AG$12,AJ$12,$J90:$AG90) -> -2406.69 | AK90: =AK72*$F$30 -> -2647.359 | AL90: =AL72*$F$30 -> -2898.8581 | AM90: =AM72*$F$30 -> -3159.7553 | AN90: =AN72*$F$30 -> -3428.3345 | AO90: =AO72*$F$30 -> -3702.6013 | AP90: =AP72*$F$30 -> -3961.7834 | AQ90: =AQ72*$F$30 -> -4219.2993 | AR90: =AR72*$F$30 -> -4472.4573 | ... AT90: =AT72*$F$30 -> -4930.8841
B91: 4 | C91: =C73 -> Тракторист | D91: тыс. тенге | E91: резидент РК | J91: =J73*$F$30 -> 484 | K91: =K73*$F$30 -> 484 | L91: =L73*$F$30 -> 484 | M91: =M73*$F$30 -> 484 | N91: =N73*$F$30 -> 484 | O91: =O73*$F$30 -> 534.82 | P91: =P73*$F$30 -> 534.82 | Q91: =Q73*$F$30 -> 534.82 | ... AG91: =AG73*$F$30 -> 588.302 | AI91: =-SUMIF($J$12:$AG$12,AI$12,$J91:$AG91) -> -2420 | AJ91: =-SUMIF($J$12:$AG$12,AJ$12,$J91:$AG91) -> -6417.84 | AK91: =AK73*$F$30 -> -7059.624 | AL91: =AL73*$F$30 -> -7730.2883 | AM91: =AM73*$F$30 -> -8426.0142 | AN91: =AN73*$F$30 -> -9142.2254 | AO91: =AO73*$F$30 -> -9873.6035 | AP91: =AP73*$F$30 -> -10564.756 | AQ91: =AQ73*$F$30 -> -11251.465 | AR91: =AR73*$F$30 -> -11926.553 | ... AT91: =AT73*$F$30 -> -13149.024
B92: 5 | C92: =C74 -> Бухглатер | D92: тыс. тенге | E92: резидент РК | J92: =J74*$F$30 -> 108.9 | K92: =K74*$F$30 -> 108.9 | L92: =L74*$F$30 -> 108.9 | M92: =M74*$F$30 -> 108.9 | N92: =N74*$F$30 -> 108.9 | O92: =O74*$F$30 -> 120.3345 | P92: =P74*$F$30 -> 120.3345 | Q92: =Q74*$F$30 -> 120.3345 | ... AG92: =AG74*$F$30 -> 132.36795 | AI92: =-SUMIF($J$12:$AG$12,AI$12,$J92:$AG92) -> -544.5 | AJ92: =-SUMIF($J$12:$AG$12,AJ$12,$J92:$AG92) -> -1444.014 | AK92: =AK74*$F$30 -> -1588.4154 | AL92: =AL74*$F$30 -> -1739.3149 | AM92: =AM74*$F$30 -> -1895.8532 | AN92: =AN74*$F$30 -> -2057.0007 | AO92: =AO74*$F$30 -> -2221.5608 | AP92: =AP74*$F$30 -> -2377.07 | AQ92: =AQ74*$F$30 -> -2531.5796 | AR92: =AR74*$F$30 -> -2683.4744 | ... AT92: =AT74*$F$30 -> -2958.5305
C93: Итого | D93: тыс. тенге | J93: =SUM(J88:J92) -> 1742.4 | K93: =SUM(K88:K92) -> 1742.4 | L93: =SUM(L88:L92) -> 1742.4 | M93: =SUM(M88:M92) -> 1742.4 | N93: =SUM(N88:N92) -> 1742.4 | O93: =SUM(O88:O92) -> 1925.352 | P93: =SUM(P88:P92) -> 1925.352 | Q93: =SUM(Q88:Q92) -> 1925.352 | ... AG93: =SUM(AG88:AG92) -> 2117.8872 | AI93: =SUM(AI88:AI92) -> -8712 | AJ93: =SUM(AJ88:AJ92) -> -23104.224 | AK93: =SUM(AK88:AK92) -> -25414.646 | AL93: =SUM(AL88:AL92) -> -27829.038 | AM93: =SUM(AM88:AM92) -> -30333.651 | AN93: =SUM(AN88:AN92) -> -32912.012 | AO93: =SUM(AO88:AO92) -> -35544.972 | AP93: =SUM(AP88:AP92) -> -38033.121 | ... AT93: =SUM(AT88:AT92) -> -47336.488
C95: Итого | D95: тыс. тенге | J95: =J93 -> 1742.4 | K95: =K93 -> 1742.4 | L95: =L93 -> 1742.4 | M95: =M93 -> 1742.4 | N95: =N93 -> 1742.4 | O95: =O93 -> 1925.352 | P95: =P93 -> 1925.352 | Q95: =Q93 -> 1925.352 | ... AT95: =AT93 -> -47336.488
B97: Итого ЗП (резиндентов РК)
B98: 1 | C98: Производственный персонал | D98: тыс. тенге | E98: резидент РК | J98: =-J93 -> -1742.4 | K98: =-K93 -> -1742.4 | L98: =-L93 -> -1742.4 | M98: =-M93 -> -1742.4 | N98: =-N93 -> -1742.4 | O98: =-O93 -> -1925.352 | P98: =-P93 -> -1925.352 | Q98: =-Q93 -> -1925.352 | ... AG98: =-AG93 -> -2117.8872 | AI98: =AI93 -> -8712 | AJ98: =AJ93 -> -23104.224 | AK98: =AK93 -> -25414.646 | AL98: =AL93 -> -27829.038 | AM98: =AM93 -> -30333.651 | AN98: =AN93 -> -32912.012 | AO98: =AO93 -> -35544.972 | AP98: =AP93 -> -38033.121 | ... AT98: =AT93 -> -47336.488
C99: Итого | D99: тыс. тенге | J99: =SUM(J98:J98) -> -1742.4 | K99: =SUM(K98:K98) -> -1742.4 | L99: =SUM(L98:L98) -> -1742.4 | M99: =SUM(M98:M98) -> -1742.4 | N99: =SUM(N98:N98) -> -1742.4 | O99: =SUM(O98:O98) -> -1925.352 | P99: =SUM(P98:P98) -> -1925.352 | Q99: =SUM(Q98:Q98) -> -1925.352 | ... AG99: =SUM(AG98:AG98) -> -2117.8872 | AI99: =SUM(AI98:AI98) -> -8712 | AJ99: =SUM(AJ98:AJ98) -> -23104.224 | AK99: =SUM(AK98:AK98) -> -25414.646 | AL99: =SUM(AL98:AL98) -> -27829.038 | AM99: =SUM(AM98:AM98) -> -30333.651 | AN99: =SUM(AN98:AN98) -> -32912.012 | AO99: =SUM(AO98:AO98) -> -35544.972 | AP99: =SUM(AP98:AP98) -> -38033.121 | ... AT99: =SUM(AT98:AT98) -> -47336.488
A101: x | B101: Взносы (удельники)
B103: Социальные отчисления (удельники)
B105: Производственный персонал
B106: 1 | C106: =C88 -> Директор фермы | D106: тыс. тенге / мес. | J106: =MIN(J60*$F$30-(1-$F$27),J$18)*J$22 -> 22.785 | K106: =MIN(K60*$F$30-(1-$F$27),K$18)*K$22 -> 22.785 | L106: =MIN(L60*$F$30-(1-$F$27),L$18)*L$22 -> 22.785 | M106: =MIN(M60*$F$30-(1-$F$27),M$18)*M$22 -> 22.785 | N106: =MIN(N60*$F$30-(1-$F$27),N$18)*N$22 -> 22.785 | O106: =MIN(O60*$F$30-(1-$F$27),O$18)*O$22 -> 25.177425 | P106: =MIN(P60*$F$30-(1-$F$27),P$18)*P$22 -> 25.177425 | Q106: =MIN(Q60*$F$30-(1-$F$27),Q$18)*Q$22 -> 25.177425 | ... AG106: =MIN(AG60*$F$30-(1-$F$27),AG$18)*AG$22 -> 27.695168 | AI106: =MIN(AI60*$F$30-(1-$F$27),AI$18)*AI$22 -> 20.825 | AJ106: =MIN(AJ60*$F$30-(1-$F$27),AJ$18)*AJ$22 -> 23.011625 | AK106: =MIN(AK60*$F$30-(1-$F$27),AK$18)*AK$22 -> 25.312788 | AL106: =MIN(AL60*$F$30-(1-$F$27),AL$18)*AL$22 -> 27.717502 | AM106: =MIN(AM60*$F$30-(1-$F$27),AM$18)*AM$22 -> 30.212078 | AN106: =MIN(AN60*$F$30-(1-$F$27),AN$18)*AN$22 -> 32.780104 | AO106: =MIN(AO60*$F$30-(1-$F$27),AO$18)*AO$22 -> 35.402512 | AP106: =MIN(AP60*$F$30-(1-$F$27),AP$18)*AP$22 -> 37.880688 | ... AT106: =MIN(AT60*$F$30-(1-$F$27),AT$18)*AT$22 -> 47.146769
B107: 2 | C107: =C89 -> Ветеринар | D107: тыс. тенге / мес. | J107: =MIN(J61*$F$30-(1-$F$27),J$18)*J$22 -> 16.9085 | K107: =MIN(K61*$F$30-(1-$F$27),K$18)*K$22 -> 16.9085 | L107: =MIN(L61*$F$30-(1-$F$27),L$18)*L$22 -> 16.9085 | M107: =MIN(M61*$F$30-(1-$F$27),M$18)*M$22 -> 16.9085 | N107: =MIN(N61*$F$30-(1-$F$27),N$18)*N$22 -> 16.9085 | O107: =MIN(O61*$F$30-(1-$F$27),O$18)*O$22 -> 18.6872 | P107: =MIN(P61*$F$30-(1-$F$27),P$18)*P$22 -> 18.6872 | Q107: =MIN(Q61*$F$30-(1-$F$27),Q$18)*Q$22 -> 18.6872 | ... AG107: =MIN(AG61*$F$30-(1-$F$27),AG$18)*AG$22 -> 20.55907 | AI107: =MIN(AI61*$F$30-(1-$F$27),AI$18)*AI$22 -> 16.9085 | AJ107: =MIN(AJ61*$F$30-(1-$F$27),AJ$18)*AJ$22 -> 18.6872 | AK107: =MIN(AK61*$F$30-(1-$F$27),AK$18)*AK$22 -> 20.55907 | AL107: =MIN(AL61*$F$30-(1-$F$27),AL$18)*AL$22 -> 22.515174 | AM107: =MIN(AM61*$F$30-(1-$F$27),AM$18)*AM$22 -> 24.544375 | AN107: =MIN(AN61*$F$30-(1-$F$27),AN$18)*AN$22 -> 26.633324 | AO107: =MIN(AO61*$F$30-(1-$F$27),AO$18)*AO$22 -> 28.76651 | AP107: =MIN(AP61*$F$30-(1-$F$27),AP$18)*AP$22 -> 30.782371 | ... AT107: =MIN(AT61*$F$30-(1-$F$27),AT$18)*AT$22 -> 38.319821
B108: 3 | C108: =C90 -> Повар | D108: тыс. тенге / мес. | J108: =MIN(J62*$F$30-(1-$F$27),J$18)*J$22 -> 12.6735 | K108: =MIN(K62*$F$30-(1-$F$27),K$18)*K$22 -> 12.6735 | L108: =MIN(L62*$F$30-(1-$F$27),L$18)*L$22 -> 12.6735 | M108: =MIN(M62*$F$30-(1-$F$27),M$18)*M$22 -> 12.6735 | N108: =MIN(N62*$F$30-(1-$F$27),N$18)*N$22 -> 12.6735 | O108: =MIN(O62*$F$30-(1-$F$27),O$18)*O$22 -> 14.007525 | P108: =MIN(P62*$F$30-(1-$F$27),P$18)*P$22 -> 14.007525 | Q108: =MIN(Q62*$F$30-(1-$F$27),Q$18)*Q$22 -> 14.007525 | ... AG108: =MIN(AG62*$F$30-(1-$F$27),AG$18)*AG$22 -> 15.411428 | AI108: =MIN(AI62*$F$30-(1-$F$27),AI$18)*AI$22 -> 12.6735 | AJ108: =MIN(AJ62*$F$30-(1-$F$27),AJ$18)*AJ$22 -> 14.007525 | AK108: =MIN(AK62*$F$30-(1-$F$27),AK$18)*AK$22 -> 15.411428 | AL108: =MIN(AL62*$F$30-(1-$F$27),AL$18)*AL$22 -> 16.878506 | AM108: =MIN(AM62*$F$30-(1-$F$27),AM$18)*AM$22 -> 18.400406 | AN108: =MIN(AN62*$F$30-(1-$F$27),AN$18)*AN$22 -> 19.967118 | AO108: =MIN(AO62*$F$30-(1-$F$27),AO$18)*AO$22 -> 21.567008 | AP108: =MIN(AP62*$F$30-(1-$F$27),AP$18)*AP$22 -> 23.078903 | ... AT108: =MIN(AT62*$F$30-(1-$F$27),AT$18)*AT$22 -> 28.731991
B109: 4 | C109: =C91 -> Тракторист | D109: тыс. тенге / мес. | J109: =MIN(J63*$F$30-(1-$F$27),J$18)*J$22 -> 16.9085 | K109: =MIN(K63*$F$30-(1-$F$27),K$18)*K$22 -> 16.9085 | L109: =MIN(L63*$F$30-(1-$F$27),L$18)*L$22 -> 16.9085 | M109: =MIN(M63*$F$30-(1-$F$27),M$18)*M$22 -> 16.9085 | N109: =MIN(N63*$F$30-(1-$F$27),N$18)*N$22 -> 16.9085 | O109: =MIN(O63*$F$30-(1-$F$27),O$18)*O$22 -> 18.6872 | P109: =MIN(P63*$F$30-(1-$F$27),P$18)*P$22 -> 18.6872 | Q109: =MIN(Q63*$F$30-(1-$F$27),Q$18)*Q$22 -> 18.6872 | ... AG109: =MIN(AG63*$F$30-(1-$F$27),AG$18)*AG$22 -> 20.55907 | AI109: =MIN(AI63*$F$30-(1-$F$27),AI$18)*AI$22 -> 16.9085 | AJ109: =MIN(AJ63*$F$30-(1-$F$27),AJ$18)*AJ$22 -> 18.6872 | AK109: =MIN(AK63*$F$30-(1-$F$27),AK$18)*AK$22 -> 20.55907 | AL109: =MIN(AL63*$F$30-(1-$F$27),AL$18)*AL$22 -> 22.515174 | AM109: =MIN(AM63*$F$30-(1-$F$27),AM$18)*AM$22 -> 24.544375 | AN109: =MIN(AN63*$F$30-(1-$F$27),AN$18)*AN$22 -> 26.633324 | AO109: =MIN(AO63*$F$30-(1-$F$27),AO$18)*AO$22 -> 28.76651 | AP109: =MIN(AP63*$F$30-(1-$F$27),AP$18)*AP$22 -> 30.782371 | ... AT109: =MIN(AT63*$F$30-(1-$F$27),AT$18)*AT$22 -> 38.319821
B110: 5 | C110: =C92 -> Бухглатер | D110: тыс. тенге / мес. | J110: =MIN(J64*$F$30-(1-$F$27),J$18)*J$22 -> 12.6735 | K110: =MIN(K64*$F$30-(1-$F$27),K$18)*K$22 -> 12.6735 | L110: =MIN(L64*$F$30-(1-$F$27),L$18)*L$22 -> 12.6735 | M110: =MIN(M64*$F$30-(1-$F$27),M$18)*M$22 -> 12.6735 | N110: =MIN(N64*$F$30-(1-$F$27),N$18)*N$22 -> 12.6735 | O110: =MIN(O64*$F$30-(1-$F$27),O$18)*O$22 -> 14.007525 | P110: =MIN(P64*$F$30-(1-$F$27),P$18)*P$22 -> 14.007525 | Q110: =MIN(Q64*$F$30-(1-$F$27),Q$18)*Q$22 -> 14.007525 | ... AG110: =MIN(AG64*$F$30-(1-$F$27),AG$18)*AG$22 -> 15.411428 | AI110: =MIN(AI64*$F$30-(1-$F$27),AI$18)*AI$22 -> 12.6735 | AJ110: =MIN(AJ64*$F$30-(1-$F$27),AJ$18)*AJ$22 -> 14.007525 | AK110: =MIN(AK64*$F$30-(1-$F$27),AK$18)*AK$22 -> 15.411428 | AL110: =MIN(AL64*$F$30-(1-$F$27),AL$18)*AL$22 -> 16.878506 | AM110: =MIN(AM64*$F$30-(1-$F$27),AM$18)*AM$22 -> 18.400406 | AN110: =MIN(AN64*$F$30-(1-$F$27),AN$18)*AN$22 -> 19.967118 | AO110: =MIN(AO64*$F$30-(1-$F$27),AO$18)*AO$22 -> 21.567008 | AP110: =MIN(AP64*$F$30-(1-$F$27),AP$18)*AP$22 -> 23.078903 | ... AT110: =MIN(AT64*$F$30-(1-$F$27),AT$18)*AT$22 -> 28.731991
B113: Социальный налог (удельники)
B115: Производственный персонал
B116: 1 | C116: =C106 -> Директор фермы | D116: тыс. тенге / мес. | J116: =(J60*$F$30*(1-$F$27-J$25))*J$23-J106 -> 37.9086 | K116: =(K60*$F$30*(1-$F$27-K$25))*K$23-K106 -> 37.9086 | L116: =(L60*$F$30*(1-$F$27-L$25))*L$23-L106 -> 37.9086 | M116: =(M60*$F$30*(1-$F$27-M$25))*M$23-M106 -> 37.9086 | N116: =(N60*$F$30*(1-$F$27-N$25))*N$23-N106 -> 37.9086 | O116: =(O60*$F$30*(1-$F$27-O$25))*O$23-O106 -> 41.889003 | P116: =(P60*$F$30*(1-$F$27-P$25))*P$23-P106 -> 41.889003 | Q116: =(Q60*$F$30*(1-$F$27-Q$25))*Q$23-Q106 -> 41.889003 | ... AG116: =(AG60*$F$30*(1-$F$27-AG$25))*AG$23-AG106 -> 46.077903 | AI116: =(AI60*$F$30*(1-$F$27-AI$25))*AI$23-AI106 -> 39.8686 | AJ116: =(AJ60*$F$30*(1-$F$27-AJ$25))*AJ$23-AJ106 -> 44.054803 | AK116: =(AK60*$F$30*(1-$F$27-AK$25))*AK$23-AK106 -> 48.460283 | AL116: =(AL60*$F$30*(1-$F$27-AL$25))*AL$23-AL106 -> 53.06401 | AM116: =(AM60*$F$30*(1-$F$27-AM$25))*AM$23-AM106 -> 57.839771 | AN116: =(AN60*$F$30*(1-$F$27-AN$25))*AN$23-AN106 -> 62.756152 | AO116: =(AO60*$F$30*(1-$F$27-AO$25))*AO$23-AO106 -> 67.776644 | AP116: =(AP60*$F$30*(1-$F$27-AP$25))*AP$23-AP106 -> 72.521009 | ... AT116: =(AT60*$F$30*(1-$F$27-AT$25))*AT$23-AT106 -> 90.260536
B117: 2 | C117: =C107 -> Ветеринар | D117: тыс. тенге / мес. | J117: =(J61*$F$30*(1-$F$27-J$25))*J$23-J107 -> 23.5539 | K117: =(K61*$F$30*(1-$F$27-K$25))*K$23-K107 -> 23.5539 | L117: =(L61*$F$30*(1-$F$27-L$25))*L$23-L107 -> 23.5539 | M117: =(M61*$F$30*(1-$F$27-M$25))*M$23-M107 -> 23.5539 | N117: =(N61*$F$30*(1-$F$27-N$25))*N$23-N107 -> 23.5539 | O117: =(O61*$F$30*(1-$F$27-O$25))*O$23-O107 -> 26.023752 | P117: =(P61*$F$30*(1-$F$27-P$25))*P$23-P107 -> 26.023752 | Q117: =(Q61*$F$30*(1-$F$27-Q$25))*Q$23-Q107 -> 26.023752 | ... AG117: =(AG61*$F$30*(1-$F$27-AG$25))*AG$23-AG107 -> 28.622977 | AI117: =(AI61*$F$30*(1-$F$27-AI$25))*AI$23-AI107 -> 23.5539 | AJ117: =(AJ61*$F$30*(1-$F$27-AJ$25))*AJ$23-AJ107 -> 26.023752 | AK117: =(AK61*$F$30*(1-$F$27-AK$25))*AK$23-AK107 -> 28.622977 | AL117: =(AL61*$F$30*(1-$F$27-AL$25))*AL$23-AL107 -> 31.339168 | AM117: =(AM61*$F$30*(1-$F$27-AM$25))*AM$23-AM107 -> 34.156858 | AN117: =(AN61*$F$30*(1-$F$27-AN$25))*AN$23-AN107 -> 37.057513 | AO117: =(AO61*$F$30*(1-$F$27-AO$25))*AO$23-AO107 -> 40.019594 | AP117: =(AP61*$F$30*(1-$F$27-AP$25))*AP$23-AP107 -> 42.818761 | ... AT117: =(AT61*$F$30*(1-$F$27-AT$25))*AT$23-AT107 -> 53.285049
B118: 3 | C118: =C108 -> Повар | D118: тыс. тенге / мес. | J118: =(J62*$F$30*(1-$F$27-J$25))*J$23-J108 -> 17.6733 | K118: =(K62*$F$30*(1-$F$27-K$25))*K$23-K108 -> 17.6733 | L118: =(L62*$F$30*(1-$F$27-L$25))*L$23-L108 -> 17.6733 | M118: =(M62*$F$30*(1-$F$27-M$25))*M$23-M108 -> 17.6733 | N118: =(N62*$F$30*(1-$F$27-N$25))*N$23-N108 -> 17.6733 | O118: =(O62*$F$30*(1-$F$27-O$25))*O$23-O108 -> 19.525689 | P118: =(P62*$F$30*(1-$F$27-P$25))*P$23-P108 -> 19.525689 | Q118: =(Q62*$F$30*(1-$F$27-Q$25))*Q$23-Q108 -> 19.525689 | ... AG118: =(AG62*$F$30*(1-$F$27-AG$25))*AG$23-AG108 -> 21.475108 | AI118: =(AI62*$F$30*(1-$F$27-AI$25))*AI$23-AI108 -> 17.6733 | AJ118: =(AJ62*$F$30*(1-$F$27-AJ$25))*AJ$23-AJ108 -> 19.525689 | AK118: =(AK62*$F$30*(1-$F$27-AK$25))*AK$23-AK108 -> 21.475108 | AL118: =(AL62*$F$30*(1-$F$27-AL$25))*AL$23-AL108 -> 23.512251 | AM118: =(AM62*$F$30*(1-$F$27-AM$25))*AM$23-AM108 -> 25.625518 | AN118: =(AN62*$F$30*(1-$F$27-AN$25))*AN$23-AN108 -> 27.80101 | AO118: =(AO62*$F$30*(1-$F$27-AO$25))*AO$23-AO108 -> 30.022571 | AP118: =(AP62*$F$30*(1-$F$27-AP$25))*AP$23-AP108 -> 32.121945 | ... AT118: =(AT62*$F$30*(1-$F$27-AT$25))*AT$23-AT108 -> 39.971662
B119: 4 | C119: =C109 -> Тракторист | D119: тыс. тенге / мес. | J119: =(J63*$F$30*(1-$F$27-J$25))*J$23-J109 -> 23.5539 | K119: =(K63*$F$30*(1-$F$27-K$25))*K$23-K109 -> 23.5539 | L119: =(L63*$F$30*(1-$F$27-L$25))*L$23-L109 -> 23.5539 | M119: =(M63*$F$30*(1-$F$27-M$25))*M$23-M109 -> 23.5539 | N119: =(N63*$F$30*(1-$F$27-N$25))*N$23-N109 -> 23.5539 | O119: =(O63*$F$30*(1-$F$27-O$25))*O$23-O109 -> 26.023752 | P119: =(P63*$F$30*(1-$F$27-P$25))*P$23-P109 -> 26.023752 | Q119: =(Q63*$F$30*(1-$F$27-Q$25))*Q$23-Q109 -> 26.023752 | ... AG119: =(AG63*$F$30*(1-$F$27-AG$25))*AG$23-AG109 -> 28.622977 | AI119: =(AI63*$F$30*(1-$F$27-AI$25))*AI$23-AI109 -> 23.5539 | AJ119: =(AJ63*$F$30*(1-$F$27-AJ$25))*AJ$23-AJ109 -> 26.023752 | AK119: =(AK63*$F$30*(1-$F$27-AK$25))*AK$23-AK109 -> 28.622977 | AL119: =(AL63*$F$30*(1-$F$27-AL$25))*AL$23-AL109 -> 31.339168 | AM119: =(AM63*$F$30*(1-$F$27-AM$25))*AM$23-AM109 -> 34.156858 | AN119: =(AN63*$F$30*(1-$F$27-AN$25))*AN$23-AN109 -> 37.057513 | AO119: =(AO63*$F$30*(1-$F$27-AO$25))*AO$23-AO109 -> 40.019594 | AP119: =(AP63*$F$30*(1-$F$27-AP$25))*AP$23-AP109 -> 42.818761 | ... AT119: =(AT63*$F$30*(1-$F$27-AT$25))*AT$23-AT109 -> 53.285049
B120: 5 | C120: =C110 -> Бухглатер | D120: тыс. тенге / мес. | J120: =(J64*$F$30*(1-$F$27-J$25))*J$23-J110 -> 17.6733 | K120: =(K64*$F$30*(1-$F$27-K$25))*K$23-K110 -> 17.6733 | L120: =(L64*$F$30*(1-$F$27-L$25))*L$23-L110 -> 17.6733 | M120: =(M64*$F$30*(1-$F$27-M$25))*M$23-M110 -> 17.6733 | N120: =(N64*$F$30*(1-$F$27-N$25))*N$23-N110 -> 17.6733 | O120: =(O64*$F$30*(1-$F$27-O$25))*O$23-O110 -> 19.525689 | P120: =(P64*$F$30*(1-$F$27-P$25))*P$23-P110 -> 19.525689 | Q120: =(Q64*$F$30*(1-$F$27-Q$25))*Q$23-Q110 -> 19.525689 | ... AG120: =(AG64*$F$30*(1-$F$27-AG$25))*AG$23-AG110 -> 21.475108 | AI120: =(AI64*$F$30*(1-$F$27-AI$25))*AI$23-AI110 -> 17.6733 | AJ120: =(AJ64*$F$30*(1-$F$27-AJ$25))*AJ$23-AJ110 -> 19.525689 | AK120: =(AK64*$F$30*(1-$F$27-AK$25))*AK$23-AK110 -> 21.475108 | AL120: =(AL64*$F$30*(1-$F$27-AL$25))*AL$23-AL110 -> 23.512251 | AM120: =(AM64*$F$30*(1-$F$27-AM$25))*AM$23-AM110 -> 25.625518 | AN120: =(AN64*$F$30*(1-$F$27-AN$25))*AN$23-AN110 -> 27.80101 | AO120: =(AO64*$F$30*(1-$F$27-AO$25))*AO$23-AO110 -> 30.022571 | AP120: =(AP64*$F$30*(1-$F$27-AP$25))*AP$23-AP110 -> 32.121945 | ... AT120: =(AT64*$F$30*(1-$F$27-AT$25))*AT$23-AT110 -> 39.971662
B123: ОСМС (удельники)
B125: Производственный персонал
B126: 1 | C126: =C116 -> Директор фермы | D126: тыс. тенге / мес. | J126: =MIN(J60*$F$30,J$19)*J$24 -> 21.78 | K126: =MIN(K60*$F$30,K$19)*K$24 -> 21.78 | L126: =MIN(L60*$F$30,L$19)*L$24 -> 21.78 | M126: =MIN(M60*$F$30,M$19)*M$24 -> 21.78 | N126: =MIN(N60*$F$30,N$19)*N$24 -> 21.78 | O126: =MIN(O60*$F$30,O$19)*O$24 -> 24.0669 | P126: =MIN(P60*$F$30,P$19)*P$24 -> 24.0669 | Q126: =MIN(Q60*$F$30,Q$19)*Q$24 -> 24.0669 | ... AG126: =MIN(AG60*$F$30,AG$19)*AG$24 -> 26.47359 | AI126: =MIN(AI60*$F$30,AI$19)*AI$24 -> 21.78 | AJ126: =MIN(AJ60*$F$30,AJ$19)*AJ$24 -> 24.0669 | AK126: =MIN(AK60*$F$30,AK$19)*AK$24 -> 26.47359 | AL126: =MIN(AL60*$F$30,AL$19)*AL$24 -> 28.988581 | AM126: =MIN(AM60*$F$30,AM$19)*AM$24 -> 31.597553 | AN126: =MIN(AN60*$F$30,AN$19)*AN$24 -> 34.283345 | AO126: =MIN(AO60*$F$30,AO$19)*AO$24 -> 37.026013 | AP126: =MIN(AP60*$F$30,AP$19)*AP$24 -> 39.617834 | ... AT126: =MIN(AT60*$F$30,AT$19)*AT$24 -> 49.308841
B127: 2 | C127: =C117 -> Ветеринар | D127: тыс. тенге / мес. | J127: =MIN(J61*$F$30,J$19)*J$24 -> 14.52 | K127: =MIN(K61*$F$30,K$19)*K$24 -> 14.52 | L127: =MIN(L61*$F$30,L$19)*L$24 -> 14.52 | M127: =MIN(M61*$F$30,M$19)*M$24 -> 14.52 | N127: =MIN(N61*$F$30,N$19)*N$24 -> 14.52 | O127: =MIN(O61*$F$30,O$19)*O$24 -> 16.0446 | P127: =MIN(P61*$F$30,P$19)*P$24 -> 16.0446 | Q127: =MIN(Q61*$F$30,Q$19)*Q$24 -> 16.0446 | ... AG127: =MIN(AG61*$F$30,AG$19)*AG$24 -> 17.64906 | AI127: =MIN(AI61*$F$30,AI$19)*AI$24 -> 14.52 | AJ127: =MIN(AJ61*$F$30,AJ$19)*AJ$24 -> 16.0446 | AK127: =MIN(AK61*$F$30,AK$19)*AK$24 -> 17.64906 | AL127: =MIN(AL61*$F$30,AL$19)*AL$24 -> 19.325721 | AM127: =MIN(AM61*$F$30,AM$19)*AM$24 -> 21.065036 | AN127: =MIN(AN61*$F$30,AN$19)*AN$24 -> 22.855564 | AO127: =MIN(AO61*$F$30,AO$19)*AO$24 -> 24.684009 | AP127: =MIN(AP61*$F$30,AP$19)*AP$24 -> 26.411889 | ... AT127: =MIN(AT61*$F$30,AT$19)*AT$24 -> 32.872561
B128: 3 | C128: =C118 -> Повар | D128: тыс. тенге / мес. | J128: =MIN(J62*$F$30,J$19)*J$24 -> 10.89 | K128: =MIN(K62*$F$30,K$19)*K$24 -> 10.89 | L128: =MIN(L62*$F$30,L$19)*L$24 -> 10.89 | M128: =MIN(M62*$F$30,M$19)*M$24 -> 10.89 | N128: =MIN(N62*$F$30,N$19)*N$24 -> 10.89 | O128: =MIN(O62*$F$30,O$19)*O$24 -> 12.03345 | P128: =MIN(P62*$F$30,P$19)*P$24 -> 12.03345 | Q128: =MIN(Q62*$F$30,Q$19)*Q$24 -> 12.03345 | ... AG128: =MIN(AG62*$F$30,AG$19)*AG$24 -> 13.236795 | AI128: =MIN(AI62*$F$30,AI$19)*AI$24 -> 10.89 | AJ128: =MIN(AJ62*$F$30,AJ$19)*AJ$24 -> 12.03345 | AK128: =MIN(AK62*$F$30,AK$19)*AK$24 -> 13.236795 | AL128: =MIN(AL62*$F$30,AL$19)*AL$24 -> 14.494291 | AM128: =MIN(AM62*$F$30,AM$19)*AM$24 -> 15.798777 | AN128: =MIN(AN62*$F$30,AN$19)*AN$24 -> 17.141673 | AO128: =MIN(AO62*$F$30,AO$19)*AO$24 -> 18.513007 | AP128: =MIN(AP62*$F$30,AP$19)*AP$24 -> 19.808917 | ... AT128: =MIN(AT62*$F$30,AT$19)*AT$24 -> 24.654421
B129: 4 | C129: =C119 -> Тракторист | D129: тыс. тенге / мес. | J129: =MIN(J63*$F$30,J$19)*J$24 -> 14.52 | K129: =MIN(K63*$F$30,K$19)*K$24 -> 14.52 | L129: =MIN(L63*$F$30,L$19)*L$24 -> 14.52 | M129: =MIN(M63*$F$30,M$19)*M$24 -> 14.52 | N129: =MIN(N63*$F$30,N$19)*N$24 -> 14.52 | O129: =MIN(O63*$F$30,O$19)*O$24 -> 16.0446 | P129: =MIN(P63*$F$30,P$19)*P$24 -> 16.0446 | Q129: =MIN(Q63*$F$30,Q$19)*Q$24 -> 16.0446 | ... AG129: =MIN(AG63*$F$30,AG$19)*AG$24 -> 17.64906 | AI129: =MIN(AI63*$F$30,AI$19)*AI$24 -> 14.52 | AJ129: =MIN(AJ63*$F$30,AJ$19)*AJ$24 -> 16.0446 | AK129: =MIN(AK63*$F$30,AK$19)*AK$24 -> 17.64906 | AL129: =MIN(AL63*$F$30,AL$19)*AL$24 -> 19.325721 | AM129: =MIN(AM63*$F$30,AM$19)*AM$24 -> 21.065036 | AN129: =MIN(AN63*$F$30,AN$19)*AN$24 -> 22.855564 | AO129: =MIN(AO63*$F$30,AO$19)*AO$24 -> 24.684009 | AP129: =MIN(AP63*$F$30,AP$19)*AP$24 -> 26.411889 | ... AT129: =MIN(AT63*$F$30,AT$19)*AT$24 -> 32.872561
B130: 5 | C130: =C120 -> Бухглатер | D130: тыс. тенге / мес. | J130: =MIN(J64*$F$30,J$19)*J$24 -> 10.89 | K130: =MIN(K64*$F$30,K$19)*K$24 -> 10.89 | L130: =MIN(L64*$F$30,L$19)*L$24 -> 10.89 | M130: =MIN(M64*$F$30,M$19)*M$24 -> 10.89 | N130: =MIN(N64*$F$30,N$19)*N$24 -> 10.89 | O130: =MIN(O64*$F$30,O$19)*O$24 -> 12.03345 | P130: =MIN(P64*$F$30,P$19)*P$24 -> 12.03345 | Q130: =MIN(Q64*$F$30,Q$19)*Q$24 -> 12.03345 | ... AG130: =MIN(AG64*$F$30,AG$19)*AG$24 -> 13.236795 | AI130: =MIN(AI64*$F$30,AI$19)*AI$24 -> 10.89 | AJ130: =MIN(AJ64*$F$30,AJ$19)*AJ$24 -> 12.03345 | AK130: =MIN(AK64*$F$30,AK$19)*AK$24 -> 13.236795 | AL130: =MIN(AL64*$F$30,AL$19)*AL$24 -> 14.494291 | AM130: =MIN(AM64*$F$30,AM$19)*AM$24 -> 15.798777 | AN130: =MIN(AN64*$F$30,AN$19)*AN$24 -> 17.141673 | AO130: =MIN(AO64*$F$30,AO$19)*AO$24 -> 18.513007 | AP130: =MIN(AP64*$F$30,AP$19)*AP$24 -> 19.808917 | ... AT130: =MIN(AT64*$F$30,AT$19)*AT$24 -> 24.654421
A133: x | B133: Взносы (расчет)
B135: Социальные отчисления
B137: Производственный персонал
B138: 1 | C138: =C126 -> Директор фермы | D138: тыс. тенге | J138: =J106*J46 -> 22.785 | K138: =K106*K46 -> 22.785 | L138: =L106*L46 -> 22.785 | M138: =M106*M46 -> 22.785 | N138: =N106*N46 -> 22.785 | O138: =O106*O46 -> 25.177425 | P138: =P106*P46 -> 25.177425 | Q138: =Q106*Q46 -> 25.177425 | ... AG138: =AG106*AG46 -> 27.695168 | AI138: =AI106*AI46*AI$10 -> 104.125 | AJ138: =AJ106*AJ46*AJ$10 -> 276.1395 | AK138: =AK106*AK46*AK$10 -> 303.75345 | AL138: =AL106*AL46*AL$10 -> 332.61003 | AM138: =AM106*AM46*AM$10 -> 362.54493 | AN138: =AN106*AN46*AN$10 -> 393.36125 | AO138: =AO106*AO46*AO$10 -> 424.83015 | AP138: =AP106*AP46*AP$10 -> 454.56826 | ... AT138: =AT106*AT46*AT$10 -> 565.76122
B139: 2 | C139: =C127 -> Ветеринар | D139: тыс. тенге | J139: =J107*J47 -> 8.45425 | K139: =K107*K47 -> 8.45425 | L139: =L107*L47 -> 8.45425 | M139: =M107*M47 -> 8.45425 | N139: =N107*N47 -> 8.45425 | O139: =O107*O47 -> 9.3436 | P139: =P107*P47 -> 9.3436 | Q139: =Q107*Q47 -> 9.3436 | ... AG139: =AG107*AG47 -> 10.279535 | AI139: =AI107*AI47*AI$10 -> 42.27125 | AJ139: =AJ107*AJ47*AJ$10 -> 112.1232 | AK139: =AK107*AK47*AK$10 -> 123.35442 | AL139: =AL107*AL47*AL$10 -> 135.09104 | AM139: =AM107*AM47*AM$10 -> 147.26625 | AN139: =AN107*AN47*AN$10 -> 159.79995 | AO139: =AO107*AO47*AO$10 -> 172.59906 | AP139: =AP107*AP47*AP$10 -> 184.69422 | ... AT139: =AT107*AT47*AT$10 -> 229.91893
B140: 3 | C140: =C128 -> Повар | D140: тыс. тенге | J140: =J108*J48 -> 6.33675 | K140: =K108*K48 -> 6.33675 | L140: =L108*L48 -> 6.33675 | M140: =M108*M48 -> 6.33675 | N140: =N108*N48 -> 6.33675 | O140: =O108*O48 -> 7.0037625 | P140: =P108*P48 -> 7.0037625 | Q140: =Q108*Q48 -> 7.0037625 | ... AG140: =AG108*AG48 -> 7.7057138 | AI140: =AI108*AI48*AI$10 -> 31.68375 | AJ140: =AJ108*AJ48*AJ$10 -> 84.04515 | AK140: =AK108*AK48*AK$10 -> 92.468565 | AL140: =AL108*AL48*AL$10 -> 101.27103 | AM140: =AM108*AM48*AM$10 -> 110.40244 | AN140: =AN108*AN48*AN$10 -> 119.80271 | AO140: =AO108*AO48*AO$10 -> 129.40205 | AP140: =AP108*AP48*AP$10 -> 138.47342 | ... AT140: =AT108*AT48*AT$10 -> 172.39194
B141: 4 | C141: =C129 -> Тракторист | D141: тыс. тенге | J141: =J109*J49 -> 16.9085 | K141: =K109*K49 -> 16.9085 | L141: =L109*L49 -> 16.9085 | M141: =M109*M49 -> 16.9085 | N141: =N109*N49 -> 16.9085 | O141: =O109*O49 -> 18.6872 | P141: =P109*P49 -> 18.6872 | Q141: =Q109*Q49 -> 18.6872 | ... AG141: =AG109*AG49 -> 20.55907 | AI141: =AI109*AI49*AI$10 -> 84.5425 | AJ141: =AJ109*AJ49*AJ$10 -> 224.2464 | AK141: =AK109*AK49*AK$10 -> 246.70884 | AL141: =AL109*AL49*AL$10 -> 270.18209 | AM141: =AM109*AM49*AM$10 -> 294.5325 | AN141: =AN109*AN49*AN$10 -> 319.59989 | AO141: =AO109*AO49*AO$10 -> 345.19812 | AP141: =AP109*AP49*AP$10 -> 369.38845 | ... AT141: =AT109*AT49*AT$10 -> 459.83785
...

Sheet CAPEX
B2: Смета капитальных расходов
A4: Код | B4: Общая стоимость капитальных затрат основной фермы | C4: Вкл. | D4: Норма м²/гол | E4: Расчётн. площ.
A5: FAC-015 | B5: Навес для техники-500м2 | C5: 1 | D5: 1.6667 | E5: =ROUND(D5*$F$87,0) -> 500 | F5: 19500 | H5: =C5*E5*F5 -> 9750000
A6: INF | B6: Жилой дом | C6: 1 | H6: =C6*30000000 -> 30000000
A7: INF | B7: Резервуар для питьевой воды-2м3 | C7: 1 | H7: =C7*1000000 -> 1000000
A8: INF | B8: Скважина | C8: 1 | H8: =C8*15000000 -> 15000000
A9: FAC-014 | B9: Автовесы | C9: 1 | H9: =C9*1500000 -> 1500000
A10: FAC-019 | B10: КПП с санпропускником-50м2 | C10: 1 | D10: 0.1667 | E10: =ROUND(D10*$F$87,0) -> 50 | F10: 40000 | H10: =C10*E10*F10 -> 2000000
A11: INF | B11: Наружные сети электроснабжения-10 Кв | C11: 1 | H11: =C11*11185000 -> 11185000
A12: INF | B12: Скотомогильник | C12: 1 | H12: =C12*4000000 -> 4000000
A13: FAC-015 | B13: Зернохранилище 2000м2 | C13: 1 | D13: 6.6667 | E13: =ROUND(D13*$F$87,0) -> 2000 | F13: 9000 | H13: =C13*E13*F13 -> 18000000
A14: INF | B14: Трап для погрузки КРС-марка ТТ-1С | C14: 1 | H14: =C14*500000 -> 500000
A15: FAC-012 | B15: Крытое помещение для ветрообработки КРС-200м2 | C15: 1 | D15: 0.6667 | E15: =ROUND(D15*$F$87,0) -> 200 | F15: 80000 | H15: =C15*E15*F15 -> 16000000
A16: FAC-014 | B16: Раскол-деление на 20голов КРС | C16: 1 | D16: 980000 | E16: 1 | H16: =C16*E16*D16 -> 980000
A17: FAC-008 | B17: Накопитель на 300 голов КРС | C17: 1 | D17: 4000 | E17: =$F$87 -> 300 | H17: =C17*E17*D17 -> 1200000
A18: FAC-015 | B18: Открытая площадка для хранения сена-40 000 рулонов сена | C18: 1 | D18: 5000 | E18: =$F$87 -> 300 | H18: =C18*E18*D18 -> 1500000
A19: FAC-001 | B19: Общий ангар на 300 голов, норма 8м2 на 1 голову | C19: =IF(Input!F64="Зимний",1,0) -> 1 | D19: =_xlfn.XLOOKUP(A19,Справочник!$A$7:$A$26,Справочник!$G$7:$G$26,D19) -> 8 | E19: =D19*$F$87 -> 2400 | F19: 12500 | H19: =C19*E19*F19 -> 30000000
A20: FAC-013 | B20: Изолятор на 15 голов, норма -8м2 на 1 голову (ветпункт 12х16м) | C20: 1 | D20: =_xlfn.XLOOKUP(A20,Справочник!$A$7:$A$26,Справочник!$G$7:$G$26,D20) -> 8 | E20: =D20*ROUNDUP($F$87*0.05,0) -> 120 | F20: 83333 | H20: =C20*E20*F20 -> 9999960
A21: FAC-009 | B21: Открытый загон для изолятора, норма-20м2 на корову с теленком | C21: 1 | D21: =_xlfn.XLOOKUP(A21,Справочник!$A$7:$A$26,Справочник!$G$7:$G$26,D21) -> 20 | E21: =D21*ROUNDUP($F$87*0.05,0) -> 300 | F21: 3450 | H21: =C21*E21*F21 -> 1035000
A22: PAD-001 | B22: Загон для 30 коров КРС , норма 20м2 на 1 голову | C22: 1 | D22: =_xlfn.XLOOKUP(A22,Справочник!$A$30:$A$37,Справочник!$D$30:$D$37,D22) -> 20 | E22: =D22*ROUNDUP($F$87*0.1,0) -> 600 | F22: 4140 | H22: =C22*E22*F22 -> 2484000
A23: PAD-007 | B23: Загон для быков -производителей, норма 25м2 на 1 голову | C23: 1 | D23: =_xlfn.XLOOKUP(A23,Справочник!$A$30:$A$37,Справочник!$D$30:$D$37,D23) -> 25 | E23: =D23*ROUNDUP($F$87/15,0) -> 500 | F23: 4968 | H23: =C23*E23*F23 -> 2484000
A24: INF | B24: Ветрозащита 20-30метров | C24: 1 | D24: 8280 | E24: =$F$87 -> 300 | H24: =C24*E24*D24 -> 2484000
A25: INF | B25: Кормовой стол, норома 0,5м2 на 1 голову | C25: 1 | D25: 0.5 | E25: =D25*$F$87 -> 150 | F25: 6900 | H25: =C25*E25*F25 -> 1035000
A26: FAC-017 | B26: Теплая поилка, 4 попловка, для быков 2 попловка | C26: =IF(Input!F64="Зимний",1,0) -> 1 | D26: 4830 | E26: =$F$87 -> 300 | H26: =C26*E26*D26 -> 1449000
B27: Расходы на работы | F27: 0.06 | H27: =SUM(H5:H26)*$F27 -> 9815157.6
B28: Непредвиденные расходы | F28: 0.025 | H28: =SUM(H5:H27)*$F28 -> 4335027.9
B29: Промежуточный итог: | H29: =SUM(H5:H28) -> 1.7773615e+08
B31: Пастбища
B32: Автономный мобильный жилой дом/вагончик | F32: 1 | G32: 4000000 | H32: 4000000
B33: Поилки от скважин с ветренными насосами | F33: 2 | G33: 8800000 | H33: =$F33*$G33 -> 17600000
B34: Скважина | F34: 1 | G34: 3000000 | H34: =$F34*$G34 -> 3000000
B35: Ограждение пастбищ | F35: 1 | G35: 18800000 | H35: =$F35*$G35 -> 18800000
B36: Расходы на строительство/работы | F36: 0.06 | H36: =SUM(H32:H35)*$F36 -> 2604000
B37: Непредвиденные расходы | F37: 0.025 | H37: =SUM(H32:H35)*$F37 -> 1085000
B38: Промежуточный итог: | H38: =SUM(H32:H37) -> 47089000
B40: Техника
B41: Колесный трактор 100–150 л.с. (дежурный) | F41: 1 | G41: 20000000 | H41: =$F41*$G41 -> 20000000
B42: Кун с ковшом и стогометом | F42: 1 | G42: 3500000 | H42: =$F42*$G42 -> 3500000
B43: Кормораздатчик (миксер-кормораздатчик) 8–12 м³ | F43: 1 | G43: 10000000 | H43: =$F43*$G43 -> 10000000
B44: Зернодробилка | F44: 1 | G44: 3000000 | H44: =$F44*$G44 -> 3000000
B45: Прицеп самосвальный 10-15 т | F45: 1 | G45: 10000000 | H45: =$F45*$G45 -> 10000000
B46: Прицеп для перевозки скота | F46: 1 | G46: 5000000 | H46: =$F46*$G46 -> 5000000
B47: Прицеп с емкостью для воды | F47: 1 | G47: 1500000 | H47: =$F47*$G47 -> 1500000
B48: Бензиновые генераторы на 3-5 квт | F48: 1 | G48: 400000 | H48: =$F48*$G48 -> 400000
B49: Промежуточный итог: | H49: =SUM(H41:H48) -> 53400000
B51: Инструменты и оборудовние
B52: Считыватель чипов | F52: 1 | G52: 50000 | H52: =$F52*$G52 -> 50000
B53: Электрический погонщик | F53: 1 | G53: 30000 | H53: =$F53*$G53 -> 30000
B54: Станок для фиксации КРС | F54: 1 | G54: 2000000 | H54: =$F54*$G54 -> 2000000
B55: Электронные весы | F55: 1 | G55: 150000 | H55: =$F55*$G55 -> 150000
B56: Вакцинаторы | F56: 5 | G56: 35000 | H56: =$F56*$G56 -> 175000
B57: Дренчер | F57: 1 | G57: 10000 | H57: =$F57*$G57 -> 10000
B58: Копытные ножи | F58: 2 | G58: 15000 | H58: =$F58*$G58 -> 30000
B59: Молокоотсос | F59: 2 | G59: 60000 | H59: =$F59*$G59 -> 120000
B60: Поилки для молока | F60: 20 | G60: 5000 | H60: =$F60*$G60 -> 100000
B61: Термо Чемодан | F61: 1 | G61: 50000 | H61: =$F61*$G61 -> 50000
B62: Огнетушитель | F62: 5 | G62: 15000 | H62: =$F62*$G62 -> 75000
B63: Набор лопат и вил | F63: 5 | G63: 30000 | H63: =$F63*$G63 -> 150000
... B70: Спутниковые антенны | F70: 1 | G70: 350000 | H70: =$F70*$G70 -> 350000
B71: Промежуточный итог: | H71: =SUM(H52:H70) -> 4240000
B73: Всего Общая Инфраструктура | H73: =SUM(H71,H49,H38,H29) -> 2.8246515e+08
B76: Справочник материалов / типов строительства
B78: Материал / тип исполнения | F78: Стоимость 1 м², тенге
B79: Лёгкий каркас | F79: =_xlfn.XLOOKUP(B79,Справочник!B41:B47,Справочник!D41:D47,0)*1000 -> 15000
B80: Сэндвич-панель | F80: =_xlfn.XLOOKUP(B80,Справочник!B41:B47,Справочник!D41:D47,0)*1000 -> 25000
B81: Металлоконструкция | F81: =_xlfn.XLOOKUP(B81,Справочник!B41:B47,Справочник!D41:D47,0)*1000 -> 35000
B82: Кирпич / капитальное | F82: =_xlfn.XLOOKUP(B82,Справочник!B41:B47,Справочник!D41:D47,0)*1000 -> 50000
B84: Выбранная цена м² (закрытые) | F84: =VLOOKUP(Input!F65,B79:F82,5,FALSE) -> 25000
B85: Выбранная цена м² (вспомог.) | F85: =VLOOKUP(Input!F66,B79:F82,5,FALSE) -> 15000
B87: Мощность репродуктора | F87: =Input!F63 -> 300 | G87: голов

Sheet OPEX 
B2: Статья | C2: Описание | D2: Кол-во | E2: Цена | F2: Итого
B3: Инструменты и расходники
A4: 28 | B4: RFID-чипы | C4: 1 на голову | D4: 1 | E4: 500 | F4: =D4*E4 -> 500
A5: 29 | B5: Считыватель чипов | C5: единицы | D5: 2 | E5: 700000 | F5: =D5*E5 -> 1400000
A6: 30 | B6: Ушные бирки | C6: 1 на голову | D6: 1 | E6: 500 | F6: =D6*E6 -> 500
A7: 31 | B7: Электрический погонщик | C7: Hot-Shot | D7: 2 | E7: 30000 | F7: =D7*E7 -> 60000
A8: 32 | B8: Набор для холодного таврирования | C8: Kerbl | D8: 1 | E8: 185000 | F8: =D8*E8 -> 185000
A9: 33 | B9: Станок для фиксации КРС | C9: Priefert либо можно отечественного произовдства, что намного дешевле | D9: 2 | E9: 850000 | F9: =D9*E9 -> 1700000
A10: 34 | B10: Электронные весы | C10: Tru-Test | D10: 1 | E10: 500000 | F10: =D10*E10 -> 500000
A11: 35 | B11: Вакцинаторы | C11: Simcro | D11: 5 | E11: 10000 | F11: =D11*E11 -> 50000
A12: 36 | B12: Дренчер | C12: Allflex | D12: 2 | E12: 8000 | F12: =D12*E12 -> 16000
A13: 37 | B13: Копытные ножи | C13: Victorinox | D13: 2 | E13: 4000 | F13: =D13*E13 -> 8000
A14: 38 | B14: Реаниматор для телят | C14: Agri-Plastics | D14: 2 | E14: 165000 | F14: =D14*E14 -> 330000
A15: 39 | B15: Хирургический набор | C15: Stille | D15: 2 | E15: 130000 | F15: =D15*E15 -> 260000
... A17: 41 | B17: Поилки для молока | C17: 20 единиц, Kerbl | D17: 20 | E17: 3000 | F17: =D17*E17 -> 60000
A18: 42 | B18: Родовспомогатель | D18: 1 | E18: 150000 | F18: =D18*E18 -> 150000
A19: 43 | B19: Термо Чемодан | D19: 1 | E19: 50000 | F19: =D19*E19 -> 50000
B20: Промежуточный итог: | F20: =SUM(F4:F19) -> 4820000
B21: Прочие расходы УК | F21: =D21*E21 -> 0
B22: Связь | F22: ='OPEX '!$H22*12 -> 960000 | H22: 80000
B23: Продукты питания | F23: ='OPEX '!$H23*12 -> 12000000 | H23: 1000000
B24: Вода | F24: ='OPEX '!$H24*12 -> 0 | H24: 0
B25: Аптека | F25: =H25*12 -> 600000 | H25: 50000
B26: Электроэнергия | F26: =H26*12 -> 1800000 | H26: 150000
A27: 44 | B27: Дизтопливо (тракторы+ген.+погрузчик) | C27: ~25 000 л / в год | D27: 25000 | E27: 250 | F27: =D27*E27 -> 6250000 | H27: =SUBTOTAL(109,Table_2[[#All],[Column1]]) -> 1280000
B28: Жидкий азот | C28: 2100 литров в год | D28: 600 | E28: 2100 | F28: =D28*E28 -> 1260000
A29: 45 | B29: Бензин (пикапы, мотоциклы) | C29: ~4 500 л / в год | D29: 4500 | E29: 230 | F29: =D29*E29 -> 1035000
